Workbook

Sheet README
A1: JOPACC Payment Systems Monthly Report — Consolidated Dataset
A3: Source: extracted data from JOPACC monthly Payment Systems Report PDFs (Sep 2024 – Aug 2026).
A5: Sheets in this workbook:
A6: • CliQ - instant/person-to-person payments (users + transactions)
A7: • JoMoPay - mobile wallet payments (users + transactions)
A8: • eFAWATEERcom - bill payment platform (users + transactions by biller)
A9: • ACH - Automated Clearing House (JOD + foreign-currency transactions)
A10: • ECCU - Electronic Cheque Clearing Unit (cheques + returned cheques)
A11: • Interoperability - cross-system / cross-institution money-transfer flows
A12: • Instant Payments - bank-account vs mobile-wallet instant payment channel (partial history)
A13: • Summary - monthly headline totals (users, transactions) side-by-side across systems
A15: Layout:
... A39: • Cells that were blank in the original stay blank (no formula), so a month with no source data is not shown as 0.

Sheet CliQ
A1: CliQ (Instant Payments)
A2: Raw Data keys → (system | period) | B2: cliq | C2: =RIGHT(C$3,4)&"-"&TEXT(MATCH(LEFT(C$3,3),{"Jan","Feb","Mar","Apr","May","Jun","Jul","Aug","Sep","Oct","Nov","Dec"},0),"00") -> 2024-09 | D2: =RIGHT(D$3,4)&"-"&TEXT(MATCH(LEFT(D$3,3),{"Jan","Feb","Mar","Apr","May","Jun","Jul","Aug","Sep","Oct","Nov","Dec"},0),"00") -> 2024-10 | E2: =RIGHT(E$3,4)&"-"&TEXT(MATCH(LEFT($E3,3),{"Jan","Feb","Mar","Apr","May","Jun","Jul","Aug","Sep","Oct","Nov","Dec"},0),"00") -> 2024-11 | F2: =RIGHT(F$3,4)&"-"&TEXT(MATCH(LEFT(F$3,3),{"Jan","Feb","Mar","Apr","May","Jun","Jul","Aug","Sep","Oct","Nov","Dec"},0),"00") -> 2024-12 | G2: =RIGHT(G$3,4)&"-"&TEXT(MATCH(LEFT(G$3,3),{"Jan","Feb","Mar","Apr","May","Jun","Jul","Aug","Sep","Oct","Nov","Dec"},0),"00") -> 2025-01 | H2: =RIGHT(H$3,4)&"-"&TEXT(MATCH(LEFT(H$3,3),{"Jan","Feb","Mar","Apr","May","Jun","Jul","Aug","Sep","Oct","Nov","Dec"},0),"00") -> 2025-02 | I2: =RIGHT(I$3,4)&"-"&TEXT(MATCH(LEFT(I$3,3),{"Jan","Feb","Mar","Apr","May","Jun","Jul","Aug","Sep","Oct","Nov","Dec"},0),"00") -> 2025-03 | J2: =RIGHT(J$3,4)&"-"&TEXT(MATCH(LEFT(J$3,3),{"Jan","Feb","Mar","Apr","May","Jun","Jul","Aug","Sep","Oct","Nov","Dec"},0),"00") -> 2025-04 | K2: =RIGHT(K$3,4)&"-"&TEXT(MATCH(LEFT(K$3,3),{"Jan","Feb","Mar","Apr","May","Jun","Jul","Aug","Sep","Oct","Nov","Dec"},0),"00") -> 2025-05 | L2: =RIGHT(L$3,4)&"-"&TEXT(MATCH(LEFT(L$3,3),{"Jan","Feb","Mar","Apr","May","Jun","Jul","Aug","Sep","Oct","Nov","Dec"},0),"00") -> 2025-06 | M2: =RIGHT(M$3,4)&"-"&TEXT(MATCH(LEFT(M$3,3),{"Jan","Feb","Mar","Apr","May","Jun","Jul","Aug","Sep","Oct","Nov","Dec"},0),"00") -> 2025-07 | ... Z2: =RIGHT(Z$3,4)&"-"&TEXT(MATCH(LEFT(Z$3,3),{"Jan","Feb","Mar","Apr","May","Jun","Jul","Aug","Sep","Oct","Nov","Dec"},0),"00") -> 2026-08
A3: Category | B3: Metric | C3: Sep 2024 | D3: Oct 2024 | E3: Nov 2024 | F3: Dec 2024 | G3: Jan 2025 | H3: Feb 2025 | I3: Mar 2025 | J3: Apr 2025 | K3: May 2025 | L3: Jun 2025 | M3: Jul 2025 | N3: Aug 2025 | O3: Sep 2025 | P3: Oct 2025 | Q3: Nov 2025 | R3: Dec 2025 | S3: Jan 2026 | T3: Feb 2026 | U3: Mar 2026 | V3: Apr 2026 | W3: May 2026 | X3: Jun 2026 | Y3: Jul 2026 | Z3: Aug 2026
A4: USERS BY NATIONALITY (Number)
A5: Users | B5: Jordanian | C5: =SUMIFS('Raw Data'!$L:$L,'Raw Data'!$B:$B,$B$2,'Raw Data'!$J:$J,C$2,'Raw Data'!$K:$K,"native",'Raw Data'!$H:$H,"Jordanian",'Raw Data'!$I:$I,"",'Raw Data'!$M:$M,"count") -> 1500000 | D5: =SUMIFS('Raw Data'!$L:$L,'Raw Data'!$B:$B,$B$2,'Raw Data'!$J:$J,D$2,'Raw Data'!$K:$K,"native",'Raw Data'!$H:$H,"Jordanian",'Raw Data'!$I:$I,"",'Raw Data'!$M:$M,"count") -> 1540000 | E5: =SUMIFS('Raw Data'!$L:$L,'Raw Data'!$B:$B,$B$2,'Raw Data'!$J:$J,E$2,'Raw Data'!$K:$K,"native",'Raw Data'!$H:$H,"Jordanian",'Raw Data'!$I:$I,"",'Raw Data'!$M:$M,"count") -> 1570000 | F5: =SUMIFS('Raw Data'!$L:$L,'Raw Data'!$B:$B,$B$2,'Raw Data'!$J:$J,F$2,'Raw Data'!$K:$K,"native",'Raw Data'!$H:$H,"Jordanian",'Raw Data'!$I:$I,"",'Raw Data'!$M:$M,"count") -> 1610000 | G5: =SUMIFS('Raw Data'!$L:$L,'Raw Data'!$B:$B,$B$2,'Raw Data'!$J:$J,G$2,'Raw Data'!$K:$K,"native",'Raw Data'!$H:$H,"Jordanian",'Raw Data'!$I:$I,"",'Raw Data'!$M:$M,"count") -> 1640000 | H5: =SUMIFS('Raw Data'!$L:$L,'Raw Data'!$B:$B,$B$2,'Raw Data'!$J:$J,H$2,'Raw Data'!$K:$K,"native",'Raw Data'!$H:$H,"Jordanian",'Raw Data'!$I:$I,"",'Raw Data'!$M:$M,"count") -> 1680000 | I5: =SUMIFS('Raw Data'!$L:$L,'Raw Data'!$B:$B,$B$2,'Raw Data'!$J:$J,I$2,'Raw Data'!$K:$K,"native",'Raw Data'!$H:$H,"Jordanian",'Raw Data'!$I:$I,"",'Raw Data'!$M:$M,"count") -> 1710000 | J5: =SUMIFS('Raw Data'!$L:$L,'Raw Data'!$B:$B,$B$2,'Raw Data'!$J:$J,J$2,'Raw Data'!$K:$K,"native",'Raw Data'!$H:$H,"Jordanian",'Raw Data'!$I:$I,"",'Raw Data'!$M:$M,"count") -> 1750000 | ... Z5: =SUMIFS('Raw Data'!$L:$L,'Raw Data'!$B:$B,$B$2,'Raw Data'!$J:$J,Z$2,'Raw Data'!$K:$K,"native",'Raw Data'!$H:$H,"Jordanian",'Raw Data'!$I:$I,"",'Raw Data'!$M:$M,"count") -> 2290000
A6: Users | B6: Non-Jordanian | C6: =SUMIFS('Raw Data'!$L:$L,'Raw Data'!$B:$B,$B$2,'Raw Data'!$J:$J,C$2,'Raw Data'!$K:$K,"native",'Raw Data'!$H:$H,"Non-Jordanian",'Raw Data'!$I:$I,"",'Raw Data'!$M:$M,"count") -> 55000 | D6: =SUMIFS('Raw Data'!$L:$L,'Raw Data'!$B:$B,$B$2,'Raw Data'!$J:$J,D$2,'Raw Data'!$K:$K,"native",'Raw Data'!$H:$H,"Non-Jordanian",'Raw Data'!$I:$I,"",'Raw Data'!$M:$M,"count") -> 57000 | E6: =SUMIFS('Raw Data'!$L:$L,'Raw Data'!$B:$B,$B$2,'Raw Data'!$J:$J,E$2,'Raw Data'!$K:$K,"native",'Raw Data'!$H:$H,"Non-Jordanian",'Raw Data'!$I:$I,"",'Raw Data'!$M:$M,"count") -> 59000 | F6: =SUMIFS('Raw Data'!$L:$L,'Raw Data'!$B:$B,$B$2,'Raw Data'!$J:$J,F$2,'Raw Data'!$K:$K,"native",'Raw Data'!$H:$H,"Non-Jordanian",'Raw Data'!$I:$I,"",'Raw Data'!$M:$M,"count") -> 61000 | G6: =SUMIFS('Raw Data'!$L:$L,'Raw Data'!$B:$B,$B$2,'Raw Data'!$J:$J,G$2,'Raw Data'!$K:$K,"native",'Raw Data'!$H:$H,"Non-Jordanian",'Raw Data'!$I:$I,"",'Raw Data'!$M:$M,"count") -> 63000 | H6: =SUMIFS('Raw Data'!$L:$L,'Raw Data'!$B:$B,$B$2,'Raw Data'!$J:$J,H$2,'Raw Data'!$K:$K,"native",'Raw Data'!$H:$H,"Non-Jordanian",'Raw Data'!$I:$I,"",'Raw Data'!$M:$M,"count") -> 65000 | I6: =SUMIFS('Raw Data'!$L:$L,'Raw Data'!$B:$B,$B$2,'Raw Data'!$J:$J,I$2,'Raw Data'!$K:$K,"native",'Raw Data'!$H:$H,"Non-Jordanian",'Raw Data'!$I:$I,"",'Raw Data'!$M:$M,"count") -> 67000 | J6: =SUMIFS('Raw Data'!$L:$L,'Raw Data'!$B:$B,$B$2,'Raw Data'!$J:$J,J$2,'Raw Data'!$K:$K,"native",'Raw Data'!$H:$H,"Non-Jordanian",'Raw Data'!$I:$I,"",'Raw Data'!$M:$M,"count") -> 68300 | ... Z6: =SUMIFS('Raw Data'!$L:$L,'Raw Data'!$B:$B,$B$2,'Raw Data'!$J:$J,Z$2,'Raw Data'!$K:$K,"native",'Raw Data'!$H:$H,"Non-Jordanian",'Raw Data'!$I:$I,"",'Raw Data'!$M:$M,"count") -> 98600
A7: USERS BY GENDER (Number)
A8: Users | B8: Female Users | C8: =SUMIFS('Raw Data'!$L:$L,'Raw Data'!$B:$B,$B$2,'Raw Data'!$J:$J,C$2,'Raw Data'!$K:$K,"native",'Raw Data'!$H:$H,"Female*",'Raw Data'!$I:$I,"",'Raw Data'!$M:$M,"count") -> 541300 | D8: =SUMIFS('Raw Data'!$L:$L,'Raw Data'!$B:$B,$B$2,'Raw Data'!$J:$J,D$2,'Raw Data'!$K:$K,"native",'Raw Data'!$H:$H,"Female*",'Raw Data'!$I:$I,"",'Raw Data'!$M:$M,"count") -> 556500 | E8: =SUMIFS('Raw Data'!$L:$L,'Raw Data'!$B:$B,$B$2,'Raw Data'!$J:$J,E$2,'Raw Data'!$K:$K,"native",'Raw Data'!$H:$H,"Female*",'Raw Data'!$I:$I,"",'Raw Data'!$M:$M,"count") -> 570000 | F8: =SUMIFS('Raw Data'!$L:$L,'Raw Data'!$B:$B,$B$2,'Raw Data'!$J:$J,F$2,'Raw Data'!$K:$K,"native",'Raw Data'!$H:$H,"Female*",'Raw Data'!$I:$I,"",'Raw Data'!$M:$M,"count") -> 580000 | G8: =SUMIFS('Raw Data'!$L:$L,'Raw Data'!$B:$B,$B$2,'Raw Data'!$J:$J,G$2,'Raw Data'!$K:$K,"native",'Raw Data'!$H:$H,"Female*",'Raw Data'!$I:$I,"",'Raw Data'!$M:$M,"count") -> 600000 | H8: =SUMIFS('Raw Data'!$L:$L,'Raw Data'!$B:$B,$B$2,'Raw Data'!$J:$J,H$2,'Raw Data'!$K:$K,"native",'Raw Data'!$H:$H,"Female*",'Raw Data'!$I:$I,"",'Raw Data'!$M:$M,"count") -> 610000 | I8: =SUMIFS('Raw Data'!$L:$L,'Raw Data'!$B:$B,$B$2,'Raw Data'!$J:$J,I$2,'Raw Data'!$K:$K,"native",'Raw Data'!$H:$H,"Female*",'Raw Data'!$I:$I,"",'Raw Data'!$M:$M,"count") -> 620000 | J8: =SUMIFS('Raw Data'!$L:$L,'Raw Data'!$B:$B,$B$2,'Raw Data'!$J:$J,J$2,'Raw Data'!$K:$K,"native",'Raw Data'!$H:$H,"Female*",'Raw Data'!$I:$I,"",'Raw Data'!$M:$M,"count") -> 640000 | ... Z8: =SUMIFS('Raw Data'!$L:$L,'Raw Data'!$B:$B,$B$2,'Raw Data'!$J:$J,Z$2,'Raw Data'!$K:$K,"native",'Raw Data'!$H:$H,"Female*",'Raw Data'!$I:$I,"",'Raw Data'!$M:$M,"count") -> 870000
A9: Users | B9: Male Users | C9: =SUMIFS('Raw Data'!$L:$L,'Raw Data'!$B:$B,$B$2,'Raw Data'!$J:$J,C$2,'Raw Data'!$K:$K,"native",'Raw Data'!$H:$H,"Male*",'Raw Data'!$I:$I,"",'Raw Data'!$M:$M,"count") -> 973400 | D9: =SUMIFS('Raw Data'!$L:$L,'Raw Data'!$B:$B,$B$2,'Raw Data'!$J:$J,D$2,'Raw Data'!$K:$K,"native",'Raw Data'!$H:$H,"Male*",'Raw Data'!$I:$I,"",'Raw Data'!$M:$M,"count") -> 997400 | E9: =SUMIFS('Raw Data'!$L:$L,'Raw Data'!$B:$B,$B$2,'Raw Data'!$J:$J,E$2,'Raw Data'!$K:$K,"native",'Raw Data'!$H:$H,"Male*",'Raw Data'!$I:$I,"",'Raw Data'!$M:$M,"count") -> 1020000 | F9: =SUMIFS('Raw Data'!$L:$L,'Raw Data'!$B:$B,$B$2,'Raw Data'!$J:$J,F$2,'Raw Data'!$K:$K,"native",'Raw Data'!$H:$H,"Male*",'Raw Data'!$I:$I,"",'Raw Data'!$M:$M,"count") -> 1040000 | G9: =SUMIFS('Raw Data'!$L:$L,'Raw Data'!$B:$B,$B$2,'Raw Data'!$J:$J,G$2,'Raw Data'!$K:$K,"native",'Raw Data'!$H:$H,"Male*",'Raw Data'!$I:$I,"",'Raw Data'!$M:$M,"count") -> 1060000 | H9: =SUMIFS('Raw Data'!$L:$L,'Raw Data'!$B:$B,$B$2,'Raw Data'!$J:$J,H$2,'Raw Data'!$K:$K,"native",'Raw Data'!$H:$H,"Male*",'Raw Data'!$I:$I,"",'Raw Data'!$M:$M,"count") -> 1080000 | I9: =SUMIFS('Raw Data'!$L:$L,'Raw Data'!$B:$B,$B$2,'Raw Data'!$J:$J,I$2,'Raw Data'!$K:$K,"native",'Raw Data'!$H:$H,"Male*",'Raw Data'!$I:$I,"",'Raw Data'!$M:$M,"count") -> 1110000 | J9: =SUMIFS('Raw Data'!$L:$L,'Raw Data'!$B:$B,$B$2,'Raw Data'!$J:$J,J$2,'Raw Data'!$K:$K,"native",'Raw Data'!$H:$H,"Male*",'Raw Data'!$I:$I,"",'Raw Data'!$M:$M,"count") -> 1130000 | ... Z9: =SUMIFS('Raw Data'!$L:$L,'Raw Data'!$B:$B,$B$2,'Raw Data'!$J:$J,Z$2,'Raw Data'!$K:$K,"native",'Raw Data'!$H:$H,"Male*",'Raw Data'!$I:$I,"",'Raw Data'!$M:$M,"count") -> 1450000
A10: USERS BY AGE BRACKET (Number)
A11: Users | B11: 18-30 | C11: =SUMIFS('Raw Data'!$L:$L,'Raw Data'!$B:$B,$B$2,'Raw Data'!$J:$J,C$2,'Raw Data'!$K:$K,"native",'Raw Data'!$H:$H,"18-30",'Raw Data'!$I:$I,"",'Raw Data'!$M:$M,"count") -> 591000 | D11: =SUMIFS('Raw Data'!$L:$L,'Raw Data'!$B:$B,$B$2,'Raw Data'!$J:$J,D$2,'Raw Data'!$K:$K,"native",'Raw Data'!$H:$H,"18-30",'Raw Data'!$I:$I,"",'Raw Data'!$M:$M,"count") -> 605000 | E11: =SUMIFS('Raw Data'!$L:$L,'Raw Data'!$B:$B,$B$2,'Raw Data'!$J:$J,E$2,'Raw Data'!$K:$K,"native",'Raw Data'!$H:$H,"18-30",'Raw Data'!$I:$I,"",'Raw Data'!$M:$M,"count") -> 615000 | F11: =SUMIFS('Raw Data'!$L:$L,'Raw Data'!$B:$B,$B$2,'Raw Data'!$J:$J,F$2,'Raw Data'!$K:$K,"native",'Raw Data'!$H:$H,"18-30",'Raw Data'!$I:$I,"",'Raw Data'!$M:$M,"count") -> 626000 | G11: =SUMIFS('Raw Data'!$L:$L,'Raw Data'!$B:$B,$B$2,'Raw Data'!$J:$J,G$2,'Raw Data'!$K:$K,"native",'Raw Data'!$H:$H,"18-30",'Raw Data'!$I:$I,"",'Raw Data'!$M:$M,"count") -> 637000 | H11: =SUMIFS('Raw Data'!$L:$L,'Raw Data'!$B:$B,$B$2,'Raw Data'!$J:$J,H$2,'Raw Data'!$K:$K,"native",'Raw Data'!$H:$H,"18-30",'Raw Data'!$I:$I,"",'Raw Data'!$M:$M,"count") -> 647000 | I11: =SUMIFS('Raw Data'!$L:$L,'Raw Data'!$B:$B,$B$2,'Raw Data'!$J:$J,I$2,'Raw Data'!$K:$K,"native",'Raw Data'!$H:$H,"18-30",'Raw Data'!$I:$I,"",'Raw Data'!$M:$M,"count") -> 657000 | J11: =SUMIFS('Raw Data'!$L:$L,'Raw Data'!$B:$B,$B$2,'Raw Data'!$J:$J,J$2,'Raw Data'!$K:$K,"native",'Raw Data'!$H:$H,"18-30",'Raw Data'!$I:$I,"",'Raw Data'!$M:$M,"count") -> 667000 | ... Z11: =SUMIFS('Raw Data'!$L:$L,'Raw Data'!$B:$B,$B$2,'Raw Data'!$J:$J,Z$2,'Raw Data'!$K:$K,"native",'Raw Data'!$H:$H,"18-30",'Raw Data'!$I:$I,"",'Raw Data'!$M:$M,"count") -> 839000
A12: Users | B12: 31-40 | C12: =SUMIFS('Raw Data'!$L:$L,'Raw Data'!$B:$B,$B$2,'Raw Data'!$J:$J,C$2,'Raw Data'!$K:$K,"native",'Raw Data'!$H:$H,"31-40",'Raw Data'!$I:$I,"",'Raw Data'!$M:$M,"count") -> 409000 | D12: =SUMIFS('Raw Data'!$L:$L,'Raw Data'!$B:$B,$B$2,'Raw Data'!$J:$J,D$2,'Raw Data'!$K:$K,"native",'Raw Data'!$H:$H,"31-40",'Raw Data'!$I:$I,"",'Raw Data'!$M:$M,"count") -> 419000 | E12: =SUMIFS('Raw Data'!$L:$L,'Raw Data'!$B:$B,$B$2,'Raw Data'!$J:$J,E$2,'Raw Data'!$K:$K,"native",'Raw Data'!$H:$H,"31-40",'Raw Data'!$I:$I,"",'Raw Data'!$M:$M,"count") -> 428000 | F12: =SUMIFS('Raw Data'!$L:$L,'Raw Data'!$B:$B,$B$2,'Raw Data'!$J:$J,F$2,'Raw Data'!$K:$K,"native",'Raw Data'!$H:$H,"31-40",'Raw Data'!$I:$I,"",'Raw Data'!$M:$M,"count") -> 438000 | G12: =SUMIFS('Raw Data'!$L:$L,'Raw Data'!$B:$B,$B$2,'Raw Data'!$J:$J,G$2,'Raw Data'!$K:$K,"native",'Raw Data'!$H:$H,"31-40",'Raw Data'!$I:$I,"",'Raw Data'!$M:$M,"count") -> 448000 | H12: =SUMIFS('Raw Data'!$L:$L,'Raw Data'!$B:$B,$B$2,'Raw Data'!$J:$J,H$2,'Raw Data'!$K:$K,"native",'Raw Data'!$H:$H,"31-40",'Raw Data'!$I:$I,"",'Raw Data'!$M:$M,"count") -> 457000 | I12: =SUMIFS('Raw Data'!$L:$L,'Raw Data'!$B:$B,$B$2,'Raw Data'!$J:$J,I$2,'Raw Data'!$K:$K,"native",'Raw Data'!$H:$H,"31-40",'Raw Data'!$I:$I,"",'Raw Data'!$M:$M,"count") -> 466000 | J12: =SUMIFS('Raw Data'!$L:$L,'Raw Data'!$B:$B,$B$2,'Raw Data'!$J:$J,J$2,'Raw Data'!$K:$K,"native",'Raw Data'!$H:$H,"31-40",'Raw Data'!$I:$I,"",'Raw Data'!$M:$M,"count") -> 474000 | ... Z12: =SUMIFS('Raw Data'!$L:$L,'Raw Data'!$B:$B,$B$2,'Raw Data'!$J:$J,Z$2,'Raw Data'!$K:$K,"native",'Raw Data'!$H:$H,"31-40",'Raw Data'!$I:$I,"",'Raw Data'!$M:$M,"count") -> 607000
A13: Users | B13: 41-50 | C13: =SUMIFS('Raw Data'!$L:$L,'Raw Data'!$B:$B,$B$2,'Raw Data'!$J:$J,C$2,'Raw Data'!$K:$K,"native",'Raw Data'!$H:$H,"41-50",'Raw Data'!$I:$I,"",'Raw Data'!$M:$M,"count") -> 267000 | D13: =SUMIFS('Raw Data'!$L:$L,'Raw Data'!$B:$B,$B$2,'Raw Data'!$J:$J,D$2,'Raw Data'!$K:$K,"native",'Raw Data'!$H:$H,"41-50",'Raw Data'!$I:$I,"",'Raw Data'!$M:$M,"count") -> 275000 | E13: =SUMIFS('Raw Data'!$L:$L,'Raw Data'!$B:$B,$B$2,'Raw Data'!$J:$J,E$2,'Raw Data'!$K:$K,"native",'Raw Data'!$H:$H,"41-50",'Raw Data'!$I:$I,"",'Raw Data'!$M:$M,"count") -> 282000 | F13: =SUMIFS('Raw Data'!$L:$L,'Raw Data'!$B:$B,$B$2,'Raw Data'!$J:$J,F$2,'Raw Data'!$K:$K,"native",'Raw Data'!$H:$H,"41-50",'Raw Data'!$I:$I,"",'Raw Data'!$M:$M,"count") -> 289000 | G13: =SUMIFS('Raw Data'!$L:$L,'Raw Data'!$B:$B,$B$2,'Raw Data'!$J:$J,G$2,'Raw Data'!$K:$K,"native",'Raw Data'!$H:$H,"41-50",'Raw Data'!$I:$I,"",'Raw Data'!$M:$M,"count") -> 297000 | H13: =SUMIFS('Raw Data'!$L:$L,'Raw Data'!$B:$B,$B$2,'Raw Data'!$J:$J,H$2,'Raw Data'!$K:$K,"native",'Raw Data'!$H:$H,"41-50",'Raw Data'!$I:$I,"",'Raw Data'!$M:$M,"count") -> 304000 | I13: =SUMIFS('Raw Data'!$L:$L,'Raw Data'!$B:$B,$B$2,'Raw Data'!$J:$J,I$2,'Raw Data'!$K:$K,"native",'Raw Data'!$H:$H,"41-50",'Raw Data'!$I:$I,"",'Raw Data'!$M:$M,"count") -> 312000 | J13: =SUMIFS('Raw Data'!$L:$L,'Raw Data'!$B:$B,$B$2,'Raw Data'!$J:$J,J$2,'Raw Data'!$K:$K,"native",'Raw Data'!$H:$H,"41-50",'Raw Data'!$I:$I,"",'Raw Data'!$M:$M,"count") -> 318000 | ... Z13: =SUMIFS('Raw Data'!$L:$L,'Raw Data'!$B:$B,$B$2,'Raw Data'!$J:$J,Z$2,'Raw Data'!$K:$K,"native",'Raw Data'!$H:$H,"41-50",'Raw Data'!$I:$I,"",'Raw Data'!$M:$M,"count") -> 431000
A14: Users | B14: 51-60 | C14: =SUMIFS('Raw Data'!$L:$L,'Raw Data'!$B:$B,$B$2,'Raw Data'!$J:$J,C$2,'Raw Data'!$K:$K,"native",'Raw Data'!$H:$H,"51-60",'Raw Data'!$I:$I,"",'Raw Data'!$M:$M,"count") -> 163000 | D14: =SUMIFS('Raw Data'!$L:$L,'Raw Data'!$B:$B,$B$2,'Raw Data'!$J:$J,D$2,'Raw Data'!$K:$K,"native",'Raw Data'!$H:$H,"51-60",'Raw Data'!$I:$I,"",'Raw Data'!$M:$M,"count") -> 167000 | E14: =SUMIFS('Raw Data'!$L:$L,'Raw Data'!$B:$B,$B$2,'Raw Data'!$J:$J,E$2,'Raw Data'!$K:$K,"native",'Raw Data'!$H:$H,"51-60",'Raw Data'!$I:$I,"",'Raw Data'!$M:$M,"count") -> 172000 | F14: =SUMIFS('Raw Data'!$L:$L,'Raw Data'!$B:$B,$B$2,'Raw Data'!$J:$J,F$2,'Raw Data'!$K:$K,"native",'Raw Data'!$H:$H,"51-60",'Raw Data'!$I:$I,"",'Raw Data'!$M:$M,"count") -> 177000 | G14: =SUMIFS('Raw Data'!$L:$L,'Raw Data'!$B:$B,$B$2,'Raw Data'!$J:$J,G$2,'Raw Data'!$K:$K,"native",'Raw Data'!$H:$H,"51-60",'Raw Data'!$I:$I,"",'Raw Data'!$M:$M,"count") -> 181000 | H14: =SUMIFS('Raw Data'!$L:$L,'Raw Data'!$B:$B,$B$2,'Raw Data'!$J:$J,H$2,'Raw Data'!$K:$K,"native",'Raw Data'!$H:$H,"51-60",'Raw Data'!$I:$I,"",'Raw Data'!$M:$M,"count") -> 186000 | I14: =SUMIFS('Raw Data'!$L:$L,'Raw Data'!$B:$B,$B$2,'Raw Data'!$J:$J,I$2,'Raw Data'!$K:$K,"native",'Raw Data'!$H:$H,"51-60",'Raw Data'!$I:$I,"",'Raw Data'!$M:$M,"count") -> 191000 | J14: =SUMIFS('Raw Data'!$L:$L,'Raw Data'!$B:$B,$B$2,'Raw Data'!$J:$J,J$2,'Raw Data'!$K:$K,"native",'Raw Data'!$H:$H,"51-60",'Raw Data'!$I:$I,"",'Raw Data'!$M:$M,"count") -> 195000 | ... Z14: =SUMIFS('Raw Data'!$L:$L,'Raw Data'!$B:$B,$B$2,'Raw Data'!$J:$J,Z$2,'Raw Data'!$K:$K,"native",'Raw Data'!$H:$H,"51-60",'Raw Data'!$I:$I,"",'Raw Data'!$M:$M,"count") -> 269000
A15: Users | B15: 61-70 | C15: =SUMIFS('Raw Data'!$L:$L,'Raw Data'!$B:$B,$B$2,'Raw Data'!$J:$J,C$2,'Raw Data'!$K:$K,"native",'Raw Data'!$H:$H,"61-70",'Raw Data'!$I:$I,"",'Raw Data'!$M:$M,"count") -> 71000 | D15: =SUMIFS('Raw Data'!$L:$L,'Raw Data'!$B:$B,$B$2,'Raw Data'!$J:$J,D$2,'Raw Data'!$K:$K,"native",'Raw Data'!$H:$H,"61-70",'Raw Data'!$I:$I,"",'Raw Data'!$M:$M,"count") -> 74000 | E15: =SUMIFS('Raw Data'!$L:$L,'Raw Data'!$B:$B,$B$2,'Raw Data'!$J:$J,E$2,'Raw Data'!$K:$K,"native",'Raw Data'!$H:$H,"61-70",'Raw Data'!$I:$I,"",'Raw Data'!$M:$M,"count") -> 76000 | F15: =SUMIFS('Raw Data'!$L:$L,'Raw Data'!$B:$B,$B$2,'Raw Data'!$J:$J,F$2,'Raw Data'!$K:$K,"native",'Raw Data'!$H:$H,"61-70",'Raw Data'!$I:$I,"",'Raw Data'!$M:$M,"count") -> 78000 | G15: =SUMIFS('Raw Data'!$L:$L,'Raw Data'!$B:$B,$B$2,'Raw Data'!$J:$J,G$2,'Raw Data'!$K:$K,"native",'Raw Data'!$H:$H,"61-70",'Raw Data'!$I:$I,"",'Raw Data'!$M:$M,"count") -> 81000 | H15: =SUMIFS('Raw Data'!$L:$L,'Raw Data'!$B:$B,$B$2,'Raw Data'!$J:$J,H$2,'Raw Data'!$K:$K,"native",'Raw Data'!$H:$H,"61-70",'Raw Data'!$I:$I,"",'Raw Data'!$M:$M,"count") -> 83000 | I15: =SUMIFS('Raw Data'!$L:$L,'Raw Data'!$B:$B,$B$2,'Raw Data'!$J:$J,I$2,'Raw Data'!$K:$K,"native",'Raw Data'!$H:$H,"61-70",'Raw Data'!$I:$I,"",'Raw Data'!$M:$M,"count") -> 86000 | J15: =SUMIFS('Raw Data'!$L:$L,'Raw Data'!$B:$B,$B$2,'Raw Data'!$J:$J,J$2,'Raw Data'!$K:$K,"native",'Raw Data'!$H:$H,"61-70",'Raw Data'!$I:$I,"",'Raw Data'!$M:$M,"count") -> 88000 | ... Z15: =SUMIFS('Raw Data'!$L:$L,'Raw Data'!$B:$B,$B$2,'Raw Data'!$J:$J,Z$2,'Raw Data'!$K:$K,"native",'Raw Data'!$H:$H,"61-70",'Raw Data'!$I:$I,"",'Raw Data'!$M:$M,"count") -> 129000
A16: Users | B16: 71-80 | C16: =SUMIFS('Raw Data'!$L:$L,'Raw Data'!$B:$B,$B$2,'Raw Data'!$J:$J,C$2,'Raw Data'!$K:$K,"native",'Raw Data'!$H:$H,"71-80",'Raw Data'!$I:$I,"",'Raw Data'!$M:$M,"count") -> 18000 | D16: =SUMIFS('Raw Data'!$L:$L,'Raw Data'!$B:$B,$B$2,'Raw Data'!$J:$J,D$2,'Raw Data'!$K:$K,"native",'Raw Data'!$H:$H,"71-80",'Raw Data'!$I:$I,"",'Raw Data'!$M:$M,"count") -> 19000 | E16: =SUMIFS('Raw Data'!$L:$L,'Raw Data'!$B:$B,$B$2,'Raw Data'!$J:$J,E$2,'Raw Data'!$K:$K,"native",'Raw Data'!$H:$H,"71-80",'Raw Data'!$I:$I,"",'Raw Data'!$M:$M,"count") -> 19000 | F16: =SUMIFS('Raw Data'!$L:$L,'Raw Data'!$B:$B,$B$2,'Raw Data'!$J:$J,F$2,'Raw Data'!$K:$K,"native",'Raw Data'!$H:$H,"71-80",'Raw Data'!$I:$I,"",'Raw Data'!$M:$M,"count") -> 20000 | G16: =SUMIFS('Raw Data'!$L:$L,'Raw Data'!$B:$B,$B$2,'Raw Data'!$J:$J,G$2,'Raw Data'!$K:$K,"native",'Raw Data'!$H:$H,"71-80",'Raw Data'!$I:$I,"",'Raw Data'!$M:$M,"count") -> 21000 | H16: =SUMIFS('Raw Data'!$L:$L,'Raw Data'!$B:$B,$B$2,'Raw Data'!$J:$J,H$2,'Raw Data'!$K:$K,"native",'Raw Data'!$H:$H,"71-80",'Raw Data'!$I:$I,"",'Raw Data'!$M:$M,"count") -> 21000 | I16: =SUMIFS('Raw Data'!$L:$L,'Raw Data'!$B:$B,$B$2,'Raw Data'!$J:$J,I$2,'Raw Data'!$K:$K,"native",'Raw Data'!$H:$H,"71-80",'Raw Data'!$I:$I,"",'Raw Data'!$M:$M,"count") -> 22000 | J16: =SUMIFS('Raw Data'!$L:$L,'Raw Data'!$B:$B,$B$2,'Raw Data'!$J:$J,J$2,'Raw Data'!$K:$K,"native",'Raw Data'!$H:$H,"71-80",'Raw Data'!$I:$I,"",'Raw Data'!$M:$M,"count") -> 23000 | ... Z16: =SUMIFS('Raw Data'!$L:$L,'Raw Data'!$B:$B,$B$2,'Raw Data'!$J:$J,Z$2,'Raw Data'!$K:$K,"native",'Raw Data'!$H:$H,"71-80",'Raw Data'!$I:$I,"",'Raw Data'!$M:$M,"count") -> 36000
A17: Users | B17: 81-90 | C17: =SUMIFS('Raw Data'!$L:$L,'Raw Data'!$B:$B,$B$2,'Raw Data'!$J:$J,C$2,'Raw Data'!$K:$K,"native",'Raw Data'!$H:$H,"81-90",'Raw Data'!$I:$I,"",'Raw Data'!$M:$M,"count") -> 4000 | D17: =SUMIFS('Raw Data'!$L:$L,'Raw Data'!$B:$B,$B$2,'Raw Data'!$J:$J,D$2,'Raw Data'!$K:$K,"native",'Raw Data'!$H:$H,"81-90",'Raw Data'!$I:$I,"",'Raw Data'!$M:$M,"count") -> 4000 | E17: =SUMIFS('Raw Data'!$L:$L,'Raw Data'!$B:$B,$B$2,'Raw Data'!$J:$J,E$2,'Raw Data'!$K:$K,"native",'Raw Data'!$H:$H,"81-90",'Raw Data'!$I:$I,"",'Raw Data'!$M:$M,"count") -> 4000 | F17: =SUMIFS('Raw Data'!$L:$L,'Raw Data'!$B:$B,$B$2,'Raw Data'!$J:$J,F$2,'Raw Data'!$K:$K,"native",'Raw Data'!$H:$H,"81-90",'Raw Data'!$I:$I,"",'Raw Data'!$M:$M,"count") -> 4000 | G17: =SUMIFS('Raw Data'!$L:$L,'Raw Data'!$B:$B,$B$2,'Raw Data'!$J:$J,G$2,'Raw Data'!$K:$K,"native",'Raw Data'!$H:$H,"81-90",'Raw Data'!$I:$I,"",'Raw Data'!$M:$M,"count") -> 4000 | H17: =SUMIFS('Raw Data'!$L:$L,'Raw Data'!$B:$B,$B$2,'Raw Data'!$J:$J,H$2,'Raw Data'!$K:$K,"native",'Raw Data'!$H:$H,"81-90",'Raw Data'!$I:$I,"",'Raw Data'!$M:$M,"count") -> 4000 | I17: =SUMIFS('Raw Data'!$L:$L,'Raw Data'!$B:$B,$B$2,'Raw Data'!$J:$J,I$2,'Raw Data'!$K:$K,"native",'Raw Data'!$H:$H,"81-90",'Raw Data'!$I:$I,"",'Raw Data'!$M:$M,"count") -> 4000 | J17: =SUMIFS('Raw Data'!$L:$L,'Raw Data'!$B:$B,$B$2,'Raw Data'!$J:$J,J$2,'Raw Data'!$K:$K,"native",'Raw Data'!$H:$H,"81-90",'Raw Data'!$I:$I,"",'Raw Data'!$M:$M,"count") -> 5000 | ... Z17: =SUMIFS('Raw Data'!$L:$L,'Raw Data'!$B:$B,$B$2,'Raw Data'!$J:$J,Z$2,'Raw Data'!$K:$K,"native",'Raw Data'!$H:$H,"81-90",'Raw Data'!$I:$I,"",'Raw Data'!$M:$M,"count") -> 9000
A18: Users | B18: <18 | C18: =SUMIFS('Raw Data'!$L:$L,'Raw Data'!$B:$B,$B$2,'Raw Data'!$J:$J,C$2,'Raw Data'!$K:$K,"native",'Raw Data'!$H:$H,"=<18",'Raw Data'!$I:$I,"",'Raw Data'!$M:$M,"count") -> 6000 | D18: =SUMIFS('Raw Data'!$L:$L,'Raw Data'!$B:$B,$B$2,'Raw Data'!$J:$J,D$2,'Raw Data'!$K:$K,"native",'Raw Data'!$H:$H,"=<18",'Raw Data'!$I:$I,"",'Raw Data'!$M:$M,"count") -> 6000 | E18: =SUMIFS('Raw Data'!$L:$L,'Raw Data'!$B:$B,$B$2,'Raw Data'!$J:$J,E$2,'Raw Data'!$K:$K,"native",'Raw Data'!$H:$H,"=<18",'Raw Data'!$I:$I,"",'Raw Data'!$M:$M,"count") -> 6000 | F18: =SUMIFS('Raw Data'!$L:$L,'Raw Data'!$B:$B,$B$2,'Raw Data'!$J:$J,F$2,'Raw Data'!$K:$K,"native",'Raw Data'!$H:$H,"=<18",'Raw Data'!$I:$I,"",'Raw Data'!$M:$M,"count") -> 6000 | G18: =SUMIFS('Raw Data'!$L:$L,'Raw Data'!$B:$B,$B$2,'Raw Data'!$J:$J,G$2,'Raw Data'!$K:$K,"native",'Raw Data'!$H:$H,"=<18",'Raw Data'!$I:$I,"",'Raw Data'!$M:$M,"count") -> 6000 | H18: =SUMIFS('Raw Data'!$L:$L,'Raw Data'!$B:$B,$B$2,'Raw Data'!$J:$J,H$2,'Raw Data'!$K:$K,"native",'Raw Data'!$H:$H,"=<18",'Raw Data'!$I:$I,"",'Raw Data'!$M:$M,"count") -> 7000 | I18: =SUMIFS('Raw Data'!$L:$L,'Raw Data'!$B:$B,$B$2,'Raw Data'!$J:$J,I$2,'Raw Data'!$K:$K,"native",'Raw Data'!$H:$H,"=<18",'Raw Data'!$I:$I,"",'Raw Data'!$M:$M,"count") -> 7000 | J18: =SUMIFS('Raw Data'!$L:$L,'Raw Data'!$B:$B,$B$2,'Raw Data'!$J:$J,J$2,'Raw Data'!$K:$K,"native",'Raw Data'!$H:$H,"=<18",'Raw Data'!$I:$I,"",'Raw Data'!$M:$M,"count") -> 8000 | ... Z18: =SUMIFS('Raw Data'!$L:$L,'Raw Data'!$B:$B,$B$2,'Raw Data'!$J:$J,Z$2,'Raw Data'!$K:$K,"native",'Raw Data'!$H:$H,"=<18",'Raw Data'!$I:$I,"",'Raw Data'!$M:$M,"count") -> 12000
A19: USERS BY USER TYPE (Number)
A20: Users | B20: Individual | C20: =SUMIFS('Raw Data'!$L:$L,'Raw Data'!$B:$B,$B$2,'Raw Data'!$J:$J,C$2,'Raw Data'!$K:$K,"native",'Raw Data'!$H:$H,"Individual",'Raw Data'!$I:$I,"",'Raw Data'!$M:$M,"count") -> 1530000 | D20: =SUMIFS('Raw Data'!$L:$L,'Raw Data'!$B:$B,$B$2,'Raw Data'!$J:$J,D$2,'Raw Data'!$K:$K,"native",'Raw Data'!$H:$H,"Individual",'Raw Data'!$I:$I,"",'Raw Data'!$M:$M,"count") -> 1570000 | E20: =SUMIFS('Raw Data'!$L:$L,'Raw Data'!$B:$B,$B$2,'Raw Data'!$J:$J,E$2,'Raw Data'!$K:$K,"native",'Raw Data'!$H:$H,"Individual",'Raw Data'!$I:$I,"",'Raw Data'!$M:$M,"count") -> 1600000 | F20: =SUMIFS('Raw Data'!$L:$L,'Raw Data'!$B:$B,$B$2,'Raw Data'!$J:$J,F$2,'Raw Data'!$K:$K,"native",'Raw Data'!$H:$H,"Individual",'Raw Data'!$I:$I,"",'Raw Data'!$M:$M,"count") -> 1640000 | G20: =SUMIFS('Raw Data'!$L:$L,'Raw Data'!$B:$B,$B$2,'Raw Data'!$J:$J,G$2,'Raw Data'!$K:$K,"native",'Raw Data'!$H:$H,"Individual",'Raw Data'!$I:$I,"",'Raw Data'!$M:$M,"count") -> 1680000 | H20: =SUMIFS('Raw Data'!$L:$L,'Raw Data'!$B:$B,$B$2,'Raw Data'!$J:$J,H$2,'Raw Data'!$K:$K,"native",'Raw Data'!$H:$H,"Individual",'Raw Data'!$I:$I,"",'Raw Data'!$M:$M,"count") -> 1710000 | I20: =SUMIFS('Raw Data'!$L:$L,'Raw Data'!$B:$B,$B$2,'Raw Data'!$J:$J,I$2,'Raw Data'!$K:$K,"native",'Raw Data'!$H:$H,"Individual",'Raw Data'!$I:$I,"",'Raw Data'!$M:$M,"count") -> 1740000 | J20: =SUMIFS('Raw Data'!$L:$L,'Raw Data'!$B:$B,$B$2,'Raw Data'!$J:$J,J$2,'Raw Data'!$K:$K,"native",'Raw Data'!$H:$H,"Individual",'Raw Data'!$I:$I,"",'Raw Data'!$M:$M,"count") -> 1780000 | ... Z20: =SUMIFS('Raw Data'!$L:$L,'Raw Data'!$B:$B,$B$2,'Raw Data'!$J:$J,Z$2,'Raw Data'!$K:$K,"native",'Raw Data'!$H:$H,"Individual",'Raw Data'!$I:$I,"",'Raw Data'!$M:$M,"count") -> 2330000
A21: Users | B21: Legal (entities) | C21: =SUMIFS('Raw Data'!$L:$L,'Raw Data'!$B:$B,$B$2,'Raw Data'!$J:$J,C$2,'Raw Data'!$K:$K,"native",'Raw Data'!$H:$H,"Legal (entities)",'Raw Data'!$I:$I,"",'Raw Data'!$M:$M,"count") -> 26500 | D21: =SUMIFS('Raw Data'!$L:$L,'Raw Data'!$B:$B,$B$2,'Raw Data'!$J:$J,D$2,'Raw Data'!$K:$K,"native",'Raw Data'!$H:$H,"Legal (entities)",'Raw Data'!$I:$I,"",'Raw Data'!$M:$M,"count") -> 28000 | E21: =SUMIFS('Raw Data'!$L:$L,'Raw Data'!$B:$B,$B$2,'Raw Data'!$J:$J,E$2,'Raw Data'!$K:$K,"native",'Raw Data'!$H:$H,"Legal (entities)",'Raw Data'!$I:$I,"",'Raw Data'!$M:$M,"count") -> 29000 | F21: =SUMIFS('Raw Data'!$L:$L,'Raw Data'!$B:$B,$B$2,'Raw Data'!$J:$J,F$2,'Raw Data'!$K:$K,"native",'Raw Data'!$H:$H,"Legal (entities)",'Raw Data'!$I:$I,"",'Raw Data'!$M:$M,"count") -> 30400 | G21: =SUMIFS('Raw Data'!$L:$L,'Raw Data'!$B:$B,$B$2,'Raw Data'!$J:$J,G$2,'Raw Data'!$K:$K,"native",'Raw Data'!$H:$H,"Legal (entities)",'Raw Data'!$I:$I,"",'Raw Data'!$M:$M,"count") -> 31600 | H21: =SUMIFS('Raw Data'!$L:$L,'Raw Data'!$B:$B,$B$2,'Raw Data'!$J:$J,H$2,'Raw Data'!$K:$K,"native",'Raw Data'!$H:$H,"Legal (entities)",'Raw Data'!$I:$I,"",'Raw Data'!$M:$M,"count") -> 32800 | I21: =SUMIFS('Raw Data'!$L:$L,'Raw Data'!$B:$B,$B$2,'Raw Data'!$J:$J,I$2,'Raw Data'!$K:$K,"native",'Raw Data'!$H:$H,"Legal (entities)",'Raw Data'!$I:$I,"",'Raw Data'!$M:$M,"count") -> 34000 | J21: =SUMIFS('Raw Data'!$L:$L,'Raw Data'!$B:$B,$B$2,'Raw Data'!$J:$J,J$2,'Raw Data'!$K:$K,"native",'Raw Data'!$H:$H,"Legal (entities)",'Raw Data'!$I:$I,"",'Raw Data'!$M:$M,"count") -> 35000 | ... Z21: =SUMIFS('Raw Data'!$L:$L,'Raw Data'!$B:$B,$B$2,'Raw Data'!$J:$J,Z$2,'Raw Data'!$K:$K,"native",'Raw Data'!$H:$H,"Legal (entities)",'Raw Data'!$I:$I,"",'Raw Data'!$M:$M,"count") -> 59000
A22: TRANSACTIONS BY TRANSACTION TYPE (Number)
A23: Transactions | B23: Money Transfers | C23: =SUMIFS('Raw Data'!$L:$L,'Raw Data'!$B:$B,$B$2,'Raw Data'!$J:$J,C$2,'Raw Data'!$K:$K,"native",'Raw Data'!$H:$H,"Money Transfers",'Raw Data'!$I:$I,"",'Raw Data'!$M:$M,"count") -> 6800000 | D23: =SUMIFS('Raw Data'!$L:$L,'Raw Data'!$B:$B,$B$2,'Raw Data'!$J:$J,D$2,'Raw Data'!$K:$K,"native",'Raw Data'!$H:$H,"Money Transfers",'Raw Data'!$I:$I,"",'Raw Data'!$M:$M,"count") -> 7620000 | E23: =SUMIFS('Raw Data'!$L:$L,'Raw Data'!$B:$B,$B$2,'Raw Data'!$J:$J,E$2,'Raw Data'!$K:$K,"native",'Raw Data'!$H:$H,"Money Transfers",'Raw Data'!$I:$I,"",'Raw Data'!$M:$M,"count") -> 7720000 | F23: =SUMIFS('Raw Data'!$L:$L,'Raw Data'!$B:$B,$B$2,'Raw Data'!$J:$J,F$2,'Raw Data'!$K:$K,"native",'Raw Data'!$H:$H,"Money Transfers",'Raw Data'!$I:$I,"",'Raw Data'!$M:$M,"count") -> 8570000 | G23: =SUMIFS('Raw Data'!$L:$L,'Raw Data'!$B:$B,$B$2,'Raw Data'!$J:$J,G$2,'Raw Data'!$K:$K,"native",'Raw Data'!$H:$H,"Money Transfers",'Raw Data'!$I:$I,"",'Raw Data'!$M:$M,"count") -> 8820000 | H23: =SUMIFS('Raw Data'!$L:$L,'Raw Data'!$B:$B,$B$2,'Raw Data'!$J:$J,H$2,'Raw Data'!$K:$K,"native",'Raw Data'!$H:$H,"Money Transfers",'Raw Data'!$I:$I,"",'Raw Data'!$M:$M,"count") -> 8450000 | I23: =SUMIFS('Raw Data'!$L:$L,'Raw Data'!$B:$B,$B$2,'Raw Data'!$J:$J,I$2,'Raw Data'!$K:$K,"native",'Raw Data'!$H:$H,"Money Transfers",'Raw Data'!$I:$I,"",'Raw Data'!$M:$M,"count") -> 10360000 | J23: =SUMIFS('Raw Data'!$L:$L,'Raw Data'!$B:$B,$B$2,'Raw Data'!$J:$J,J$2,'Raw Data'!$K:$K,"native",'Raw Data'!$H:$H,"Money Transfers",'Raw Data'!$I:$I,"",'Raw Data'!$M:$M,"count") -> 9780000 | ... Z23: =SUMIFS('Raw Data'!$L:$L,'Raw Data'!$B:$B,$B$2,'Raw Data'!$J:$J,Z$2,'Raw Data'!$K:$K,"native",'Raw Data'!$H:$H,"Money Transfers",'Raw Data'!$I:$I,"",'Raw Data'!$M:$M,"count") -> 19020000
A24: Transactions | B24: Purchases | C24: =SUMIFS('Raw Data'!$L:$L,'Raw Data'!$B:$B,$B$2,'Raw Data'!$J:$J,C$2,'Raw Data'!$K:$K,"native",'Raw Data'!$H:$H,"Purchases",'Raw Data'!$I:$I,"",'Raw Data'!$M:$M,"count") -> 1090000 | D24: =SUMIFS('Raw Data'!$L:$L,'Raw Data'!$B:$B,$B$2,'Raw Data'!$J:$J,D$2,'Raw Data'!$K:$K,"native",'Raw Data'!$H:$H,"Purchases",'Raw Data'!$I:$I,"",'Raw Data'!$M:$M,"count") -> 1240000 | E24: =SUMIFS('Raw Data'!$L:$L,'Raw Data'!$B:$B,$B$2,'Raw Data'!$J:$J,E$2,'Raw Data'!$K:$K,"native",'Raw Data'!$H:$H,"Purchases",'Raw Data'!$I:$I,"",'Raw Data'!$M:$M,"count") -> 1260000 | F24: =SUMIFS('Raw Data'!$L:$L,'Raw Data'!$B:$B,$B$2,'Raw Data'!$J:$J,F$2,'Raw Data'!$K:$K,"native",'Raw Data'!$H:$H,"Purchases",'Raw Data'!$I:$I,"",'Raw Data'!$M:$M,"count") -> 1430000 | G24: =SUMIFS('Raw Data'!$L:$L,'Raw Data'!$B:$B,$B$2,'Raw Data'!$J:$J,G$2,'Raw Data'!$K:$K,"native",'Raw Data'!$H:$H,"Purchases",'Raw Data'!$I:$I,"",'Raw Data'!$M:$M,"count") -> 1500000 | H24: =SUMIFS('Raw Data'!$L:$L,'Raw Data'!$B:$B,$B$2,'Raw Data'!$J:$J,H$2,'Raw Data'!$K:$K,"native",'Raw Data'!$H:$H,"Purchases",'Raw Data'!$I:$I,"",'Raw Data'!$M:$M,"count") -> 1450000 | I24: =SUMIFS('Raw Data'!$L:$L,'Raw Data'!$B:$B,$B$2,'Raw Data'!$J:$J,I$2,'Raw Data'!$K:$K,"native",'Raw Data'!$H:$H,"Purchases",'Raw Data'!$I:$I,"",'Raw Data'!$M:$M,"count") -> 1750000 | J24: =SUMIFS('Raw Data'!$L:$L,'Raw Data'!$B:$B,$B$2,'Raw Data'!$J:$J,J$2,'Raw Data'!$K:$K,"native",'Raw Data'!$H:$H,"Purchases",'Raw Data'!$I:$I,"",'Raw Data'!$M:$M,"count") -> 1740000 | ... Z24: =SUMIFS('Raw Data'!$L:$L,'Raw Data'!$B:$B,$B$2,'Raw Data'!$J:$J,Z$2,'Raw Data'!$K:$K,"native",'Raw Data'!$H:$H,"Purchases",'Raw Data'!$I:$I,"",'Raw Data'!$M:$M,"count") -> 4970000
A25: TRANSACTIONS BY TYPE — DETAIL (%)
A26: Transactions | B26: Money Transfers: Other | C26: =(SUMIFS('Raw Data'!$L:$L,'Raw Data'!$B:$B,$B$2,'Raw Data'!$J:$J,C$2,'Raw Data'!$K:$K,"native",'Raw Data'!$H:$H,"Money Transfers",'Raw Data'!$I:$I,"Other",'Raw Data'!$M:$M,"percent",'Raw Data'!$F:$F,"Number*"))/100 -> 0.034 | D26: =(SUMIFS('Raw Data'!$L:$L,'Raw Data'!$B:$B,$B$2,'Raw Data'!$J:$J,D$2,'Raw Data'!$K:$K,"native",'Raw Data'!$H:$H,"Money Transfers",'Raw Data'!$I:$I,"Other",'Raw Data'!$M:$M,"percent",'Raw Data'!$F:$F,"Number*"))/100 -> 0.037 | E26: =(SUMIFS('Raw Data'!$L:$L,'Raw Data'!$B:$B,$B$2,'Raw Data'!$J:$J,E$2,'Raw Data'!$K:$K,"native",'Raw Data'!$H:$H,"Money Transfers",'Raw Data'!$I:$I,"Other",'Raw Data'!$M:$M,"percent",'Raw Data'!$F:$F,"Number*"))/100 -> 0.036 | F26: =(SUMIFS('Raw Data'!$L:$L,'Raw Data'!$B:$B,$B$2,'Raw Data'!$J:$J,F$2,'Raw Data'!$K:$K,"native",'Raw Data'!$H:$H,"Money Transfers",'Raw Data'!$I:$I,"Other",'Raw Data'!$M:$M,"percent",'Raw Data'!$F:$F,"Number*"))/100 -> 0.0357 | G26: =(SUMIFS('Raw Data'!$L:$L,'Raw Data'!$B:$B,$B$2,'Raw Data'!$J:$J,G$2,'Raw Data'!$K:$K,"native",'Raw Data'!$H:$H,"Money Transfers",'Raw Data'!$I:$I,"Other",'Raw Data'!$M:$M,"percent",'Raw Data'!$F:$F,"Number*"))/100 -> 0.035 | H26: =(SUMIFS('Raw Data'!$L:$L,'Raw Data'!$B:$B,$B$2,'Raw Data'!$J:$J,H$2,'Raw Data'!$K:$K,"native",'Raw Data'!$H:$H,"Money Transfers",'Raw Data'!$I:$I,"Other",'Raw Data'!$M:$M,"percent",'Raw Data'!$F:$F,"Number*"))/100 -> 0.036 | I26: =(SUMIFS('Raw Data'!$L:$L,'Raw Data'!$B:$B,$B$2,'Raw Data'!$J:$J,I$2,'Raw Data'!$K:$K,"native",'Raw Data'!$H:$H,"Money Transfers",'Raw Data'!$I:$I,"Other",'Raw Data'!$M:$M,"percent",'Raw Data'!$F:$F,"Number*"))/100 -> 0.04 | J26: =(SUMIFS('Raw Data'!$L:$L,'Raw Data'!$B:$B,$B$2,'Raw Data'!$J:$J,J$2,'Raw Data'!$K:$K,"native",'Raw Data'!$H:$H,"Money Transfers",'Raw Data'!$I:$I,"Other",'Raw Data'!$M:$M,"percent",'Raw Data'!$F:$F,"Number*"))/100 -> 0.034 | ... M26: =(SUMIFS('Raw Data'!$L:$L,'Raw Data'!$B:$B,$B$2,'Raw Data'!$J:$J,M$2,'Raw Data'!$K:$K,"native",'Raw Data'!$H:$H,"Money Transfers",'Raw Data'!$I:$I,"Other",'Raw Data'!$M:$M,"percent",'Raw Data'!$F:$F,"Number*"))/100 -> 0.012 | T26: =(SUMIFS('Raw Data'!$L:$L,'Raw Data'!$B:$B,$B$2,'Raw Data'!$J:$J,T$2,'Raw Data'!$K:$K,"native",'Raw Data'!$H:$H,"Money Transfers",'Raw Data'!$I:$I,"Other",'Raw Data'!$M:$M,"percent",'Raw Data'!$F:$F,"Number*"))/100 -> 0 | Z26: =(SUMIFS('Raw Data'!$L:$L,'Raw Data'!$B:$B,$B$2,'Raw Data'!$J:$J,Z$2,'Raw Data'!$K:$K,"native",'Raw Data'!$H:$H,"Money Transfers",'Raw Data'!$I:$I,"Other",'Raw Data'!$M:$M,"percent",'Raw Data'!$F:$F,"Number*"))/100 -> 0.021
A27: Transactions | B27: Money Transfers: Transfer to Family/Friends | C27: =(SUMIFS('Raw Data'!$L:$L,'Raw Data'!$B:$B,$B$2,'Raw Data'!$J:$J,C$2,'Raw Data'!$K:$K,"native",'Raw Data'!$H:$H,"Money Transfers",'Raw Data'!$I:$I,"Transfer to Family/Friends",'Raw Data'!$M:$M,"percent",'Raw Data'!$F:$F,"Number*"))/100 -> 0.85 | D27: =(SUMIFS('Raw Data'!$L:$L,'Raw Data'!$B:$B,$B$2,'Raw Data'!$J:$J,D$2,'Raw Data'!$K:$K,"native",'Raw Data'!$H:$H,"Money Transfers",'Raw Data'!$I:$I,"Transfer to Family/Friends",'Raw Data'!$M:$M,"percent",'Raw Data'!$F:$F,"Number*"))/100 -> 0.849 | E27: =(SUMIFS('Raw Data'!$L:$L,'Raw Data'!$B:$B,$B$2,'Raw Data'!$J:$J,E$2,'Raw Data'!$K:$K,"native",'Raw Data'!$H:$H,"Money Transfers",'Raw Data'!$I:$I,"Transfer to Family/Friends",'Raw Data'!$M:$M,"percent",'Raw Data'!$F:$F,"Number*"))/100 -> 0.849 | F27: =(SUMIFS('Raw Data'!$L:$L,'Raw Data'!$B:$B,$B$2,'Raw Data'!$J:$J,F$2,'Raw Data'!$K:$K,"native",'Raw Data'!$H:$H,"Money Transfers",'Raw Data'!$I:$I,"Transfer to Family/Friends",'Raw Data'!$M:$M,"percent",'Raw Data'!$F:$F,"Number*"))/100 -> 0.8496 | G27: =(SUMIFS('Raw Data'!$L:$L,'Raw Data'!$B:$B,$B$2,'Raw Data'!$J:$J,G$2,'Raw Data'!$K:$K,"native",'Raw Data'!$H:$H,"Money Transfers",'Raw Data'!$I:$I,"Transfer to Family/Friends",'Raw Data'!$M:$M,"percent",'Raw Data'!$F:$F,"Number*"))/100 -> 0.852 | H27: =(SUMIFS('Raw Data'!$L:$L,'Raw Data'!$B:$B,$B$2,'Raw Data'!$J:$J,H$2,'Raw Data'!$K:$K,"native",'Raw Data'!$H:$H,"Money Transfers",'Raw Data'!$I:$I,"Transfer to Family/Friends",'Raw Data'!$M:$M,"percent",'Raw Data'!$F:$F,"Number*"))/100 -> 0.852 | I27: =(SUMIFS('Raw Data'!$L:$L,'Raw Data'!$B:$B,$B$2,'Raw Data'!$J:$J,I$2,'Raw Data'!$K:$K,"native",'Raw Data'!$H:$H,"Money Transfers",'Raw Data'!$I:$I,"Transfer to Family/Friends",'Raw Data'!$M:$M,"percent",'Raw Data'!$F:$F,"Number*"))/100 -> 0.85 | J27: =(SUMIFS('Raw Data'!$L:$L,'Raw Data'!$B:$B,$B$2,'Raw Data'!$J:$J,J$2,'Raw Data'!$K:$K,"native",'Raw Data'!$H:$H,"Money Transfers",'Raw Data'!$I:$I,"Transfer to Family/Friends",'Raw Data'!$M:$M,"percent",'Raw Data'!$F:$F,"Number*"))/100 -> 0.853 | ... M27: =(SUMIFS('Raw Data'!$L:$L,'Raw Data'!$B:$B,$B$2,'Raw Data'!$J:$J,M$2,'Raw Data'!$K:$K,"native",'Raw Data'!$H:$H,"Money Transfers",'Raw Data'!$I:$I,"Transfer to Family/Friends",'Raw Data'!$M:$M,"percent",'Raw Data'!$F:$F,"Number*"))/100 -> 0.884 | Z27: =(SUMIFS('Raw Data'!$L:$L,'Raw Data'!$B:$B,$B$2,'Raw Data'!$J:$J,Z$2,'Raw Data'!$K:$K,"native",'Raw Data'!$H:$H,"Money Transfers",'Raw Data'!$I:$I,"Transfer to Family/Friends",'Raw Data'!$M:$M,"percent",'Raw Data'!$F:$F,"Number*"))/100 -> 0.881
A28: Transactions | B28: Money Transfers: Transfer to Own Account | C28: =(SUMIFS('Raw Data'!$L:$L,'Raw Data'!$B:$B,$B$2,'Raw Data'!$J:$J,C$2,'Raw Data'!$K:$K,"native",'Raw Data'!$H:$H,"Money Transfers",'Raw Data'!$I:$I,"Transfer to Own Account",'Raw Data'!$M:$M,"percent",'Raw Data'!$F:$F,"Number*"))/100 -> 0.116 | D28: =(SUMIFS('Raw Data'!$L:$L,'Raw Data'!$B:$B,$B$2,'Raw Data'!$J:$J,D$2,'Raw Data'!$K:$K,"native",'Raw Data'!$H:$H,"Money Transfers",'Raw Data'!$I:$I,"Transfer to Own Account",'Raw Data'!$M:$M,"percent",'Raw Data'!$F:$F,"Number*"))/100 -> 0.114 | E28: =(SUMIFS('Raw Data'!$L:$L,'Raw Data'!$B:$B,$B$2,'Raw Data'!$J:$J,E$2,'Raw Data'!$K:$K,"native",'Raw Data'!$H:$H,"Money Transfers",'Raw Data'!$I:$I,"Transfer to Own Account",'Raw Data'!$M:$M,"percent",'Raw Data'!$F:$F,"Number*"))/100 -> 0.115 | F28: =(SUMIFS('Raw Data'!$L:$L,'Raw Data'!$B:$B,$B$2,'Raw Data'!$J:$J,F$2,'Raw Data'!$K:$K,"native",'Raw Data'!$H:$H,"Money Transfers",'Raw Data'!$I:$I,"Transfer to Own Account",'Raw Data'!$M:$M,"percent",'Raw Data'!$F:$F,"Number*"))/100 -> 0.1147 | G28: =(SUMIFS('Raw Data'!$L:$L,'Raw Data'!$B:$B,$B$2,'Raw Data'!$J:$J,G$2,'Raw Data'!$K:$K,"native",'Raw Data'!$H:$H,"Money Transfers",'Raw Data'!$I:$I,"Transfer to Own Account",'Raw Data'!$M:$M,"percent",'Raw Data'!$F:$F,"Number*"))/100 -> 0.113 | H28: =(SUMIFS('Raw Data'!$L:$L,'Raw Data'!$B:$B,$B$2,'Raw Data'!$J:$J,H$2,'Raw Data'!$K:$K,"native",'Raw Data'!$H:$H,"Money Transfers",'Raw Data'!$I:$I,"Transfer to Own Account",'Raw Data'!$M:$M,"percent",'Raw Data'!$F:$F,"Number*"))/100 -> 0.112 | I28: =(SUMIFS('Raw Data'!$L:$L,'Raw Data'!$B:$B,$B$2,'Raw Data'!$J:$J,I$2,'Raw Data'!$K:$K,"native",'Raw Data'!$H:$H,"Money Transfers",'Raw Data'!$I:$I,"Transfer to Own Account",'Raw Data'!$M:$M,"percent",'Raw Data'!$F:$F,"Number*"))/100 -> 0.11 | J28: =(SUMIFS('Raw Data'!$L:$L,'Raw Data'!$B:$B,$B$2,'Raw Data'!$J:$J,J$2,'Raw Data'!$K:$K,"native",'Raw Data'!$H:$H,"Money Transfers",'Raw Data'!$I:$I,"Transfer to Own Account",'Raw Data'!$M:$M,"percent",'Raw Data'!$F:$F,"Number*"))/100 -> 0.112 | ... M28: =(SUMIFS('Raw Data'!$L:$L,'Raw Data'!$B:$B,$B$2,'Raw Data'!$J:$J,M$2,'Raw Data'!$K:$K,"native",'Raw Data'!$H:$H,"Money Transfers",'Raw Data'!$I:$I,"Transfer to Own Account",'Raw Data'!$M:$M,"percent",'Raw Data'!$F:$F,"Number*"))/100 -> 0.104 | Z28: =(SUMIFS('Raw Data'!$L:$L,'Raw Data'!$B:$B,$B$2,'Raw Data'!$J:$J,Z$2,'Raw Data'!$K:$K,"native",'Raw Data'!$H:$H,"Money Transfers",'Raw Data'!$I:$I,"Transfer to Own Account",'Raw Data'!$M:$M,"percent",'Raw Data'!$F:$F,"Number*"))/100 -> 0.098
A29: Transactions | B29: Purchases: Non-QR Purchases | C29: =(SUMIFS('Raw Data'!$L:$L,'Raw Data'!$B:$B,$B$2,'Raw Data'!$J:$J,C$2,'Raw Data'!$K:$K,"native",'Raw Data'!$H:$H,"Purchases",'Raw Data'!$I:$I,"Non-QR Purchases",'Raw Data'!$M:$M,"percent",'Raw Data'!$F:$F,"Number*"))/100 -> 0.995 | D29: =(SUMIFS('Raw Data'!$L:$L,'Raw Data'!$B:$B,$B$2,'Raw Data'!$J:$J,D$2,'Raw Data'!$K:$K,"native",'Raw Data'!$H:$H,"Purchases",'Raw Data'!$I:$I,"Non-QR Purchases",'Raw Data'!$M:$M,"percent",'Raw Data'!$F:$F,"Number*"))/100 -> 0.995 | E29: =(SUMIFS('Raw Data'!$L:$L,'Raw Data'!$B:$B,$B$2,'Raw Data'!$J:$J,E$2,'Raw Data'!$K:$K,"native",'Raw Data'!$H:$H,"Purchases",'Raw Data'!$I:$I,"Non-QR Purchases",'Raw Data'!$M:$M,"percent",'Raw Data'!$F:$F,"Number*"))/100 -> 0.995 | F29: =(SUMIFS('Raw Data'!$L:$L,'Raw Data'!$B:$B,$B$2,'Raw Data'!$J:$J,F$2,'Raw Data'!$K:$K,"native",'Raw Data'!$H:$H,"Purchases",'Raw Data'!$I:$I,"Non-QR Purchases",'Raw Data'!$M:$M,"percent",'Raw Data'!$F:$F,"Number*"))/100 -> 0.995 | G29: =(SUMIFS('Raw Data'!$L:$L,'Raw Data'!$B:$B,$B$2,'Raw Data'!$J:$J,G$2,'Raw Data'!$K:$K,"native",'Raw Data'!$H:$H,"Purchases",'Raw Data'!$I:$I,"Non-QR Purchases",'Raw Data'!$M:$M,"percent",'Raw Data'!$F:$F,"Number*"))/100 -> 0.995 | H29: =(SUMIFS('Raw Data'!$L:$L,'Raw Data'!$B:$B,$B$2,'Raw Data'!$J:$J,H$2,'Raw Data'!$K:$K,"native",'Raw Data'!$H:$H,"Purchases",'Raw Data'!$I:$I,"Non-QR Purchases",'Raw Data'!$M:$M,"percent",'Raw Data'!$F:$F,"Number*"))/100 -> 0.994 | I29: =(SUMIFS('Raw Data'!$L:$L,'Raw Data'!$B:$B,$B$2,'Raw Data'!$J:$J,I$2,'Raw Data'!$K:$K,"native",'Raw Data'!$H:$H,"Purchases",'Raw Data'!$I:$I,"Non-QR Purchases",'Raw Data'!$M:$M,"percent",'Raw Data'!$F:$F,"Number*"))/100 -> 0.994 | J29: =(SUMIFS('Raw Data'!$L:$L,'Raw Data'!$B:$B,$B$2,'Raw Data'!$J:$J,J$2,'Raw Data'!$K:$K,"native",'Raw Data'!$H:$H,"Purchases",'Raw Data'!$I:$I,"Non-QR Purchases",'Raw Data'!$M:$M,"percent",'Raw Data'!$F:$F,"Number*"))/100 -> 0.993 | ... M29: =(SUMIFS('Raw Data'!$L:$L,'Raw Data'!$B:$B,$B$2,'Raw Data'!$J:$J,M$2,'Raw Data'!$K:$K,"native",'Raw Data'!$H:$H,"Purchases",'Raw Data'!$I:$I,"Non-QR Purchases",'Raw Data'!$M:$M,"percent",'Raw Data'!$F:$F,"Number*"))/100 -> 0.993 | Z29: =(SUMIFS('Raw Data'!$L:$L,'Raw Data'!$B:$B,$B$2,'Raw Data'!$J:$J,Z$2,'Raw Data'!$K:$K,"native",'Raw Data'!$H:$H,"Purchases",'Raw Data'!$I:$I,"Non-QR Purchases",'Raw Data'!$M:$M,"percent",'Raw Data'!$F:$F,"Number*"))/100 -> 0.992
A30: Transactions | B30: Purchases: QR Purchases | C30: =(SUMIFS('Raw Data'!$L:$L,'Raw Data'!$B:$B,$B$2,'Raw Data'!$J:$J,C$2,'Raw Data'!$K:$K,"native",'Raw Data'!$H:$H,"Purchases",'Raw Data'!$I:$I,"QR Purchases",'Raw Data'!$M:$M,"percent",'Raw Data'!$F:$F,"Number*"))/100 -> 0.005 | D30: =(SUMIFS('Raw Data'!$L:$L,'Raw Data'!$B:$B,$B$2,'Raw Data'!$J:$J,D$2,'Raw Data'!$K:$K,"native",'Raw Data'!$H:$H,"Purchases",'Raw Data'!$I:$I,"QR Purchases",'Raw Data'!$M:$M,"percent",'Raw Data'!$F:$F,"Number*"))/100 -> 0.005 | E30: =(SUMIFS('Raw Data'!$L:$L,'Raw Data'!$B:$B,$B$2,'Raw Data'!$J:$J,E$2,'Raw Data'!$K:$K,"native",'Raw Data'!$H:$H,"Purchases",'Raw Data'!$I:$I,"QR Purchases",'Raw Data'!$M:$M,"percent",'Raw Data'!$F:$F,"Number*"))/100 -> 0.005 | F30: =(SUMIFS('Raw Data'!$L:$L,'Raw Data'!$B:$B,$B$2,'Raw Data'!$J:$J,F$2,'Raw Data'!$K:$K,"native",'Raw Data'!$H:$H,"Purchases",'Raw Data'!$I:$I,"QR Purchases",'Raw Data'!$M:$M,"percent",'Raw Data'!$F:$F,"Number*"))/100 -> 0.005 | G30: =(SUMIFS('Raw Data'!$L:$L,'Raw Data'!$B:$B,$B$2,'Raw Data'!$J:$J,G$2,'Raw Data'!$K:$K,"native",'Raw Data'!$H:$H,"Purchases",'Raw Data'!$I:$I,"QR Purchases",'Raw Data'!$M:$M,"percent",'Raw Data'!$F:$F,"Number*"))/100 -> 0.005 | H30: =(SUMIFS('Raw Data'!$L:$L,'Raw Data'!$B:$B,$B$2,'Raw Data'!$J:$J,H$2,'Raw Data'!$K:$K,"native",'Raw Data'!$H:$H,"Purchases",'Raw Data'!$I:$I,"QR Purchases",'Raw Data'!$M:$M,"percent",'Raw Data'!$F:$F,"Number*"))/100 -> 0.006 | I30: =(SUMIFS('Raw Data'!$L:$L,'Raw Data'!$B:$B,$B$2,'Raw Data'!$J:$J,I$2,'Raw Data'!$K:$K,"native",'Raw Data'!$H:$H,"Purchases",'Raw Data'!$I:$I,"QR Purchases",'Raw Data'!$M:$M,"percent",'Raw Data'!$F:$F,"Number*"))/100 -> 0.006 | J30: =(SUMIFS('Raw Data'!$L:$L,'Raw Data'!$B:$B,$B$2,'Raw Data'!$J:$J,J$2,'Raw Data'!$K:$K,"native",'Raw Data'!$H:$H,"Purchases",'Raw Data'!$I:$I,"QR Purchases",'Raw Data'!$M:$M,"percent",'Raw Data'!$F:$F,"Number*"))/100 -> 0.007 | ... M30: =(SUMIFS('Raw Data'!$L:$L,'Raw Data'!$B:$B,$B$2,'Raw Data'!$J:$J,M$2,'Raw Data'!$K:$K,"native",'Raw Data'!$H:$H,"Purchases",'Raw Data'!$I:$I,"QR Purchases",'Raw Data'!$M:$M,"percent",'Raw Data'!$F:$F,"Number*"))/100 -> 0.007 | Z30: =(SUMIFS('Raw Data'!$L:$L,'Raw Data'!$B:$B,$B$2,'Raw Data'!$J:$J,Z$2,'Raw Data'!$K:$K,"native",'Raw Data'!$H:$H,"Purchases",'Raw Data'!$I:$I,"QR Purchases",'Raw Data'!$M:$M,"percent",'Raw Data'!$F:$F,"Number*"))/100 -> 0.008
A31: TRANSACTIONS BY TRANSACTION TYPE (Value, JOD)
A32: Transactions | B32: Money Transfers | C32: =SUMIFS('Raw Data'!$L:$L,'Raw Data'!$B:$B,$B$2,'Raw Data'!$J:$J,C$2,'Raw Data'!$K:$K,"native",'Raw Data'!$H:$H,"Money Transfers",'Raw Data'!$I:$I,"",'Raw Data'!$M:$M,"JOD") -> 936100000 | D32: =SUMIFS('Raw Data'!$L:$L,'Raw Data'!$B:$B,$B$2,'Raw Data'!$J:$J,D$2,'Raw Data'!$K:$K,"native",'Raw Data'!$H:$H,"Money Transfers",'Raw Data'!$I:$I,"",'Raw Data'!$M:$M,"JOD") -> 992600000 | E32: =SUMIFS('Raw Data'!$L:$L,'Raw Data'!$B:$B,$B$2,'Raw Data'!$J:$J,E$2,'Raw Data'!$K:$K,"native",'Raw Data'!$H:$H,"Money Transfers",'Raw Data'!$I:$I,"",'Raw Data'!$M:$M,"JOD") -> 954200000 | F32: =SUMIFS('Raw Data'!$L:$L,'Raw Data'!$B:$B,$B$2,'Raw Data'!$J:$J,F$2,'Raw Data'!$K:$K,"native",'Raw Data'!$H:$H,"Money Transfers",'Raw Data'!$I:$I,"",'Raw Data'!$M:$M,"JOD") -> 1080000000 | G32: =SUMIFS('Raw Data'!$L:$L,'Raw Data'!$B:$B,$B$2,'Raw Data'!$J:$J,G$2,'Raw Data'!$K:$K,"native",'Raw Data'!$H:$H,"Money Transfers",'Raw Data'!$I:$I,"",'Raw Data'!$M:$M,"JOD") -> 1080000000 | H32: =SUMIFS('Raw Data'!$L:$L,'Raw Data'!$B:$B,$B$2,'Raw Data'!$J:$J,H$2,'Raw Data'!$K:$K,"native",'Raw Data'!$H:$H,"Money Transfers",'Raw Data'!$I:$I,"",'Raw Data'!$M:$M,"JOD") -> 1030000000 | I32: =SUMIFS('Raw Data'!$L:$L,'Raw Data'!$B:$B,$B$2,'Raw Data'!$J:$J,I$2,'Raw Data'!$K:$K,"native",'Raw Data'!$H:$H,"Money Transfers",'Raw Data'!$I:$I,"",'Raw Data'!$M:$M,"JOD") -> 1260000000 | J32: =SUMIFS('Raw Data'!$L:$L,'Raw Data'!$B:$B,$B$2,'Raw Data'!$J:$J,J$2,'Raw Data'!$K:$K,"native",'Raw Data'!$H:$H,"Money Transfers",'Raw Data'!$I:$I,"",'Raw Data'!$M:$M,"JOD") -> 1170000000 | ... Z32: =SUMIFS('Raw Data'!$L:$L,'Raw Data'!$B:$B,$B$2,'Raw Data'!$J:$J,Z$2,'Raw Data'!$K:$K,"native",'Raw Data'!$H:$H,"Money Transfers",'Raw Data'!$I:$I,"",'Raw Data'!$M:$M,"JOD") -> 1730000000
A33: Transactions | B33: Purchases | C33: =SUMIFS('Raw Data'!$L:$L,'Raw Data'!$B:$B,$B$2,'Raw Data'!$J:$J,C$2,'Raw Data'!$K:$K,"native",'Raw Data'!$H:$H,"Purchases",'Raw Data'!$I:$I,"",'Raw Data'!$M:$M,"JOD") -> 208200000 | D33: =SUMIFS('Raw Data'!$L:$L,'Raw Data'!$B:$B,$B$2,'Raw Data'!$J:$J,D$2,'Raw Data'!$K:$K,"native",'Raw Data'!$H:$H,"Purchases",'Raw Data'!$I:$I,"",'Raw Data'!$M:$M,"JOD") -> 227200000 | E33: =SUMIFS('Raw Data'!$L:$L,'Raw Data'!$B:$B,$B$2,'Raw Data'!$J:$J,E$2,'Raw Data'!$K:$K,"native",'Raw Data'!$H:$H,"Purchases",'Raw Data'!$I:$I,"",'Raw Data'!$M:$M,"JOD") -> 220900000 | F33: =SUMIFS('Raw Data'!$L:$L,'Raw Data'!$B:$B,$B$2,'Raw Data'!$J:$J,F$2,'Raw Data'!$K:$K,"native",'Raw Data'!$H:$H,"Purchases",'Raw Data'!$I:$I,"",'Raw Data'!$M:$M,"JOD") -> 253700000 | G33: =SUMIFS('Raw Data'!$L:$L,'Raw Data'!$B:$B,$B$2,'Raw Data'!$J:$J,G$2,'Raw Data'!$K:$K,"native",'Raw Data'!$H:$H,"Purchases",'Raw Data'!$I:$I,"",'Raw Data'!$M:$M,"JOD") -> 259000000 | H33: =SUMIFS('Raw Data'!$L:$L,'Raw Data'!$B:$B,$B$2,'Raw Data'!$J:$J,H$2,'Raw Data'!$K:$K,"native",'Raw Data'!$H:$H,"Purchases",'Raw Data'!$I:$I,"",'Raw Data'!$M:$M,"JOD") -> 248700000 | I33: =SUMIFS('Raw Data'!$L:$L,'Raw Data'!$B:$B,$B$2,'Raw Data'!$J:$J,I$2,'Raw Data'!$K:$K,"native",'Raw Data'!$H:$H,"Purchases",'Raw Data'!$I:$I,"",'Raw Data'!$M:$M,"JOD") -> 300140000 | J33: =SUMIFS('Raw Data'!$L:$L,'Raw Data'!$B:$B,$B$2,'Raw Data'!$J:$J,J$2,'Raw Data'!$K:$K,"native",'Raw Data'!$H:$H,"Purchases",'Raw Data'!$I:$I,"",'Raw Data'!$M:$M,"JOD") -> 312800000 | ... Z33: =SUMIFS('Raw Data'!$L:$L,'Raw Data'!$B:$B,$B$2,'Raw Data'!$J:$J,Z$2,'Raw Data'!$K:$K,"native",'Raw Data'!$H:$H,"Purchases",'Raw Data'!$I:$I,"",'Raw Data'!$M:$M,"JOD") -> 694700000
A34: TRANSACTIONS BY TYPE — DETAIL (%)
A35: Transactions | B35: Money Transfers: Other | C35: =(SUMIFS('Raw Data'!$L:$L,'Raw Data'!$B:$B,$B$2,'Raw Data'!$J:$J,C$2,'Raw Data'!$K:$K,"native",'Raw Data'!$H:$H,"Money Transfers",'Raw Data'!$I:$I,"Other",'Raw Data'!$M:$M,"percent",'Raw Data'!$F:$F,"Value*"))/100 -> 0.053 | D35: =(SUMIFS('Raw Data'!$L:$L,'Raw Data'!$B:$B,$B$2,'Raw Data'!$J:$J,D$2,'Raw Data'!$K:$K,"native",'Raw Data'!$H:$H,"Money Transfers",'Raw Data'!$I:$I,"Other",'Raw Data'!$M:$M,"percent",'Raw Data'!$F:$F,"Value*"))/100 -> 0.056 | E35: =(SUMIFS('Raw Data'!$L:$L,'Raw Data'!$B:$B,$B$2,'Raw Data'!$J:$J,E$2,'Raw Data'!$K:$K,"native",'Raw Data'!$H:$H,"Money Transfers",'Raw Data'!$I:$I,"Other",'Raw Data'!$M:$M,"percent",'Raw Data'!$F:$F,"Value*"))/100 -> 0.0568 | F35: =(SUMIFS('Raw Data'!$L:$L,'Raw Data'!$B:$B,$B$2,'Raw Data'!$J:$J,F$2,'Raw Data'!$K:$K,"native",'Raw Data'!$H:$H,"Money Transfers",'Raw Data'!$I:$I,"Other",'Raw Data'!$M:$M,"percent",'Raw Data'!$F:$F,"Value*"))/100 -> 0.0572 | G35: =(SUMIFS('Raw Data'!$L:$L,'Raw Data'!$B:$B,$B$2,'Raw Data'!$J:$J,G$2,'Raw Data'!$K:$K,"native",'Raw Data'!$H:$H,"Money Transfers",'Raw Data'!$I:$I,"Other",'Raw Data'!$M:$M,"percent",'Raw Data'!$F:$F,"Value*"))/100 -> 0.057 | H35: =(SUMIFS('Raw Data'!$L:$L,'Raw Data'!$B:$B,$B$2,'Raw Data'!$J:$J,H$2,'Raw Data'!$K:$K,"native",'Raw Data'!$H:$H,"Money Transfers",'Raw Data'!$I:$I,"Other",'Raw Data'!$M:$M,"percent",'Raw Data'!$F:$F,"Value*"))/100 -> 0.058 | I35: =(SUMIFS('Raw Data'!$L:$L,'Raw Data'!$B:$B,$B$2,'Raw Data'!$J:$J,I$2,'Raw Data'!$K:$K,"native",'Raw Data'!$H:$H,"Money Transfers",'Raw Data'!$I:$I,"Other",'Raw Data'!$M:$M,"percent",'Raw Data'!$F:$F,"Value*"))/100 -> 0.06 | J35: =(SUMIFS('Raw Data'!$L:$L,'Raw Data'!$B:$B,$B$2,'Raw Data'!$J:$J,J$2,'Raw Data'!$K:$K,"native",'Raw Data'!$H:$H,"Money Transfers",'Raw Data'!$I:$I,"Other",'Raw Data'!$M:$M,"percent",'Raw Data'!$F:$F,"Value*"))/100 -> 0.055 | ... M35: =(SUMIFS('Raw Data'!$L:$L,'Raw Data'!$B:$B,$B$2,'Raw Data'!$J:$J,M$2,'Raw Data'!$K:$K,"native",'Raw Data'!$H:$H,"Money Transfers",'Raw Data'!$I:$I,"Other",'Raw Data'!$M:$M,"percent",'Raw Data'!$F:$F,"Value*"))/100 -> 0.03 | Z35: =(SUMIFS('Raw Data'!$L:$L,'Raw Data'!$B:$B,$B$2,'Raw Data'!$J:$J,Z$2,'Raw Data'!$K:$K,"native",'Raw Data'!$H:$H,"Money Transfers",'Raw Data'!$I:$I,"Other",'Raw Data'!$M:$M,"percent",'Raw Data'!$F:$F,"Value*"))/100 -> 0.059
A36: Transactions | B36: Money Transfers: Transfer to Family/Friends | C36: =(SUMIFS('Raw Data'!$L:$L,'Raw Data'!$B:$B,$B$2,'Raw Data'!$J:$J,C$2,'Raw Data'!$K:$K,"native",'Raw Data'!$H:$H,"Money Transfers",'Raw Data'!$I:$I,"Transfer to Family/Friends",'Raw Data'!$M:$M,"percent",'Raw Data'!$F:$F,"Value*"))/100 -> 0.738 | D36: =(SUMIFS('Raw Data'!$L:$L,'Raw Data'!$B:$B,$B$2,'Raw Data'!$J:$J,D$2,'Raw Data'!$K:$K,"native",'Raw Data'!$H:$H,"Money Transfers",'Raw Data'!$I:$I,"Transfer to Family/Friends",'Raw Data'!$M:$M,"percent",'Raw Data'!$F:$F,"Value*"))/100 -> 0.731 | E36: =(SUMIFS('Raw Data'!$L:$L,'Raw Data'!$B:$B,$B$2,'Raw Data'!$J:$J,E$2,'Raw Data'!$K:$K,"native",'Raw Data'!$H:$H,"Money Transfers",'Raw Data'!$I:$I,"Transfer to Family/Friends",'Raw Data'!$M:$M,"percent",'Raw Data'!$F:$F,"Value*"))/100 -> 0.7286 | F36: =(SUMIFS('Raw Data'!$L:$L,'Raw Data'!$B:$B,$B$2,'Raw Data'!$J:$J,F$2,'Raw Data'!$K:$K,"native",'Raw Data'!$H:$H,"Money Transfers",'Raw Data'!$I:$I,"Transfer to Family/Friends",'Raw Data'!$M:$M,"percent",'Raw Data'!$F:$F,"Value*"))/100 -> 0.7215 | G36: =(SUMIFS('Raw Data'!$L:$L,'Raw Data'!$B:$B,$B$2,'Raw Data'!$J:$J,G$2,'Raw Data'!$K:$K,"native",'Raw Data'!$H:$H,"Money Transfers",'Raw Data'!$I:$I,"Transfer to Family/Friends",'Raw Data'!$M:$M,"percent",'Raw Data'!$F:$F,"Value*"))/100 -> 0.722 | H36: =(SUMIFS('Raw Data'!$L:$L,'Raw Data'!$B:$B,$B$2,'Raw Data'!$J:$J,H$2,'Raw Data'!$K:$K,"native",'Raw Data'!$H:$H,"Money Transfers",'Raw Data'!$I:$I,"Transfer to Family/Friends",'Raw Data'!$M:$M,"percent",'Raw Data'!$F:$F,"Value*"))/100 -> 0.724 | I36: =(SUMIFS('Raw Data'!$L:$L,'Raw Data'!$B:$B,$B$2,'Raw Data'!$J:$J,I$2,'Raw Data'!$K:$K,"native",'Raw Data'!$H:$H,"Money Transfers",'Raw Data'!$I:$I,"Transfer to Family/Friends",'Raw Data'!$M:$M,"percent",'Raw Data'!$F:$F,"Value*"))/100 -> 0.728 | J36: =(SUMIFS('Raw Data'!$L:$L,'Raw Data'!$B:$B,$B$2,'Raw Data'!$J:$J,J$2,'Raw Data'!$K:$K,"native",'Raw Data'!$H:$H,"Money Transfers",'Raw Data'!$I:$I,"Transfer to Family/Friends",'Raw Data'!$M:$M,"percent",'Raw Data'!$F:$F,"Value*"))/100 -> 0.716 | ... M36: =(SUMIFS('Raw Data'!$L:$L,'Raw Data'!$B:$B,$B$2,'Raw Data'!$J:$J,M$2,'Raw Data'!$K:$K,"native",'Raw Data'!$H:$H,"Money Transfers",'Raw Data'!$I:$I,"Transfer to Family/Friends",'Raw Data'!$M:$M,"percent",'Raw Data'!$F:$F,"Value*"))/100 -> 0.753 | Z36: =(SUMIFS('Raw Data'!$L:$L,'Raw Data'!$B:$B,$B$2,'Raw Data'!$J:$J,Z$2,'Raw Data'!$K:$K,"native",'Raw Data'!$H:$H,"Money Transfers",'Raw Data'!$I:$I,"Transfer to Family/Friends",'Raw Data'!$M:$M,"percent",'Raw Data'!$F:$F,"Value*"))/100 -> 0.718
A37: Transactions | B37: Money Transfers: Transfer to Own Account | C37: =(SUMIFS('Raw Data'!$L:$L,'Raw Data'!$B:$B,$B$2,'Raw Data'!$J:$J,C$2,'Raw Data'!$K:$K,"native",'Raw Data'!$H:$H,"Money Transfers",'Raw Data'!$I:$I,"Transfer to Own Account",'Raw Data'!$M:$M,"percent",'Raw Data'!$F:$F,"Value*"))/100 -> 0.209 | D37: =(SUMIFS('Raw Data'!$L:$L,'Raw Data'!$B:$B,$B$2,'Raw Data'!$J:$J,D$2,'Raw Data'!$K:$K,"native",'Raw Data'!$H:$H,"Money Transfers",'Raw Data'!$I:$I,"Transfer to Own Account",'Raw Data'!$M:$M,"percent",'Raw Data'!$F:$F,"Value*"))/100 -> 0.213 | E37: =(SUMIFS('Raw Data'!$L:$L,'Raw Data'!$B:$B,$B$2,'Raw Data'!$J:$J,E$2,'Raw Data'!$K:$K,"native",'Raw Data'!$H:$H,"Money Transfers",'Raw Data'!$I:$I,"Transfer to Own Account",'Raw Data'!$M:$M,"percent",'Raw Data'!$F:$F,"Value*"))/100 -> 0.2146 | F37: =(SUMIFS('Raw Data'!$L:$L,'Raw Data'!$B:$B,$B$2,'Raw Data'!$J:$J,F$2,'Raw Data'!$K:$K,"native",'Raw Data'!$H:$H,"Money Transfers",'Raw Data'!$I:$I,"Transfer to Own Account",'Raw Data'!$M:$M,"percent",'Raw Data'!$F:$F,"Value*"))/100 -> 0.2213 | G37: =(SUMIFS('Raw Data'!$L:$L,'Raw Data'!$B:$B,$B$2,'Raw Data'!$J:$J,G$2,'Raw Data'!$K:$K,"native",'Raw Data'!$H:$H,"Money Transfers",'Raw Data'!$I:$I,"Transfer to Own Account",'Raw Data'!$M:$M,"percent",'Raw Data'!$F:$F,"Value*"))/100 -> 0.221 | H37: =(SUMIFS('Raw Data'!$L:$L,'Raw Data'!$B:$B,$B$2,'Raw Data'!$J:$J,H$2,'Raw Data'!$K:$K,"native",'Raw Data'!$H:$H,"Money Transfers",'Raw Data'!$I:$I,"Transfer to Own Account",'Raw Data'!$M:$M,"percent",'Raw Data'!$F:$F,"Value*"))/100 -> 0.218 | I37: =(SUMIFS('Raw Data'!$L:$L,'Raw Data'!$B:$B,$B$2,'Raw Data'!$J:$J,I$2,'Raw Data'!$K:$K,"native",'Raw Data'!$H:$H,"Money Transfers",'Raw Data'!$I:$I,"Transfer to Own Account",'Raw Data'!$M:$M,"percent",'Raw Data'!$F:$F,"Value*"))/100 -> 0.212 | J37: =(SUMIFS('Raw Data'!$L:$L,'Raw Data'!$B:$B,$B$2,'Raw Data'!$J:$J,J$2,'Raw Data'!$K:$K,"native",'Raw Data'!$H:$H,"Money Transfers",'Raw Data'!$I:$I,"Transfer to Own Account",'Raw Data'!$M:$M,"percent",'Raw Data'!$F:$F,"Value*"))/100 -> 0.229 | ... M37: =(SUMIFS('Raw Data'!$L:$L,'Raw Data'!$B:$B,$B$2,'Raw Data'!$J:$J,M$2,'Raw Data'!$K:$K,"native",'Raw Data'!$H:$H,"Money Transfers",'Raw Data'!$I:$I,"Transfer to Own Account",'Raw Data'!$M:$M,"percent",'Raw Data'!$F:$F,"Value*"))/100 -> 0.217 | Z37: =(SUMIFS('Raw Data'!$L:$L,'Raw Data'!$B:$B,$B$2,'Raw Data'!$J:$J,Z$2,'Raw Data'!$K:$K,"native",'Raw Data'!$H:$H,"Money Transfers",'Raw Data'!$I:$I,"Transfer to Own Account",'Raw Data'!$M:$M,"percent",'Raw Data'!$F:$F,"Value*"))/100 -> 0.223
A38: Transactions | B38: Purchases: Non-QR Purchases | C38: =(SUMIFS('Raw Data'!$L:$L,'Raw Data'!$B:$B,$B$2,'Raw Data'!$J:$J,C$2,'Raw Data'!$K:$K,"native",'Raw Data'!$H:$H,"Purchases",'Raw Data'!$I:$I,"Non-QR Purchases",'Raw Data'!$M:$M,"percent",'Raw Data'!$F:$F,"Value*"))/100 -> 0.9992 | D38: =(SUMIFS('Raw Data'!$L:$L,'Raw Data'!$B:$B,$B$2,'Raw Data'!$J:$J,D$2,'Raw Data'!$K:$K,"native",'Raw Data'!$H:$H,"Purchases",'Raw Data'!$I:$I,"Non-QR Purchases",'Raw Data'!$M:$M,"percent",'Raw Data'!$F:$F,"Value*"))/100 -> 0.9994 | E38: =(SUMIFS('Raw Data'!$L:$L,'Raw Data'!$B:$B,$B$2,'Raw Data'!$J:$J,E$2,'Raw Data'!$K:$K,"native",'Raw Data'!$H:$H,"Purchases",'Raw Data'!$I:$I,"Non-QR Purchases",'Raw Data'!$M:$M,"percent",'Raw Data'!$F:$F,"Value*"))/100 -> 0.9992 | F38: =(SUMIFS('Raw Data'!$L:$L,'Raw Data'!$B:$B,$B$2,'Raw Data'!$J:$J,F$2,'Raw Data'!$K:$K,"native",'Raw Data'!$H:$H,"Purchases",'Raw Data'!$I:$I,"Non-QR Purchases",'Raw Data'!$M:$M,"percent",'Raw Data'!$F:$F,"Value*"))/100 -> 0.9993 | G38: =(SUMIFS('Raw Data'!$L:$L,'Raw Data'!$B:$B,$B$2,'Raw Data'!$J:$J,G$2,'Raw Data'!$K:$K,"native",'Raw Data'!$H:$H,"Purchases",'Raw Data'!$I:$I,"Non-QR Purchases",'Raw Data'!$M:$M,"percent",'Raw Data'!$F:$F,"Value*"))/100 -> 0.9993 | H38: =(SUMIFS('Raw Data'!$L:$L,'Raw Data'!$B:$B,$B$2,'Raw Data'!$J:$J,H$2,'Raw Data'!$K:$K,"native",'Raw Data'!$H:$H,"Purchases",'Raw Data'!$I:$I,"Non-QR Purchases",'Raw Data'!$M:$M,"percent",'Raw Data'!$F:$F,"Value*"))/100 -> 0.9992 | I38: =(SUMIFS('Raw Data'!$L:$L,'Raw Data'!$B:$B,$B$2,'Raw Data'!$J:$J,I$2,'Raw Data'!$K:$K,"native",'Raw Data'!$H:$H,"Purchases",'Raw Data'!$I:$I,"Non-QR Purchases",'Raw Data'!$M:$M,"percent",'Raw Data'!$F:$F,"Value*"))/100 -> 0.9993 | J38: =(SUMIFS('Raw Data'!$L:$L,'Raw Data'!$B:$B,$B$2,'Raw Data'!$J:$J,J$2,'Raw Data'!$K:$K,"native",'Raw Data'!$H:$H,"Purchases",'Raw Data'!$I:$I,"Non-QR Purchases",'Raw Data'!$M:$M,"percent",'Raw Data'!$F:$F,"Value*"))/100 -> 0.9992 | ... M38: =(SUMIFS('Raw Data'!$L:$L,'Raw Data'!$B:$B,$B$2,'Raw Data'!$J:$J,M$2,'Raw Data'!$K:$K,"native",'Raw Data'!$H:$H,"Purchases",'Raw Data'!$I:$I,"Non-QR Purchases",'Raw Data'!$M:$M,"percent",'Raw Data'!$F:$F,"Value*"))/100 -> 0.9992 | Z38: =(SUMIFS('Raw Data'!$L:$L,'Raw Data'!$B:$B,$B$2,'Raw Data'!$J:$J,Z$2,'Raw Data'!$K:$K,"native",'Raw Data'!$H:$H,"Purchases",'Raw Data'!$I:$I,"Non-QR Purchases",'Raw Data'!$M:$M,"percent",'Raw Data'!$F:$F,"Value*"))/100 -> 0.9991
A39: Transactions | B39: Purchases: QR Purchases | C39: =(SUMIFS('Raw Data'!$L:$L,'Raw Data'!$B:$B,$B$2,'Raw Data'!$J:$J,C$2,'Raw Data'!$K:$K,"native",'Raw Data'!$H:$H,"Purchases",'Raw Data'!$I:$I,"QR Purchases",'Raw Data'!$M:$M,"percent",'Raw Data'!$F:$F,"Value*"))/100 -> 0.0008 | D39: =(SUMIFS('Raw Data'!$L:$L,'Raw Data'!$B:$B,$B$2,'Raw Data'!$J:$J,D$2,'Raw Data'!$K:$K,"native",'Raw Data'!$H:$H,"Purchases",'Raw Data'!$I:$I,"QR Purchases",'Raw Data'!$M:$M,"percent",'Raw Data'!$F:$F,"Value*"))/100 -> 0.0006 | E39: =(SUMIFS('Raw Data'!$L:$L,'Raw Data'!$B:$B,$B$2,'Raw Data'!$J:$J,E$2,'Raw Data'!$K:$K,"native",'Raw Data'!$H:$H,"Purchases",'Raw Data'!$I:$I,"QR Purchases",'Raw Data'!$M:$M,"percent",'Raw Data'!$F:$F,"Value*"))/100 -> 0.0008 | F39: =(SUMIFS('Raw Data'!$L:$L,'Raw Data'!$B:$B,$B$2,'Raw Data'!$J:$J,F$2,'Raw Data'!$K:$K,"native",'Raw Data'!$H:$H,"Purchases",'Raw Data'!$I:$I,"QR Purchases",'Raw Data'!$M:$M,"percent",'Raw Data'!$F:$F,"Value*"))/100 -> 0.0007 | G39: =(SUMIFS('Raw Data'!$L:$L,'Raw Data'!$B:$B,$B$2,'Raw Data'!$J:$J,G$2,'Raw Data'!$K:$K,"native",'Raw Data'!$H:$H,"Purchases",'Raw Data'!$I:$I,"QR Purchases",'Raw Data'!$M:$M,"percent",'Raw Data'!$F:$F,"Value*"))/100 -> 0.0007 | H39: =(SUMIFS('Raw Data'!$L:$L,'Raw Data'!$B:$B,$B$2,'Raw Data'!$J:$J,H$2,'Raw Data'!$K:$K,"native",'Raw Data'!$H:$H,"Purchases",'Raw Data'!$I:$I,"QR Purchases",'Raw Data'!$M:$M,"percent",'Raw Data'!$F:$F,"Value*"))/100 -> 0.0008 | I39: =(SUMIFS('Raw Data'!$L:$L,'Raw Data'!$B:$B,$B$2,'Raw Data'!$J:$J,I$2,'Raw Data'!$K:$K,"native",'Raw Data'!$H:$H,"Purchases",'Raw Data'!$I:$I,"QR Purchases",'Raw Data'!$M:$M,"percent",'Raw Data'!$F:$F,"Value*"))/100 -> 0.0007 | J39: =(SUMIFS('Raw Data'!$L:$L,'Raw Data'!$B:$B,$B$2,'Raw Data'!$J:$J,J$2,'Raw Data'!$K:$K,"native",'Raw Data'!$H:$H,"Purchases",'Raw Data'!$I:$I,"QR Purchases",'Raw Data'!$M:$M,"percent",'Raw Data'!$F:$F,"Value*"))/100 -> 0.0008 | ... M39: =(SUMIFS('Raw Data'!$L:$L,'Raw Data'!$B:$B,$B$2,'Raw Data'!$J:$J,M$2,'Raw Data'!$K:$K,"native",'Raw Data'!$H:$H,"Purchases",'Raw Data'!$I:$I,"QR Purchases",'Raw Data'!$M:$M,"percent",'Raw Data'!$F:$F,"Value*"))/100 -> 0.0008 | Z39: =(SUMIFS('Raw Data'!$L:$L,'Raw Data'!$B:$B,$B$2,'Raw Data'!$J:$J,Z$2,'Raw Data'!$K:$K,"native",'Raw Data'!$H:$H,"Purchases",'Raw Data'!$I:$I,"QR Purchases",'Raw Data'!$M:$M,"percent",'Raw Data'!$F:$F,"Value*"))/100 -> 0.0009
A40: Transactions | B40: Purchases: Non-QR
A41: TRANSACTIONS BY DIRECTION (ON US / OFF US) (Number)
A42: Transactions | B42: Off Us | C42: =SUMIFS('Raw Data'!$L:$L,'Raw Data'!$B:$B,$B$2,'Raw Data'!$J:$J,C$2,'Raw Data'!$K:$K,"native",'Raw Data'!$H:$H,"Off Us",'Raw Data'!$I:$I,"",'Raw Data'!$M:$M,"count") -> 3710000 | D42: =SUMIFS('Raw Data'!$L:$L,'Raw Data'!$B:$B,$B$2,'Raw Data'!$J:$J,D$2,'Raw Data'!$K:$K,"native",'Raw Data'!$H:$H,"Off Us",'Raw Data'!$I:$I,"",'Raw Data'!$M:$M,"count") -> 4170000 | E42: =SUMIFS('Raw Data'!$L:$L,'Raw Data'!$B:$B,$B$2,'Raw Data'!$J:$J,E$2,'Raw Data'!$K:$K,"native",'Raw Data'!$H:$H,"Off Us",'Raw Data'!$I:$I,"",'Raw Data'!$M:$M,"count") -> 4190000 | F42: =SUMIFS('Raw Data'!$L:$L,'Raw Data'!$B:$B,$B$2,'Raw Data'!$J:$J,F$2,'Raw Data'!$K:$K,"native",'Raw Data'!$H:$H,"Off Us",'Raw Data'!$I:$I,"",'Raw Data'!$M:$M,"count") -> 4650000 | G42: =SUMIFS('Raw Data'!$L:$L,'Raw Data'!$B:$B,$B$2,'Raw Data'!$J:$J,G$2,'Raw Data'!$K:$K,"native",'Raw Data'!$H:$H,"Off Us",'Raw Data'!$I:$I,"",'Raw Data'!$M:$M,"count") -> 4720000 | H42: =SUMIFS('Raw Data'!$L:$L,'Raw Data'!$B:$B,$B$2,'Raw Data'!$J:$J,H$2,'Raw Data'!$K:$K,"native",'Raw Data'!$H:$H,"Off Us",'Raw Data'!$I:$I,"",'Raw Data'!$M:$M,"count") -> 4510000 | I42: =SUMIFS('Raw Data'!$L:$L,'Raw Data'!$B:$B,$B$2,'Raw Data'!$J:$J,I$2,'Raw Data'!$K:$K,"native",'Raw Data'!$H:$H,"Off Us",'Raw Data'!$I:$I,"",'Raw Data'!$M:$M,"count") -> 5510000 | J42: =SUMIFS('Raw Data'!$L:$L,'Raw Data'!$B:$B,$B$2,'Raw Data'!$J:$J,J$2,'Raw Data'!$K:$K,"native",'Raw Data'!$H:$H,"Off Us",'Raw Data'!$I:$I,"",'Raw Data'!$M:$M,"count") -> 5160000 | ... Z42: =SUMIFS('Raw Data'!$L:$L,'Raw Data'!$B:$B,$B$2,'Raw Data'!$J:$J,Z$2,'Raw Data'!$K:$K,"native",'Raw Data'!$H:$H,"Off Us",'Raw Data'!$I:$I,"",'Raw Data'!$M:$M,"count") -> 9260000
A43: Transactions | B43: On Us | C43: =SUMIFS('Raw Data'!$L:$L,'Raw Data'!$B:$B,$B$2,'Raw Data'!$J:$J,C$2,'Raw Data'!$K:$K,"native",'Raw Data'!$H:$H,"On Us",'Raw Data'!$I:$I,"",'Raw Data'!$M:$M,"count") -> 1280000 | D43: =SUMIFS('Raw Data'!$L:$L,'Raw Data'!$B:$B,$B$2,'Raw Data'!$J:$J,D$2,'Raw Data'!$K:$K,"native",'Raw Data'!$H:$H,"On Us",'Raw Data'!$I:$I,"",'Raw Data'!$M:$M,"count") -> 1440000 | E43: =SUMIFS('Raw Data'!$L:$L,'Raw Data'!$B:$B,$B$2,'Raw Data'!$J:$J,E$2,'Raw Data'!$K:$K,"native",'Raw Data'!$H:$H,"On Us",'Raw Data'!$I:$I,"",'Raw Data'!$M:$M,"count") -> 1460000 | F43: =SUMIFS('Raw Data'!$L:$L,'Raw Data'!$B:$B,$B$2,'Raw Data'!$J:$J,F$2,'Raw Data'!$K:$K,"native",'Raw Data'!$H:$H,"On Us",'Raw Data'!$I:$I,"",'Raw Data'!$M:$M,"count") -> 1620000 | G43: =SUMIFS('Raw Data'!$L:$L,'Raw Data'!$B:$B,$B$2,'Raw Data'!$J:$J,G$2,'Raw Data'!$K:$K,"native",'Raw Data'!$H:$H,"On Us",'Raw Data'!$I:$I,"",'Raw Data'!$M:$M,"count") -> 1670000 | H43: =SUMIFS('Raw Data'!$L:$L,'Raw Data'!$B:$B,$B$2,'Raw Data'!$J:$J,H$2,'Raw Data'!$K:$K,"native",'Raw Data'!$H:$H,"On Us",'Raw Data'!$I:$I,"",'Raw Data'!$M:$M,"count") -> 1600000 | I43: =SUMIFS('Raw Data'!$L:$L,'Raw Data'!$B:$B,$B$2,'Raw Data'!$J:$J,I$2,'Raw Data'!$K:$K,"native",'Raw Data'!$H:$H,"On Us",'Raw Data'!$I:$I,"",'Raw Data'!$M:$M,"count") -> 1930000 | J43: =SUMIFS('Raw Data'!$L:$L,'Raw Data'!$B:$B,$B$2,'Raw Data'!$J:$J,J$2,'Raw Data'!$K:$K,"native",'Raw Data'!$H:$H,"On Us",'Raw Data'!$I:$I,"",'Raw Data'!$M:$M,"count") -> 1840000 | ... Z43: =SUMIFS('Raw Data'!$L:$L,'Raw Data'!$B:$B,$B$2,'Raw Data'!$J:$J,Z$2,'Raw Data'!$K:$K,"native",'Raw Data'!$H:$H,"On Us",'Raw Data'!$I:$I,"",'Raw Data'!$M:$M,"count") -> 3520000
A44: TRANSACTIONS BY DIRECTION (ON US / OFF US) (Value, JOD)
A45: Transactions | B45: Off Us | C45: =SUMIFS('Raw Data'!$L:$L,'Raw Data'!$B:$B,$B$2,'Raw Data'!$J:$J,C$2,'Raw Data'!$K:$K,"native",'Raw Data'!$H:$H,"Off Us",'Raw Data'!$I:$I,"",'Raw Data'!$M:$M,"JOD") -> 640400000 | D45: =SUMIFS('Raw Data'!$L:$L,'Raw Data'!$B:$B,$B$2,'Raw Data'!$J:$J,D$2,'Raw Data'!$K:$K,"native",'Raw Data'!$H:$H,"Off Us",'Raw Data'!$I:$I,"",'Raw Data'!$M:$M,"JOD") -> 680800000 | E45: =SUMIFS('Raw Data'!$L:$L,'Raw Data'!$B:$B,$B$2,'Raw Data'!$J:$J,E$2,'Raw Data'!$K:$K,"native",'Raw Data'!$H:$H,"Off Us",'Raw Data'!$I:$I,"",'Raw Data'!$M:$M,"JOD") -> 651100000 | F45: =SUMIFS('Raw Data'!$L:$L,'Raw Data'!$B:$B,$B$2,'Raw Data'!$J:$J,F$2,'Raw Data'!$K:$K,"native",'Raw Data'!$H:$H,"Off Us",'Raw Data'!$I:$I,"",'Raw Data'!$M:$M,"JOD") -> 743000000 | G45: =SUMIFS('Raw Data'!$L:$L,'Raw Data'!$B:$B,$B$2,'Raw Data'!$J:$J,G$2,'Raw Data'!$K:$K,"native",'Raw Data'!$H:$H,"Off Us",'Raw Data'!$I:$I,"",'Raw Data'!$M:$M,"JOD") -> 736600000 | H45: =SUMIFS('Raw Data'!$L:$L,'Raw Data'!$B:$B,$B$2,'Raw Data'!$J:$J,H$2,'Raw Data'!$K:$K,"native",'Raw Data'!$H:$H,"Off Us",'Raw Data'!$I:$I,"",'Raw Data'!$M:$M,"JOD") -> 700800000 | I45: =SUMIFS('Raw Data'!$L:$L,'Raw Data'!$B:$B,$B$2,'Raw Data'!$J:$J,I$2,'Raw Data'!$K:$K,"native",'Raw Data'!$H:$H,"Off Us",'Raw Data'!$I:$I,"",'Raw Data'!$M:$M,"JOD") -> 856400000 | J45: =SUMIFS('Raw Data'!$L:$L,'Raw Data'!$B:$B,$B$2,'Raw Data'!$J:$J,J$2,'Raw Data'!$K:$K,"native",'Raw Data'!$H:$H,"Off Us",'Raw Data'!$I:$I,"",'Raw Data'!$M:$M,"JOD") -> 802800000 | ... Z45: =SUMIFS('Raw Data'!$L:$L,'Raw Data'!$B:$B,$B$2,'Raw Data'!$J:$J,Z$2,'Raw Data'!$K:$K,"native",'Raw Data'!$H:$H,"Off Us",'Raw Data'!$I:$I,"",'Raw Data'!$M:$M,"JOD") -> 1140000000
A46: Transactions | B46: On Us | C46: =SUMIFS('Raw Data'!$L:$L,'Raw Data'!$B:$B,$B$2,'Raw Data'!$J:$J,C$2,'Raw Data'!$K:$K,"native",'Raw Data'!$H:$H,"On Us",'Raw Data'!$I:$I,"",'Raw Data'!$M:$M,"JOD") -> 162900000 | D46: =SUMIFS('Raw Data'!$L:$L,'Raw Data'!$B:$B,$B$2,'Raw Data'!$J:$J,D$2,'Raw Data'!$K:$K,"native",'Raw Data'!$H:$H,"On Us",'Raw Data'!$I:$I,"",'Raw Data'!$M:$M,"JOD") -> 172600000 | E46: =SUMIFS('Raw Data'!$L:$L,'Raw Data'!$B:$B,$B$2,'Raw Data'!$J:$J,E$2,'Raw Data'!$K:$K,"native",'Raw Data'!$H:$H,"On Us",'Raw Data'!$I:$I,"",'Raw Data'!$M:$M,"JOD") -> 167300000 | F46: =SUMIFS('Raw Data'!$L:$L,'Raw Data'!$B:$B,$B$2,'Raw Data'!$J:$J,F$2,'Raw Data'!$K:$K,"native",'Raw Data'!$H:$H,"On Us",'Raw Data'!$I:$I,"",'Raw Data'!$M:$M,"JOD") -> 190500000 | G46: =SUMIFS('Raw Data'!$L:$L,'Raw Data'!$B:$B,$B$2,'Raw Data'!$J:$J,G$2,'Raw Data'!$K:$K,"native",'Raw Data'!$H:$H,"On Us",'Raw Data'!$I:$I,"",'Raw Data'!$M:$M,"JOD") -> 189400000 | H46: =SUMIFS('Raw Data'!$L:$L,'Raw Data'!$B:$B,$B$2,'Raw Data'!$J:$J,H$2,'Raw Data'!$K:$K,"native",'Raw Data'!$H:$H,"On Us",'Raw Data'!$I:$I,"",'Raw Data'!$M:$M,"JOD") -> 181700000 | I46: =SUMIFS('Raw Data'!$L:$L,'Raw Data'!$B:$B,$B$2,'Raw Data'!$J:$J,I$2,'Raw Data'!$K:$K,"native",'Raw Data'!$H:$H,"On Us",'Raw Data'!$I:$I,"",'Raw Data'!$M:$M,"JOD") -> 223900000 | J46: =SUMIFS('Raw Data'!$L:$L,'Raw Data'!$B:$B,$B$2,'Raw Data'!$J:$J,J$2,'Raw Data'!$K:$K,"native",'Raw Data'!$H:$H,"On Us",'Raw Data'!$I:$I,"",'Raw Data'!$M:$M,"JOD") -> 207800000 | ... Z46: =SUMIFS('Raw Data'!$L:$L,'Raw Data'!$B:$B,$B$2,'Raw Data'!$J:$J,Z$2,'Raw Data'!$K:$K,"native",'Raw Data'!$H:$H,"On Us",'Raw Data'!$I:$I,"",'Raw Data'!$M:$M,"JOD") -> 328100000

Sheet JoMoPay
A1: JoMoPay (Mobile Wallets)
A2: Raw Data keys → (system | period) | B2: jomopay | C2: =RIGHT(C$3,4)&"-"&TEXT(MATCH(LEFT(C$3,3),{"Jan","Feb","Mar","Apr","May","Jun","Jul","Aug","Sep","Oct","Nov","Dec"},0),"00") -> 2024-09 | D2: =RIGHT(D$3,4)&"-"&TEXT(MATCH(LEFT(D$3,3),{"Jan","Feb","Mar","Apr","May","Jun","Jul","Aug","Sep","Oct","Nov","Dec"},0),"00") -> 2024-10 | E2: =RIGHT(E$3,4)&"-"&TEXT(MATCH(LEFT(E$3,3),{"Jan","Feb","Mar","Apr","May","Jun","Jul","Aug","Sep","Oct","Nov","Dec"},0),"00") -> 2024-11 | F2: =RIGHT(F$3,4)&"-"&TEXT(MATCH(LEFT(F$3,3),{"Jan","Feb","Mar","Apr","May","Jun","Jul","Aug","Sep","Oct","Nov","Dec"},0),"00") -> 2024-12 | G2: =RIGHT(G$3,4)&"-"&TEXT(MATCH(LEFT(G$3,3),{"Jan","Feb","Mar","Apr","May","Jun","Jul","Aug","Sep","Oct","Nov","Dec"},0),"00") -> 2025-01 | H2: =RIGHT(H$3,4)&"-"&TEXT(MATCH(LEFT(H$3,3),{"Jan","Feb","Mar","Apr","May","Jun","Jul","Aug","Sep","Oct","Nov","Dec"},0),"00") -> 2025-02 | I2: =RIGHT(I$3,4)&"-"&TEXT(MATCH(LEFT(I$3,3),{"Jan","Feb","Mar","Apr","May","Jun","Jul","Aug","Sep","Oct","Nov","Dec"},0),"00") -> 2025-03 | J2: =RIGHT(J$3,4)&"-"&TEXT(MATCH(LEFT(J$3,3),{"Jan","Feb","Mar","Apr","May","Jun","Jul","Aug","Sep","Oct","Nov","Dec"},0),"00") -> 2025-04 | ... Z2: =RIGHT(Z$3,4)&"-"&TEXT(MATCH(LEFT(Z$3,3),{"Jan","Feb","Mar","Apr","May","Jun","Jul","Aug","Sep","Oct","Nov","Dec"},0),"00") -> 2026-08
A3: Category | B3: Metric | C3: Sep 2024 | D3: Oct 2024 | E3: Nov 2024 | F3: Dec 2024 | G3: Jan 2025 | H3: Feb 2025 | I3: Mar 2025 | J3: Apr 2025 | K3: May 2025 | L3: Jun 2025 | M3: Jul 2025 | N3: Aug 2025 | O3: Sep 2025 | P3: Oct 2025 | Q3: Nov 2025 | R3: Dec 2025 | S3: Jan 2026 | T3: Feb 2026 | U3: Mar 2026 | V3: Apr 2026 | W3: May 2026 | X3: Jun 2026 | Y3: Jul 2026 | Z3: Aug 2026
A4: USERS BY NATIONALITY (Number)
A5: Users | B5: Jordanian | C5: =SUMIFS('Raw Data'!$L:$L,'Raw Data'!$B:$B,$B$2,'Raw Data'!$J:$J,C$2,'Raw Data'!$K:$K,"native",'Raw Data'!$H:$H,"Jordanian",'Raw Data'!$I:$I,"",'Raw Data'!$M:$M,"count") -> 2050000 | D5: =SUMIFS('Raw Data'!$L:$L,'Raw Data'!$B:$B,$B$2,'Raw Data'!$J:$J,D$2,'Raw Data'!$K:$K,"native",'Raw Data'!$H:$H,"Jordanian",'Raw Data'!$I:$I,"",'Raw Data'!$M:$M,"count") -> 2090000 | E5: =SUMIFS('Raw Data'!$L:$L,'Raw Data'!$B:$B,$B$2,'Raw Data'!$J:$J,E$2,'Raw Data'!$K:$K,"native",'Raw Data'!$H:$H,"Jordanian",'Raw Data'!$I:$I,"",'Raw Data'!$M:$M,"count") -> 2120000 | F5: =SUMIFS('Raw Data'!$L:$L,'Raw Data'!$B:$B,$B$2,'Raw Data'!$J:$J,F$2,'Raw Data'!$K:$K,"native",'Raw Data'!$H:$H,"Jordanian",'Raw Data'!$I:$I,"",'Raw Data'!$M:$M,"count") -> 2290000 | G5: =SUMIFS('Raw Data'!$L:$L,'Raw Data'!$B:$B,$B$2,'Raw Data'!$J:$J,G$2,'Raw Data'!$K:$K,"native",'Raw Data'!$H:$H,"Jordanian",'Raw Data'!$I:$I,"",'Raw Data'!$M:$M,"count") -> 2240000 | H5: =SUMIFS('Raw Data'!$L:$L,'Raw Data'!$B:$B,$B$2,'Raw Data'!$J:$J,H$2,'Raw Data'!$K:$K,"native",'Raw Data'!$H:$H,"Jordanian",'Raw Data'!$I:$I,"",'Raw Data'!$M:$M,"count") -> 2270000 | I5: =SUMIFS('Raw Data'!$L:$L,'Raw Data'!$B:$B,$B$2,'Raw Data'!$J:$J,I$2,'Raw Data'!$K:$K,"native",'Raw Data'!$H:$H,"Jordanian",'Raw Data'!$I:$I,"",'Raw Data'!$M:$M,"count") -> 2290000 | J5: =SUMIFS('Raw Data'!$L:$L,'Raw Data'!$B:$B,$B$2,'Raw Data'!$J:$J,J$2,'Raw Data'!$K:$K,"native",'Raw Data'!$H:$H,"Jordanian",'Raw Data'!$I:$I,"",'Raw Data'!$M:$M,"count") -> 2320000 | ... Z5: =SUMIFS('Raw Data'!$L:$L,'Raw Data'!$B:$B,$B$2,'Raw Data'!$J:$J,Z$2,'Raw Data'!$K:$K,"native",'Raw Data'!$H:$H,"Jordanian",'Raw Data'!$I:$I,"",'Raw Data'!$M:$M,"count") -> 2680000
A6: Users | B6: Non-Jordanian | C6: =SUMIFS('Raw Data'!$L:$L,'Raw Data'!$B:$B,$B$2,'Raw Data'!$J:$J,C$2,'Raw Data'!$K:$K,"native",'Raw Data'!$H:$H,"Non-Jordanian",'Raw Data'!$I:$I,"",'Raw Data'!$M:$M,"count") -> 278000 | D6: =SUMIFS('Raw Data'!$L:$L,'Raw Data'!$B:$B,$B$2,'Raw Data'!$J:$J,D$2,'Raw Data'!$K:$K,"native",'Raw Data'!$H:$H,"Non-Jordanian",'Raw Data'!$I:$I,"",'Raw Data'!$M:$M,"count") -> 282000 | E6: =SUMIFS('Raw Data'!$L:$L,'Raw Data'!$B:$B,$B$2,'Raw Data'!$J:$J,E$2,'Raw Data'!$K:$K,"native",'Raw Data'!$H:$H,"Non-Jordanian",'Raw Data'!$I:$I,"",'Raw Data'!$M:$M,"count") -> 285000 | F6: =SUMIFS('Raw Data'!$L:$L,'Raw Data'!$B:$B,$B$2,'Raw Data'!$J:$J,F$2,'Raw Data'!$K:$K,"native",'Raw Data'!$H:$H,"Non-Jordanian",'Raw Data'!$I:$I,"",'Raw Data'!$M:$M,"count") -> 300400 | G6: =SUMIFS('Raw Data'!$L:$L,'Raw Data'!$B:$B,$B$2,'Raw Data'!$J:$J,G$2,'Raw Data'!$K:$K,"native",'Raw Data'!$H:$H,"Non-Jordanian",'Raw Data'!$I:$I,"",'Raw Data'!$M:$M,"count") -> 303900 | H6: =SUMIFS('Raw Data'!$L:$L,'Raw Data'!$B:$B,$B$2,'Raw Data'!$J:$J,H$2,'Raw Data'!$K:$K,"native",'Raw Data'!$H:$H,"Non-Jordanian",'Raw Data'!$I:$I,"",'Raw Data'!$M:$M,"count") -> 307100 | I6: =SUMIFS('Raw Data'!$L:$L,'Raw Data'!$B:$B,$B$2,'Raw Data'!$J:$J,I$2,'Raw Data'!$K:$K,"native",'Raw Data'!$H:$H,"Non-Jordanian",'Raw Data'!$I:$I,"",'Raw Data'!$M:$M,"count") -> 310100 | J6: =SUMIFS('Raw Data'!$L:$L,'Raw Data'!$B:$B,$B$2,'Raw Data'!$J:$J,J$2,'Raw Data'!$K:$K,"native",'Raw Data'!$H:$H,"Non-Jordanian",'Raw Data'!$I:$I,"",'Raw Data'!$M:$M,"count") -> 313300 | ... Z6: =SUMIFS('Raw Data'!$L:$L,'Raw Data'!$B:$B,$B$2,'Raw Data'!$J:$J,Z$2,'Raw Data'!$K:$K,"native",'Raw Data'!$H:$H,"Non-Jordanian",'Raw Data'!$I:$I,"",'Raw Data'!$M:$M,"count") -> 387600
A7: USERS BY GENDER (Number)
A8: Users | B8: Female Users | C8: =SUMIFS('Raw Data'!$L:$L,'Raw Data'!$B:$B,$B$2,'Raw Data'!$J:$J,C$2,'Raw Data'!$K:$K,"native",'Raw Data'!$H:$H,"Female*",'Raw Data'!$I:$I,"",'Raw Data'!$M:$M,"count") -> 1140000 | D8: =SUMIFS('Raw Data'!$L:$L,'Raw Data'!$B:$B,$B$2,'Raw Data'!$J:$J,D$2,'Raw Data'!$K:$K,"native",'Raw Data'!$H:$H,"Female*",'Raw Data'!$I:$I,"",'Raw Data'!$M:$M,"count") -> 1170000 | E8: =SUMIFS('Raw Data'!$L:$L,'Raw Data'!$B:$B,$B$2,'Raw Data'!$J:$J,E$2,'Raw Data'!$K:$K,"native",'Raw Data'!$H:$H,"Female*",'Raw Data'!$I:$I,"",'Raw Data'!$M:$M,"count") -> 1190000 | F8: =SUMIFS('Raw Data'!$L:$L,'Raw Data'!$B:$B,$B$2,'Raw Data'!$J:$J,F$2,'Raw Data'!$K:$K,"native",'Raw Data'!$H:$H,"Female*",'Raw Data'!$I:$I,"",'Raw Data'!$M:$M,"count") -> 1260000 | G8: =SUMIFS('Raw Data'!$L:$L,'Raw Data'!$B:$B,$B$2,'Raw Data'!$J:$J,G$2,'Raw Data'!$K:$K,"native",'Raw Data'!$H:$H,"Female*",'Raw Data'!$I:$I,"",'Raw Data'!$M:$M,"count") -> 1280000 | H8: =SUMIFS('Raw Data'!$L:$L,'Raw Data'!$B:$B,$B$2,'Raw Data'!$J:$J,H$2,'Raw Data'!$K:$K,"native",'Raw Data'!$H:$H,"Female*",'Raw Data'!$I:$I,"",'Raw Data'!$M:$M,"count") -> 1300000 | I8: =SUMIFS('Raw Data'!$L:$L,'Raw Data'!$B:$B,$B$2,'Raw Data'!$J:$J,I$2,'Raw Data'!$K:$K,"native",'Raw Data'!$H:$H,"Female*",'Raw Data'!$I:$I,"",'Raw Data'!$M:$M,"count") -> 1300000 | J8: =SUMIFS('Raw Data'!$L:$L,'Raw Data'!$B:$B,$B$2,'Raw Data'!$J:$J,J$2,'Raw Data'!$K:$K,"native",'Raw Data'!$H:$H,"Female*",'Raw Data'!$I:$I,"",'Raw Data'!$M:$M,"count") -> 1300000 | ... Z8: =SUMIFS('Raw Data'!$L:$L,'Raw Data'!$B:$B,$B$2,'Raw Data'!$J:$J,Z$2,'Raw Data'!$K:$K,"native",'Raw Data'!$H:$H,"Female*",'Raw Data'!$I:$I,"",'Raw Data'!$M:$M,"count") -> 1170000
A9: Users | B9: Male Users | C9: =SUMIFS('Raw Data'!$L:$L,'Raw Data'!$B:$B,$B$2,'Raw Data'!$J:$J,C$2,'Raw Data'!$K:$K,"native",'Raw Data'!$H:$H,"Male*",'Raw Data'!$I:$I,"",'Raw Data'!$M:$M,"count") -> 1180000 | D9: =SUMIFS('Raw Data'!$L:$L,'Raw Data'!$B:$B,$B$2,'Raw Data'!$J:$J,D$2,'Raw Data'!$K:$K,"native",'Raw Data'!$H:$H,"Male*",'Raw Data'!$I:$I,"",'Raw Data'!$M:$M,"count") -> 1190000 | E9: =SUMIFS('Raw Data'!$L:$L,'Raw Data'!$B:$B,$B$2,'Raw Data'!$J:$J,E$2,'Raw Data'!$K:$K,"native",'Raw Data'!$H:$H,"Male*",'Raw Data'!$I:$I,"",'Raw Data'!$M:$M,"count") -> 1200000 | F9: =SUMIFS('Raw Data'!$L:$L,'Raw Data'!$B:$B,$B$2,'Raw Data'!$J:$J,F$2,'Raw Data'!$K:$K,"native",'Raw Data'!$H:$H,"Male*",'Raw Data'!$I:$I,"",'Raw Data'!$M:$M,"count") -> 1310000 | G9: =SUMIFS('Raw Data'!$L:$L,'Raw Data'!$B:$B,$B$2,'Raw Data'!$J:$J,G$2,'Raw Data'!$K:$K,"native",'Raw Data'!$H:$H,"Male*",'Raw Data'!$I:$I,"",'Raw Data'!$M:$M,"count") -> 1260000 | H9: =SUMIFS('Raw Data'!$L:$L,'Raw Data'!$B:$B,$B$2,'Raw Data'!$J:$J,H$2,'Raw Data'!$K:$K,"native",'Raw Data'!$H:$H,"Male*",'Raw Data'!$I:$I,"",'Raw Data'!$M:$M,"count") -> 1270000 | I9: =SUMIFS('Raw Data'!$L:$L,'Raw Data'!$B:$B,$B$2,'Raw Data'!$J:$J,I$2,'Raw Data'!$K:$K,"native",'Raw Data'!$H:$H,"Male*",'Raw Data'!$I:$I,"",'Raw Data'!$M:$M,"count") -> 1300000 | J9: =SUMIFS('Raw Data'!$L:$L,'Raw Data'!$B:$B,$B$2,'Raw Data'!$J:$J,J$2,'Raw Data'!$K:$K,"native",'Raw Data'!$H:$H,"Male*",'Raw Data'!$I:$I,"",'Raw Data'!$M:$M,"count") -> 1320000 | ... Z9: =SUMIFS('Raw Data'!$L:$L,'Raw Data'!$B:$B,$B$2,'Raw Data'!$J:$J,Z$2,'Raw Data'!$K:$K,"native",'Raw Data'!$H:$H,"Male*",'Raw Data'!$I:$I,"",'Raw Data'!$M:$M,"count") -> 1880000
A10: USERS BY AGE BRACKET (Number)
A11: Users | B11: 18-30 | C11: =SUMIFS('Raw Data'!$L:$L,'Raw Data'!$B:$B,$B$2,'Raw Data'!$J:$J,C$2,'Raw Data'!$K:$K,"native",'Raw Data'!$H:$H,"18-30",'Raw Data'!$I:$I,"",'Raw Data'!$M:$M,"count") -> 828000 | D11: =SUMIFS('Raw Data'!$L:$L,'Raw Data'!$B:$B,$B$2,'Raw Data'!$J:$J,D$2,'Raw Data'!$K:$K,"native",'Raw Data'!$H:$H,"18-30",'Raw Data'!$I:$I,"",'Raw Data'!$M:$M,"count") -> 842000 | E11: =SUMIFS('Raw Data'!$L:$L,'Raw Data'!$B:$B,$B$2,'Raw Data'!$J:$J,E$2,'Raw Data'!$K:$K,"native",'Raw Data'!$H:$H,"18-30",'Raw Data'!$I:$I,"",'Raw Data'!$M:$M,"count") -> 854000 | F11: =SUMIFS('Raw Data'!$L:$L,'Raw Data'!$B:$B,$B$2,'Raw Data'!$J:$J,F$2,'Raw Data'!$K:$K,"native",'Raw Data'!$H:$H,"18-30",'Raw Data'!$I:$I,"",'Raw Data'!$M:$M,"count") -> 917000 | G11: =SUMIFS('Raw Data'!$L:$L,'Raw Data'!$B:$B,$B$2,'Raw Data'!$J:$J,G$2,'Raw Data'!$K:$K,"native",'Raw Data'!$H:$H,"18-30",'Raw Data'!$I:$I,"",'Raw Data'!$M:$M,"count") -> 919000 | H11: =SUMIFS('Raw Data'!$L:$L,'Raw Data'!$B:$B,$B$2,'Raw Data'!$J:$J,H$2,'Raw Data'!$K:$K,"native",'Raw Data'!$H:$H,"18-30",'Raw Data'!$I:$I,"",'Raw Data'!$M:$M,"count") -> 929000 | I11: =SUMIFS('Raw Data'!$L:$L,'Raw Data'!$B:$B,$B$2,'Raw Data'!$J:$J,I$2,'Raw Data'!$K:$K,"native",'Raw Data'!$H:$H,"18-30",'Raw Data'!$I:$I,"",'Raw Data'!$M:$M,"count") -> 938000 | J11: =SUMIFS('Raw Data'!$L:$L,'Raw Data'!$B:$B,$B$2,'Raw Data'!$J:$J,J$2,'Raw Data'!$K:$K,"native",'Raw Data'!$H:$H,"18-30",'Raw Data'!$I:$I,"",'Raw Data'!$M:$M,"count") -> 946000 | ... Z11: =SUMIFS('Raw Data'!$L:$L,'Raw Data'!$B:$B,$B$2,'Raw Data'!$J:$J,Z$2,'Raw Data'!$K:$K,"native",'Raw Data'!$H:$H,"18-30",'Raw Data'!$I:$I,"",'Raw Data'!$M:$M,"count") -> 1100000
A12: Users | B12: 31-40 | C12: =SUMIFS('Raw Data'!$L:$L,'Raw Data'!$B:$B,$B$2,'Raw Data'!$J:$J,C$2,'Raw Data'!$K:$K,"native",'Raw Data'!$H:$H,"31-40",'Raw Data'!$I:$I,"",'Raw Data'!$M:$M,"count") -> 603000 | D12: =SUMIFS('Raw Data'!$L:$L,'Raw Data'!$B:$B,$B$2,'Raw Data'!$J:$J,D$2,'Raw Data'!$K:$K,"native",'Raw Data'!$H:$H,"31-40",'Raw Data'!$I:$I,"",'Raw Data'!$M:$M,"count") -> 612000 | E12: =SUMIFS('Raw Data'!$L:$L,'Raw Data'!$B:$B,$B$2,'Raw Data'!$J:$J,E$2,'Raw Data'!$K:$K,"native",'Raw Data'!$H:$H,"31-40",'Raw Data'!$I:$I,"",'Raw Data'!$M:$M,"count") -> 621000 | F12: =SUMIFS('Raw Data'!$L:$L,'Raw Data'!$B:$B,$B$2,'Raw Data'!$J:$J,F$2,'Raw Data'!$K:$K,"native",'Raw Data'!$H:$H,"31-40",'Raw Data'!$I:$I,"",'Raw Data'!$M:$M,"count") -> 667000 | G12: =SUMIFS('Raw Data'!$L:$L,'Raw Data'!$B:$B,$B$2,'Raw Data'!$J:$J,G$2,'Raw Data'!$K:$K,"native",'Raw Data'!$H:$H,"31-40",'Raw Data'!$I:$I,"",'Raw Data'!$M:$M,"count") -> 653000 | H12: =SUMIFS('Raw Data'!$L:$L,'Raw Data'!$B:$B,$B$2,'Raw Data'!$J:$J,H$2,'Raw Data'!$K:$K,"native",'Raw Data'!$H:$H,"31-40",'Raw Data'!$I:$I,"",'Raw Data'!$M:$M,"count") -> 661000 | I12: =SUMIFS('Raw Data'!$L:$L,'Raw Data'!$B:$B,$B$2,'Raw Data'!$J:$J,I$2,'Raw Data'!$K:$K,"native",'Raw Data'!$H:$H,"31-40",'Raw Data'!$I:$I,"",'Raw Data'!$M:$M,"count") -> 668000 | J12: =SUMIFS('Raw Data'!$L:$L,'Raw Data'!$B:$B,$B$2,'Raw Data'!$J:$J,J$2,'Raw Data'!$K:$K,"native",'Raw Data'!$H:$H,"31-40",'Raw Data'!$I:$I,"",'Raw Data'!$M:$M,"count") -> 676000 | ... Z12: =SUMIFS('Raw Data'!$L:$L,'Raw Data'!$B:$B,$B$2,'Raw Data'!$J:$J,Z$2,'Raw Data'!$K:$K,"native",'Raw Data'!$H:$H,"31-40",'Raw Data'!$I:$I,"",'Raw Data'!$M:$M,"count") -> 788000
A13: Users | B13: 41-50 | C13: =SUMIFS('Raw Data'!$L:$L,'Raw Data'!$B:$B,$B$2,'Raw Data'!$J:$J,C$2,'Raw Data'!$K:$K,"native",'Raw Data'!$H:$H,"41-50",'Raw Data'!$I:$I,"",'Raw Data'!$M:$M,"count") -> 456000 | D13: =SUMIFS('Raw Data'!$L:$L,'Raw Data'!$B:$B,$B$2,'Raw Data'!$J:$J,D$2,'Raw Data'!$K:$K,"native",'Raw Data'!$H:$H,"41-50",'Raw Data'!$I:$I,"",'Raw Data'!$M:$M,"count") -> 463000 | E13: =SUMIFS('Raw Data'!$L:$L,'Raw Data'!$B:$B,$B$2,'Raw Data'!$J:$J,E$2,'Raw Data'!$K:$K,"native",'Raw Data'!$H:$H,"41-50",'Raw Data'!$I:$I,"",'Raw Data'!$M:$M,"count") -> 470000 | F13: =SUMIFS('Raw Data'!$L:$L,'Raw Data'!$B:$B,$B$2,'Raw Data'!$J:$J,F$2,'Raw Data'!$K:$K,"native",'Raw Data'!$H:$H,"41-50",'Raw Data'!$I:$I,"",'Raw Data'!$M:$M,"count") -> 503000 | G13: =SUMIFS('Raw Data'!$L:$L,'Raw Data'!$B:$B,$B$2,'Raw Data'!$J:$J,G$2,'Raw Data'!$K:$K,"native",'Raw Data'!$H:$H,"41-50",'Raw Data'!$I:$I,"",'Raw Data'!$M:$M,"count") -> 493000 | H13: =SUMIFS('Raw Data'!$L:$L,'Raw Data'!$B:$B,$B$2,'Raw Data'!$J:$J,H$2,'Raw Data'!$K:$K,"native",'Raw Data'!$H:$H,"41-50",'Raw Data'!$I:$I,"",'Raw Data'!$M:$M,"count") -> 499000 | I13: =SUMIFS('Raw Data'!$L:$L,'Raw Data'!$B:$B,$B$2,'Raw Data'!$J:$J,I$2,'Raw Data'!$K:$K,"native",'Raw Data'!$H:$H,"41-50",'Raw Data'!$I:$I,"",'Raw Data'!$M:$M,"count") -> 504000 | J13: =SUMIFS('Raw Data'!$L:$L,'Raw Data'!$B:$B,$B$2,'Raw Data'!$J:$J,J$2,'Raw Data'!$K:$K,"native",'Raw Data'!$H:$H,"41-50",'Raw Data'!$I:$I,"",'Raw Data'!$M:$M,"count") -> 510000 | ... Z13: =SUMIFS('Raw Data'!$L:$L,'Raw Data'!$B:$B,$B$2,'Raw Data'!$J:$J,Z$2,'Raw Data'!$K:$K,"native",'Raw Data'!$H:$H,"41-50",'Raw Data'!$I:$I,"",'Raw Data'!$M:$M,"count") -> 589000
A14: Users | B14: 51-60 | C14: =SUMIFS('Raw Data'!$L:$L,'Raw Data'!$B:$B,$B$2,'Raw Data'!$J:$J,C$2,'Raw Data'!$K:$K,"native",'Raw Data'!$H:$H,"51-60",'Raw Data'!$I:$I,"",'Raw Data'!$M:$M,"count") -> 285000 | D14: =SUMIFS('Raw Data'!$L:$L,'Raw Data'!$B:$B,$B$2,'Raw Data'!$J:$J,D$2,'Raw Data'!$K:$K,"native",'Raw Data'!$H:$H,"51-60",'Raw Data'!$I:$I,"",'Raw Data'!$M:$M,"count") -> 290000 | E14: =SUMIFS('Raw Data'!$L:$L,'Raw Data'!$B:$B,$B$2,'Raw Data'!$J:$J,E$2,'Raw Data'!$K:$K,"native",'Raw Data'!$H:$H,"51-60",'Raw Data'!$I:$I,"",'Raw Data'!$M:$M,"count") -> 294000 | F14: =SUMIFS('Raw Data'!$L:$L,'Raw Data'!$B:$B,$B$2,'Raw Data'!$J:$J,F$2,'Raw Data'!$K:$K,"native",'Raw Data'!$H:$H,"51-60",'Raw Data'!$I:$I,"",'Raw Data'!$M:$M,"count") -> 318000 | G14: =SUMIFS('Raw Data'!$L:$L,'Raw Data'!$B:$B,$B$2,'Raw Data'!$J:$J,G$2,'Raw Data'!$K:$K,"native",'Raw Data'!$H:$H,"51-60",'Raw Data'!$I:$I,"",'Raw Data'!$M:$M,"count") -> 309000 | H14: =SUMIFS('Raw Data'!$L:$L,'Raw Data'!$B:$B,$B$2,'Raw Data'!$J:$J,H$2,'Raw Data'!$K:$K,"native",'Raw Data'!$H:$H,"51-60",'Raw Data'!$I:$I,"",'Raw Data'!$M:$M,"count") -> 313000 | I14: =SUMIFS('Raw Data'!$L:$L,'Raw Data'!$B:$B,$B$2,'Raw Data'!$J:$J,I$2,'Raw Data'!$K:$K,"native",'Raw Data'!$H:$H,"51-60",'Raw Data'!$I:$I,"",'Raw Data'!$M:$M,"count") -> 317000 | J14: =SUMIFS('Raw Data'!$L:$L,'Raw Data'!$B:$B,$B$2,'Raw Data'!$J:$J,J$2,'Raw Data'!$K:$K,"native",'Raw Data'!$H:$H,"51-60",'Raw Data'!$I:$I,"",'Raw Data'!$M:$M,"count") -> 322000 | ... Z14: =SUMIFS('Raw Data'!$L:$L,'Raw Data'!$B:$B,$B$2,'Raw Data'!$J:$J,Z$2,'Raw Data'!$K:$K,"native",'Raw Data'!$H:$H,"51-60",'Raw Data'!$I:$I,"",'Raw Data'!$M:$M,"count") -> 373000
A15: Users | B15: 61-70 | C15: =SUMIFS('Raw Data'!$L:$L,'Raw Data'!$B:$B,$B$2,'Raw Data'!$J:$J,C$2,'Raw Data'!$K:$K,"native",'Raw Data'!$H:$H,"61-70",'Raw Data'!$I:$I,"",'Raw Data'!$M:$M,"count") -> 103000 | D15: =SUMIFS('Raw Data'!$L:$L,'Raw Data'!$B:$B,$B$2,'Raw Data'!$J:$J,D$2,'Raw Data'!$K:$K,"native",'Raw Data'!$H:$H,"61-70",'Raw Data'!$I:$I,"",'Raw Data'!$M:$M,"count") -> 105000 | E15: =SUMIFS('Raw Data'!$L:$L,'Raw Data'!$B:$B,$B$2,'Raw Data'!$J:$J,E$2,'Raw Data'!$K:$K,"native",'Raw Data'!$H:$H,"61-70",'Raw Data'!$I:$I,"",'Raw Data'!$M:$M,"count") -> 107000 | F15: =SUMIFS('Raw Data'!$L:$L,'Raw Data'!$B:$B,$B$2,'Raw Data'!$J:$J,F$2,'Raw Data'!$K:$K,"native",'Raw Data'!$H:$H,"61-70",'Raw Data'!$I:$I,"",'Raw Data'!$M:$M,"count") -> 119000 | G15: =SUMIFS('Raw Data'!$L:$L,'Raw Data'!$B:$B,$B$2,'Raw Data'!$J:$J,G$2,'Raw Data'!$K:$K,"native",'Raw Data'!$H:$H,"61-70",'Raw Data'!$I:$I,"",'Raw Data'!$M:$M,"count") -> 114000 | H15: =SUMIFS('Raw Data'!$L:$L,'Raw Data'!$B:$B,$B$2,'Raw Data'!$J:$J,H$2,'Raw Data'!$K:$K,"native",'Raw Data'!$H:$H,"61-70",'Raw Data'!$I:$I,"",'Raw Data'!$M:$M,"count") -> 117000 | I15: =SUMIFS('Raw Data'!$L:$L,'Raw Data'!$B:$B,$B$2,'Raw Data'!$J:$J,I$2,'Raw Data'!$K:$K,"native",'Raw Data'!$H:$H,"61-70",'Raw Data'!$I:$I,"",'Raw Data'!$M:$M,"count") -> 118000 | J15: =SUMIFS('Raw Data'!$L:$L,'Raw Data'!$B:$B,$B$2,'Raw Data'!$J:$J,J$2,'Raw Data'!$K:$K,"native",'Raw Data'!$H:$H,"61-70",'Raw Data'!$I:$I,"",'Raw Data'!$M:$M,"count") -> 121000 | ... Z15: =SUMIFS('Raw Data'!$L:$L,'Raw Data'!$B:$B,$B$2,'Raw Data'!$J:$J,Z$2,'Raw Data'!$K:$K,"native",'Raw Data'!$H:$H,"61-70",'Raw Data'!$I:$I,"",'Raw Data'!$M:$M,"count") -> 149000
A16: Users | B16: 71-80 | C16: =SUMIFS('Raw Data'!$L:$L,'Raw Data'!$B:$B,$B$2,'Raw Data'!$J:$J,C$2,'Raw Data'!$K:$K,"native",'Raw Data'!$H:$H,"71-80",'Raw Data'!$I:$I,"",'Raw Data'!$M:$M,"count") -> 34000 | D16: =SUMIFS('Raw Data'!$L:$L,'Raw Data'!$B:$B,$B$2,'Raw Data'!$J:$J,D$2,'Raw Data'!$K:$K,"native",'Raw Data'!$H:$H,"71-80",'Raw Data'!$I:$I,"",'Raw Data'!$M:$M,"count") -> 35000 | E16: =SUMIFS('Raw Data'!$L:$L,'Raw Data'!$B:$B,$B$2,'Raw Data'!$J:$J,E$2,'Raw Data'!$K:$K,"native",'Raw Data'!$H:$H,"71-80",'Raw Data'!$I:$I,"",'Raw Data'!$M:$M,"count") -> 35000 | F16: =SUMIFS('Raw Data'!$L:$L,'Raw Data'!$B:$B,$B$2,'Raw Data'!$J:$J,F$2,'Raw Data'!$K:$K,"native",'Raw Data'!$H:$H,"71-80",'Raw Data'!$I:$I,"",'Raw Data'!$M:$M,"count") -> 40000 | G16: =SUMIFS('Raw Data'!$L:$L,'Raw Data'!$B:$B,$B$2,'Raw Data'!$J:$J,G$2,'Raw Data'!$K:$K,"native",'Raw Data'!$H:$H,"71-80",'Raw Data'!$I:$I,"",'Raw Data'!$M:$M,"count") -> 36000 | H16: =SUMIFS('Raw Data'!$L:$L,'Raw Data'!$B:$B,$B$2,'Raw Data'!$J:$J,H$2,'Raw Data'!$K:$K,"native",'Raw Data'!$H:$H,"71-80",'Raw Data'!$I:$I,"",'Raw Data'!$M:$M,"count") -> 36000 | I16: =SUMIFS('Raw Data'!$L:$L,'Raw Data'!$B:$B,$B$2,'Raw Data'!$J:$J,I$2,'Raw Data'!$K:$K,"native",'Raw Data'!$H:$H,"71-80",'Raw Data'!$I:$I,"",'Raw Data'!$M:$M,"count") -> 37000 | J16: =SUMIFS('Raw Data'!$L:$L,'Raw Data'!$B:$B,$B$2,'Raw Data'!$J:$J,J$2,'Raw Data'!$K:$K,"native",'Raw Data'!$H:$H,"71-80",'Raw Data'!$I:$I,"",'Raw Data'!$M:$M,"count") -> 38000 | ... Z16: =SUMIFS('Raw Data'!$L:$L,'Raw Data'!$B:$B,$B$2,'Raw Data'!$J:$J,Z$2,'Raw Data'!$K:$K,"native",'Raw Data'!$H:$H,"71-80",'Raw Data'!$I:$I,"",'Raw Data'!$M:$M,"count") -> 43000
A17: Users | B17: 81-90 | C17: =SUMIFS('Raw Data'!$L:$L,'Raw Data'!$B:$B,$B$2,'Raw Data'!$J:$J,C$2,'Raw Data'!$K:$K,"native",'Raw Data'!$H:$H,"81-90",'Raw Data'!$I:$I,"",'Raw Data'!$M:$M,"count") -> 13000 | D17: =SUMIFS('Raw Data'!$L:$L,'Raw Data'!$B:$B,$B$2,'Raw Data'!$J:$J,D$2,'Raw Data'!$K:$K,"native",'Raw Data'!$H:$H,"81-90",'Raw Data'!$I:$I,"",'Raw Data'!$M:$M,"count") -> 13000 | E17: =SUMIFS('Raw Data'!$L:$L,'Raw Data'!$B:$B,$B$2,'Raw Data'!$J:$J,E$2,'Raw Data'!$K:$K,"native",'Raw Data'!$H:$H,"81-90",'Raw Data'!$I:$I,"",'Raw Data'!$M:$M,"count") -> 13000 | F17: =SUMIFS('Raw Data'!$L:$L,'Raw Data'!$B:$B,$B$2,'Raw Data'!$J:$J,F$2,'Raw Data'!$K:$K,"native",'Raw Data'!$H:$H,"81-90",'Raw Data'!$I:$I,"",'Raw Data'!$M:$M,"count") -> 14000 | G17: =SUMIFS('Raw Data'!$L:$L,'Raw Data'!$B:$B,$B$2,'Raw Data'!$J:$J,G$2,'Raw Data'!$K:$K,"native",'Raw Data'!$H:$H,"81-90",'Raw Data'!$I:$I,"",'Raw Data'!$M:$M,"count") -> 12000 | H17: =SUMIFS('Raw Data'!$L:$L,'Raw Data'!$B:$B,$B$2,'Raw Data'!$J:$J,H$2,'Raw Data'!$K:$K,"native",'Raw Data'!$H:$H,"81-90",'Raw Data'!$I:$I,"",'Raw Data'!$M:$M,"count") -> 12000 | I17: =SUMIFS('Raw Data'!$L:$L,'Raw Data'!$B:$B,$B$2,'Raw Data'!$J:$J,I$2,'Raw Data'!$K:$K,"native",'Raw Data'!$H:$H,"81-90",'Raw Data'!$I:$I,"",'Raw Data'!$M:$M,"count") -> 13000 | J17: =SUMIFS('Raw Data'!$L:$L,'Raw Data'!$B:$B,$B$2,'Raw Data'!$J:$J,J$2,'Raw Data'!$K:$K,"native",'Raw Data'!$H:$H,"81-90",'Raw Data'!$I:$I,"",'Raw Data'!$M:$M,"count") -> 13000 | ... Z17: =SUMIFS('Raw Data'!$L:$L,'Raw Data'!$B:$B,$B$2,'Raw Data'!$J:$J,Z$2,'Raw Data'!$K:$K,"native",'Raw Data'!$H:$H,"81-90",'Raw Data'!$I:$I,"",'Raw Data'!$M:$M,"count") -> 15000
A18: Users | B18: <18 | C18: =SUMIFS('Raw Data'!$L:$L,'Raw Data'!$B:$B,$B$2,'Raw Data'!$J:$J,C$2,'Raw Data'!$K:$K,"native",'Raw Data'!$H:$H,"=<18",'Raw Data'!$I:$I,"",'Raw Data'!$M:$M,"count") -> 1000 | D18: =SUMIFS('Raw Data'!$L:$L,'Raw Data'!$B:$B,$B$2,'Raw Data'!$J:$J,D$2,'Raw Data'!$K:$K,"native",'Raw Data'!$H:$H,"=<18",'Raw Data'!$I:$I,"",'Raw Data'!$M:$M,"count") -> 1000 | E18: =SUMIFS('Raw Data'!$L:$L,'Raw Data'!$B:$B,$B$2,'Raw Data'!$J:$J,E$2,'Raw Data'!$K:$K,"native",'Raw Data'!$H:$H,"=<18",'Raw Data'!$I:$I,"",'Raw Data'!$M:$M,"count") -> 1000 | F18: =SUMIFS('Raw Data'!$L:$L,'Raw Data'!$B:$B,$B$2,'Raw Data'!$J:$J,F$2,'Raw Data'!$K:$K,"native",'Raw Data'!$H:$H,"=<18",'Raw Data'!$I:$I,"",'Raw Data'!$M:$M,"count") -> 1000 | G18: =SUMIFS('Raw Data'!$L:$L,'Raw Data'!$B:$B,$B$2,'Raw Data'!$J:$J,G$2,'Raw Data'!$K:$K,"native",'Raw Data'!$H:$H,"=<18",'Raw Data'!$I:$I,"",'Raw Data'!$M:$M,"count") -> 1000 | H18: =SUMIFS('Raw Data'!$L:$L,'Raw Data'!$B:$B,$B$2,'Raw Data'!$J:$J,H$2,'Raw Data'!$K:$K,"native",'Raw Data'!$H:$H,"=<18",'Raw Data'!$I:$I,"",'Raw Data'!$M:$M,"count") -> 1000 | I18: =SUMIFS('Raw Data'!$L:$L,'Raw Data'!$B:$B,$B$2,'Raw Data'!$J:$J,I$2,'Raw Data'!$K:$K,"native",'Raw Data'!$H:$H,"=<18",'Raw Data'!$I:$I,"",'Raw Data'!$M:$M,"count") -> 1000 | J18: =SUMIFS('Raw Data'!$L:$L,'Raw Data'!$B:$B,$B$2,'Raw Data'!$J:$J,J$2,'Raw Data'!$K:$K,"native",'Raw Data'!$H:$H,"=<18",'Raw Data'!$I:$I,"",'Raw Data'!$M:$M,"count") -> 1000 | ... Z18: =SUMIFS('Raw Data'!$L:$L,'Raw Data'!$B:$B,$B$2,'Raw Data'!$J:$J,Z$2,'Raw Data'!$K:$K,"native",'Raw Data'!$H:$H,"=<18",'Raw Data'!$I:$I,"",'Raw Data'!$M:$M,"count") -> 1000
A19: WALLETS BY WALLET TYPE (Number)
A20: Wallets | B20: Agent Wallet | C20: =SUMIFS('Raw Data'!$L:$L,'Raw Data'!$B:$B,$B$2,'Raw Data'!$J:$J,C$2,'Raw Data'!$K:$K,"native",'Raw Data'!$H:$H,"Agent Wallet",'Raw Data'!$I:$I,"",'Raw Data'!$M:$M,"count") -> 1376 | D20: =SUMIFS('Raw Data'!$L:$L,'Raw Data'!$B:$B,$B$2,'Raw Data'!$J:$J,D$2,'Raw Data'!$K:$K,"native",'Raw Data'!$H:$H,"Agent Wallet",'Raw Data'!$I:$I,"",'Raw Data'!$M:$M,"count") -> 1390 | E20: =SUMIFS('Raw Data'!$L:$L,'Raw Data'!$B:$B,$B$2,'Raw Data'!$J:$J,E$2,'Raw Data'!$K:$K,"native",'Raw Data'!$H:$H,"Agent Wallet",'Raw Data'!$I:$I,"",'Raw Data'!$M:$M,"count") -> 1255 | F20: =SUMIFS('Raw Data'!$L:$L,'Raw Data'!$B:$B,$B$2,'Raw Data'!$J:$J,F$2,'Raw Data'!$K:$K,"native",'Raw Data'!$H:$H,"Agent Wallet",'Raw Data'!$I:$I,"",'Raw Data'!$M:$M,"count") -> 1077 | G20: =SUMIFS('Raw Data'!$L:$L,'Raw Data'!$B:$B,$B$2,'Raw Data'!$J:$J,G$2,'Raw Data'!$K:$K,"native",'Raw Data'!$H:$H,"Agent Wallet",'Raw Data'!$I:$I,"",'Raw Data'!$M:$M,"count") -> 911 | H20: =SUMIFS('Raw Data'!$L:$L,'Raw Data'!$B:$B,$B$2,'Raw Data'!$J:$J,H$2,'Raw Data'!$K:$K,"native",'Raw Data'!$H:$H,"Agent Wallet",'Raw Data'!$I:$I,"",'Raw Data'!$M:$M,"count") -> 909 | I20: =SUMIFS('Raw Data'!$L:$L,'Raw Data'!$B:$B,$B$2,'Raw Data'!$J:$J,I$2,'Raw Data'!$K:$K,"native",'Raw Data'!$H:$H,"Agent Wallet",'Raw Data'!$I:$I,"",'Raw Data'!$M:$M,"count") -> 918 | J20: =SUMIFS('Raw Data'!$L:$L,'Raw Data'!$B:$B,$B$2,'Raw Data'!$J:$J,J$2,'Raw Data'!$K:$K,"native",'Raw Data'!$H:$H,"Agent Wallet",'Raw Data'!$I:$I,"",'Raw Data'!$M:$M,"count") -> 939 | ... Z20: =SUMIFS('Raw Data'!$L:$L,'Raw Data'!$B:$B,$B$2,'Raw Data'!$J:$J,Z$2,'Raw Data'!$K:$K,"native",'Raw Data'!$H:$H,"Agent Wallet",'Raw Data'!$I:$I,"",'Raw Data'!$M:$M,"count") -> 1087
A21: Wallets | B21: Business Wallet | C21: =SUMIFS('Raw Data'!$L:$L,'Raw Data'!$B:$B,$B$2,'Raw Data'!$J:$J,C$2,'Raw Data'!$K:$K,"native",'Raw Data'!$H:$H,"Business Wallet",'Raw Data'!$I:$I,"",'Raw Data'!$M:$M,"count") -> 1088 | D21: =SUMIFS('Raw Data'!$L:$L,'Raw Data'!$B:$B,$B$2,'Raw Data'!$J:$J,D$2,'Raw Data'!$K:$K,"native",'Raw Data'!$H:$H,"Business Wallet",'Raw Data'!$I:$I,"",'Raw Data'!$M:$M,"count") -> 1124 | E21: =SUMIFS('Raw Data'!$L:$L,'Raw Data'!$B:$B,$B$2,'Raw Data'!$J:$J,E$2,'Raw Data'!$K:$K,"native",'Raw Data'!$H:$H,"Business Wallet",'Raw Data'!$I:$I,"",'Raw Data'!$M:$M,"count") -> 1139 | F21: =SUMIFS('Raw Data'!$L:$L,'Raw Data'!$B:$B,$B$2,'Raw Data'!$J:$J,F$2,'Raw Data'!$K:$K,"native",'Raw Data'!$H:$H,"Business Wallet",'Raw Data'!$I:$I,"",'Raw Data'!$M:$M,"count") -> 1149 | G21: =SUMIFS('Raw Data'!$L:$L,'Raw Data'!$B:$B,$B$2,'Raw Data'!$J:$J,G$2,'Raw Data'!$K:$K,"native",'Raw Data'!$H:$H,"Business Wallet",'Raw Data'!$I:$I,"",'Raw Data'!$M:$M,"count") -> 1149 | H21: =SUMIFS('Raw Data'!$L:$L,'Raw Data'!$B:$B,$B$2,'Raw Data'!$J:$J,H$2,'Raw Data'!$K:$K,"native",'Raw Data'!$H:$H,"Business Wallet",'Raw Data'!$I:$I,"",'Raw Data'!$M:$M,"count") -> 1160 | I21: =SUMIFS('Raw Data'!$L:$L,'Raw Data'!$B:$B,$B$2,'Raw Data'!$J:$J,I$2,'Raw Data'!$K:$K,"native",'Raw Data'!$H:$H,"Business Wallet",'Raw Data'!$I:$I,"",'Raw Data'!$M:$M,"count") -> 1176 | J21: =SUMIFS('Raw Data'!$L:$L,'Raw Data'!$B:$B,$B$2,'Raw Data'!$J:$J,J$2,'Raw Data'!$K:$K,"native",'Raw Data'!$H:$H,"Business Wallet",'Raw Data'!$I:$I,"",'Raw Data'!$M:$M,"count") -> 1201 | ... Z21: =SUMIFS('Raw Data'!$L:$L,'Raw Data'!$B:$B,$B$2,'Raw Data'!$J:$J,Z$2,'Raw Data'!$K:$K,"native",'Raw Data'!$H:$H,"Business Wallet",'Raw Data'!$I:$I,"",'Raw Data'!$M:$M,"count") -> 2170
A22: Wallets | B22: Government Wallet | C22: =SUMIFS('Raw Data'!$L:$L,'Raw Data'!$B:$B,$B$2,'Raw Data'!$J:$J,C$2,'Raw Data'!$K:$K,"native",'Raw Data'!$H:$H,"Government Wallet",'Raw Data'!$I:$I,"",'Raw Data'!$M:$M,"count") -> 8 | D22: =SUMIFS('Raw Data'!$L:$L,'Raw Data'!$B:$B,$B$2,'Raw Data'!$J:$J,D$2,'Raw Data'!$K:$K,"native",'Raw Data'!$H:$H,"Government Wallet",'Raw Data'!$I:$I,"",'Raw Data'!$M:$M,"count") -> 8 | E22: =SUMIFS('Raw Data'!$L:$L,'Raw Data'!$B:$B,$B$2,'Raw Data'!$J:$J,E$2,'Raw Data'!$K:$K,"native",'Raw Data'!$H:$H,"Government Wallet",'Raw Data'!$I:$I,"",'Raw Data'!$M:$M,"count") -> 8 | F22: =SUMIFS('Raw Data'!$L:$L,'Raw Data'!$B:$B,$B$2,'Raw Data'!$J:$J,F$2,'Raw Data'!$K:$K,"native",'Raw Data'!$H:$H,"Government Wallet",'Raw Data'!$I:$I,"",'Raw Data'!$M:$M,"count") -> 7 | G22: =SUMIFS('Raw Data'!$L:$L,'Raw Data'!$B:$B,$B$2,'Raw Data'!$J:$J,G$2,'Raw Data'!$K:$K,"native",'Raw Data'!$H:$H,"Government Wallet",'Raw Data'!$I:$I,"",'Raw Data'!$M:$M,"count") -> 6 | H22: =SUMIFS('Raw Data'!$L:$L,'Raw Data'!$B:$B,$B$2,'Raw Data'!$J:$J,H$2,'Raw Data'!$K:$K,"native",'Raw Data'!$H:$H,"Government Wallet",'Raw Data'!$I:$I,"",'Raw Data'!$M:$M,"count") -> 6 | I22: =SUMIFS('Raw Data'!$L:$L,'Raw Data'!$B:$B,$B$2,'Raw Data'!$J:$J,I$2,'Raw Data'!$K:$K,"native",'Raw Data'!$H:$H,"Government Wallet",'Raw Data'!$I:$I,"",'Raw Data'!$M:$M,"count") -> 6 | J22: =SUMIFS('Raw Data'!$L:$L,'Raw Data'!$B:$B,$B$2,'Raw Data'!$J:$J,J$2,'Raw Data'!$K:$K,"native",'Raw Data'!$H:$H,"Government Wallet",'Raw Data'!$I:$I,"",'Raw Data'!$M:$M,"count") -> 7 | ... Z22: =SUMIFS('Raw Data'!$L:$L,'Raw Data'!$B:$B,$B$2,'Raw Data'!$J:$J,Z$2,'Raw Data'!$K:$K,"native",'Raw Data'!$H:$H,"Government Wallet",'Raw Data'!$I:$I,"",'Raw Data'!$M:$M,"count") -> 8
A23: Wallets | B23: Individual Wallet | C23: =SUMIFS('Raw Data'!$L:$L,'Raw Data'!$B:$B,$B$2,'Raw Data'!$J:$J,C$2,'Raw Data'!$K:$K,"native",'Raw Data'!$H:$H,"Individual Wallet",'Raw Data'!$I:$I,"",'Raw Data'!$M:$M,"count") -> 2240000 | D23: =SUMIFS('Raw Data'!$L:$L,'Raw Data'!$B:$B,$B$2,'Raw Data'!$J:$J,D$2,'Raw Data'!$K:$K,"native",'Raw Data'!$H:$H,"Individual Wallet",'Raw Data'!$I:$I,"",'Raw Data'!$M:$M,"count") -> 2280000 | E23: =SUMIFS('Raw Data'!$L:$L,'Raw Data'!$B:$B,$B$2,'Raw Data'!$J:$J,E$2,'Raw Data'!$K:$K,"native",'Raw Data'!$H:$H,"Individual Wallet",'Raw Data'!$I:$I,"",'Raw Data'!$M:$M,"count") -> 2320000 | F23: =SUMIFS('Raw Data'!$L:$L,'Raw Data'!$B:$B,$B$2,'Raw Data'!$J:$J,F$2,'Raw Data'!$K:$K,"native",'Raw Data'!$H:$H,"Individual Wallet",'Raw Data'!$I:$I,"",'Raw Data'!$M:$M,"count") -> 2510000 | G23: =SUMIFS('Raw Data'!$L:$L,'Raw Data'!$B:$B,$B$2,'Raw Data'!$J:$J,G$2,'Raw Data'!$K:$K,"native",'Raw Data'!$H:$H,"Individual Wallet",'Raw Data'!$I:$I,"",'Raw Data'!$M:$M,"count") -> 2460000 | H23: =SUMIFS('Raw Data'!$L:$L,'Raw Data'!$B:$B,$B$2,'Raw Data'!$J:$J,H$2,'Raw Data'!$K:$K,"native",'Raw Data'!$H:$H,"Individual Wallet",'Raw Data'!$I:$I,"",'Raw Data'!$M:$M,"count") -> 2490000 | I23: =SUMIFS('Raw Data'!$L:$L,'Raw Data'!$B:$B,$B$2,'Raw Data'!$J:$J,I$2,'Raw Data'!$K:$K,"native",'Raw Data'!$H:$H,"Individual Wallet",'Raw Data'!$I:$I,"",'Raw Data'!$M:$M,"count") -> 2520000 | J23: =SUMIFS('Raw Data'!$L:$L,'Raw Data'!$B:$B,$B$2,'Raw Data'!$J:$J,J$2,'Raw Data'!$K:$K,"native",'Raw Data'!$H:$H,"Individual Wallet",'Raw Data'!$I:$I,"",'Raw Data'!$M:$M,"count") -> 2560000 | ... Z23: =SUMIFS('Raw Data'!$L:$L,'Raw Data'!$B:$B,$B$2,'Raw Data'!$J:$J,Z$2,'Raw Data'!$K:$K,"native",'Raw Data'!$H:$H,"Individual Wallet",'Raw Data'!$I:$I,"",'Raw Data'!$M:$M,"count") -> 3020000
A24: Wallets | B24: Merchant Wallet | C24: =SUMIFS('Raw Data'!$L:$L,'Raw Data'!$B:$B,$B$2,'Raw Data'!$J:$J,C$2,'Raw Data'!$K:$K,"native",'Raw Data'!$H:$H,"Merchant Wallet",'Raw Data'!$I:$I,"",'Raw Data'!$M:$M,"count") -> 4122 | D24: =SUMIFS('Raw Data'!$L:$L,'Raw Data'!$B:$B,$B$2,'Raw Data'!$J:$J,D$2,'Raw Data'!$K:$K,"native",'Raw Data'!$H:$H,"Merchant Wallet",'Raw Data'!$I:$I,"",'Raw Data'!$M:$M,"count") -> 4182 | E24: =SUMIFS('Raw Data'!$L:$L,'Raw Data'!$B:$B,$B$2,'Raw Data'!$J:$J,E$2,'Raw Data'!$K:$K,"native",'Raw Data'!$H:$H,"Merchant Wallet",'Raw Data'!$I:$I,"",'Raw Data'!$M:$M,"count") -> 3960 | F24: =SUMIFS('Raw Data'!$L:$L,'Raw Data'!$B:$B,$B$2,'Raw Data'!$J:$J,F$2,'Raw Data'!$K:$K,"native",'Raw Data'!$H:$H,"Merchant Wallet",'Raw Data'!$I:$I,"",'Raw Data'!$M:$M,"count") -> 3415 | G24: =SUMIFS('Raw Data'!$L:$L,'Raw Data'!$B:$B,$B$2,'Raw Data'!$J:$J,G$2,'Raw Data'!$K:$K,"native",'Raw Data'!$H:$H,"Merchant Wallet",'Raw Data'!$I:$I,"",'Raw Data'!$M:$M,"count") -> 3268 | H24: =SUMIFS('Raw Data'!$L:$L,'Raw Data'!$B:$B,$B$2,'Raw Data'!$J:$J,H$2,'Raw Data'!$K:$K,"native",'Raw Data'!$H:$H,"Merchant Wallet",'Raw Data'!$I:$I,"",'Raw Data'!$M:$M,"count") -> 3301 | I24: =SUMIFS('Raw Data'!$L:$L,'Raw Data'!$B:$B,$B$2,'Raw Data'!$J:$J,I$2,'Raw Data'!$K:$K,"native",'Raw Data'!$H:$H,"Merchant Wallet",'Raw Data'!$I:$I,"",'Raw Data'!$M:$M,"count") -> 3329 | J24: =SUMIFS('Raw Data'!$L:$L,'Raw Data'!$B:$B,$B$2,'Raw Data'!$J:$J,J$2,'Raw Data'!$K:$K,"native",'Raw Data'!$H:$H,"Merchant Wallet",'Raw Data'!$I:$I,"",'Raw Data'!$M:$M,"count") -> 3358 | ... Z24: =SUMIFS('Raw Data'!$L:$L,'Raw Data'!$B:$B,$B$2,'Raw Data'!$J:$J,Z$2,'Raw Data'!$K:$K,"native",'Raw Data'!$H:$H,"Merchant Wallet",'Raw Data'!$I:$I,"",'Raw Data'!$M:$M,"count") -> 4813
A25: TRANSACTIONS BY TRANSACTION TYPE (Number)
A26: Transactions | B26: Cash In | C26: =SUMIFS('Raw Data'!$L:$L,'Raw Data'!$B:$B,$B$2,'Raw Data'!$J:$J,C$2,'Raw Data'!$K:$K,"native",'Raw Data'!$H:$H,"Cash In",'Raw Data'!$I:$I,"",'Raw Data'!$M:$M,"count") -> 111800 | D26: =SUMIFS('Raw Data'!$L:$L,'Raw Data'!$B:$B,$B$2,'Raw Data'!$J:$J,D$2,'Raw Data'!$K:$K,"native",'Raw Data'!$H:$H,"Cash In",'Raw Data'!$I:$I,"",'Raw Data'!$M:$M,"count") -> 126100 | E26: =SUMIFS('Raw Data'!$L:$L,'Raw Data'!$B:$B,$B$2,'Raw Data'!$J:$J,E$2,'Raw Data'!$K:$K,"native",'Raw Data'!$H:$H,"Cash In",'Raw Data'!$I:$I,"",'Raw Data'!$M:$M,"count") -> 115400 | F26: =SUMIFS('Raw Data'!$L:$L,'Raw Data'!$B:$B,$B$2,'Raw Data'!$J:$J,F$2,'Raw Data'!$K:$K,"native",'Raw Data'!$H:$H,"Cash In",'Raw Data'!$I:$I,"",'Raw Data'!$M:$M,"count") -> 125700 | G26: =SUMIFS('Raw Data'!$L:$L,'Raw Data'!$B:$B,$B$2,'Raw Data'!$J:$J,G$2,'Raw Data'!$K:$K,"native",'Raw Data'!$H:$H,"Cash In",'Raw Data'!$I:$I,"",'Raw Data'!$M:$M,"count") -> 117400 | H26: =SUMIFS('Raw Data'!$L:$L,'Raw Data'!$B:$B,$B$2,'Raw Data'!$J:$J,H$2,'Raw Data'!$K:$K,"native",'Raw Data'!$H:$H,"Cash In",'Raw Data'!$I:$I,"",'Raw Data'!$M:$M,"count") -> 107400 | I26: =SUMIFS('Raw Data'!$L:$L,'Raw Data'!$B:$B,$B$2,'Raw Data'!$J:$J,I$2,'Raw Data'!$K:$K,"native",'Raw Data'!$H:$H,"Cash In",'Raw Data'!$I:$I,"",'Raw Data'!$M:$M,"count") -> 115100 | J26: =SUMIFS('Raw Data'!$L:$L,'Raw Data'!$B:$B,$B$2,'Raw Data'!$J:$J,J$2,'Raw Data'!$K:$K,"native",'Raw Data'!$H:$H,"Cash In",'Raw Data'!$I:$I,"",'Raw Data'!$M:$M,"count") -> 116000 | ... Z26: =SUMIFS('Raw Data'!$L:$L,'Raw Data'!$B:$B,$B$2,'Raw Data'!$J:$J,Z$2,'Raw Data'!$K:$K,"native",'Raw Data'!$H:$H,"Cash In",'Raw Data'!$I:$I,"",'Raw Data'!$M:$M,"count") -> 20600
A27: Transactions | B27: Cash Out | C27: =SUMIFS('Raw Data'!$L:$L,'Raw Data'!$B:$B,$B$2,'Raw Data'!$J:$J,C$2,'Raw Data'!$K:$K,"native",'Raw Data'!$H:$H,"Cash Out",'Raw Data'!$I:$I,"",'Raw Data'!$M:$M,"count") -> 172300 | D27: =SUMIFS('Raw Data'!$L:$L,'Raw Data'!$B:$B,$B$2,'Raw Data'!$J:$J,D$2,'Raw Data'!$K:$K,"native",'Raw Data'!$H:$H,"Cash Out",'Raw Data'!$I:$I,"",'Raw Data'!$M:$M,"count") -> 198100 | E27: =SUMIFS('Raw Data'!$L:$L,'Raw Data'!$B:$B,$B$2,'Raw Data'!$J:$J,E$2,'Raw Data'!$K:$K,"native",'Raw Data'!$H:$H,"Cash Out",'Raw Data'!$I:$I,"",'Raw Data'!$M:$M,"count") -> 169300 | F27: =SUMIFS('Raw Data'!$L:$L,'Raw Data'!$B:$B,$B$2,'Raw Data'!$J:$J,F$2,'Raw Data'!$K:$K,"native",'Raw Data'!$H:$H,"Cash Out",'Raw Data'!$I:$I,"",'Raw Data'!$M:$M,"count") -> 183600 | G27: =SUMIFS('Raw Data'!$L:$L,'Raw Data'!$B:$B,$B$2,'Raw Data'!$J:$J,G$2,'Raw Data'!$K:$K,"native",'Raw Data'!$H:$H,"Cash Out",'Raw Data'!$I:$I,"",'Raw Data'!$M:$M,"count") -> 172900 | H27: =SUMIFS('Raw Data'!$L:$L,'Raw Data'!$B:$B,$B$2,'Raw Data'!$J:$J,H$2,'Raw Data'!$K:$K,"native",'Raw Data'!$H:$H,"Cash Out",'Raw Data'!$I:$I,"",'Raw Data'!$M:$M,"count") -> 147700 | I27: =SUMIFS('Raw Data'!$L:$L,'Raw Data'!$B:$B,$B$2,'Raw Data'!$J:$J,I$2,'Raw Data'!$K:$K,"native",'Raw Data'!$H:$H,"Cash Out",'Raw Data'!$I:$I,"",'Raw Data'!$M:$M,"count") -> 186400 | J27: =SUMIFS('Raw Data'!$L:$L,'Raw Data'!$B:$B,$B$2,'Raw Data'!$J:$J,J$2,'Raw Data'!$K:$K,"native",'Raw Data'!$H:$H,"Cash Out",'Raw Data'!$I:$I,"",'Raw Data'!$M:$M,"count") -> 152400 | ... Z27: =SUMIFS('Raw Data'!$L:$L,'Raw Data'!$B:$B,$B$2,'Raw Data'!$J:$J,Z$2,'Raw Data'!$K:$K,"native",'Raw Data'!$H:$H,"Cash Out",'Raw Data'!$I:$I,"",'Raw Data'!$M:$M,"count") -> 60500
A28: Transactions | B28: Money Transfers | C28: =SUMIFS('Raw Data'!$L:$L,'Raw Data'!$B:$B,$B$2,'Raw Data'!$J:$J,C$2,'Raw Data'!$K:$K,"native",'Raw Data'!$H:$H,"Money Transfers",'Raw Data'!$I:$I,"",'Raw Data'!$M:$M,"count") -> 4580000 | D28: =SUMIFS('Raw Data'!$L:$L,'Raw Data'!$B:$B,$B$2,'Raw Data'!$J:$J,D$2,'Raw Data'!$K:$K,"native",'Raw Data'!$H:$H,"Money Transfers",'Raw Data'!$I:$I,"",'Raw Data'!$M:$M,"count") -> 5080000 | E28: =SUMIFS('Raw Data'!$L:$L,'Raw Data'!$B:$B,$B$2,'Raw Data'!$J:$J,E$2,'Raw Data'!$K:$K,"native",'Raw Data'!$H:$H,"Money Transfers",'Raw Data'!$I:$I,"",'Raw Data'!$M:$M,"count") -> 5090000 | F28: =SUMIFS('Raw Data'!$L:$L,'Raw Data'!$B:$B,$B$2,'Raw Data'!$J:$J,F$2,'Raw Data'!$K:$K,"native",'Raw Data'!$H:$H,"Money Transfers",'Raw Data'!$I:$I,"",'Raw Data'!$M:$M,"count") -> 5730000 | G28: =SUMIFS('Raw Data'!$L:$L,'Raw Data'!$B:$B,$B$2,'Raw Data'!$J:$J,G$2,'Raw Data'!$K:$K,"native",'Raw Data'!$H:$H,"Money Transfers",'Raw Data'!$I:$I,"",'Raw Data'!$M:$M,"count") -> 5930000 | H28: =SUMIFS('Raw Data'!$L:$L,'Raw Data'!$B:$B,$B$2,'Raw Data'!$J:$J,H$2,'Raw Data'!$K:$K,"native",'Raw Data'!$H:$H,"Money Transfers",'Raw Data'!$I:$I,"",'Raw Data'!$M:$M,"count") -> 5500000 | I28: =SUMIFS('Raw Data'!$L:$L,'Raw Data'!$B:$B,$B$2,'Raw Data'!$J:$J,I$2,'Raw Data'!$K:$K,"native",'Raw Data'!$H:$H,"Money Transfers",'Raw Data'!$I:$I,"",'Raw Data'!$M:$M,"count") -> 6760000 | J28: =SUMIFS('Raw Data'!$L:$L,'Raw Data'!$B:$B,$B$2,'Raw Data'!$J:$J,J$2,'Raw Data'!$K:$K,"native",'Raw Data'!$H:$H,"Money Transfers",'Raw Data'!$I:$I,"",'Raw Data'!$M:$M,"count") -> 6480000 | ... Z28: =SUMIFS('Raw Data'!$L:$L,'Raw Data'!$B:$B,$B$2,'Raw Data'!$J:$J,Z$2,'Raw Data'!$K:$K,"native",'Raw Data'!$H:$H,"Money Transfers",'Raw Data'!$I:$I,"",'Raw Data'!$M:$M,"count") -> 14400000
A29: Transactions | B29: Purchases | C29: =SUMIFS('Raw Data'!$L:$L,'Raw Data'!$B:$B,$B$2,'Raw Data'!$J:$J,C$2,'Raw Data'!$K:$K,"native",'Raw Data'!$H:$H,"Purchases",'Raw Data'!$I:$I,"",'Raw Data'!$M:$M,"count") -> 177900 | D29: =SUMIFS('Raw Data'!$L:$L,'Raw Data'!$B:$B,$B$2,'Raw Data'!$J:$J,D$2,'Raw Data'!$K:$K,"native",'Raw Data'!$H:$H,"Purchases",'Raw Data'!$I:$I,"",'Raw Data'!$M:$M,"count") -> 187700 | E29: =SUMIFS('Raw Data'!$L:$L,'Raw Data'!$B:$B,$B$2,'Raw Data'!$J:$J,E$2,'Raw Data'!$K:$K,"native",'Raw Data'!$H:$H,"Purchases",'Raw Data'!$I:$I,"",'Raw Data'!$M:$M,"count") -> 191900 | F29: =SUMIFS('Raw Data'!$L:$L,'Raw Data'!$B:$B,$B$2,'Raw Data'!$J:$J,F$2,'Raw Data'!$K:$K,"native",'Raw Data'!$H:$H,"Purchases",'Raw Data'!$I:$I,"",'Raw Data'!$M:$M,"count") -> 217200 | G29: =SUMIFS('Raw Data'!$L:$L,'Raw Data'!$B:$B,$B$2,'Raw Data'!$J:$J,G$2,'Raw Data'!$K:$K,"native",'Raw Data'!$H:$H,"Purchases",'Raw Data'!$I:$I,"",'Raw Data'!$M:$M,"count") -> 190800 | H29: =SUMIFS('Raw Data'!$L:$L,'Raw Data'!$B:$B,$B$2,'Raw Data'!$J:$J,H$2,'Raw Data'!$K:$K,"native",'Raw Data'!$H:$H,"Purchases",'Raw Data'!$I:$I,"",'Raw Data'!$M:$M,"count") -> 176900 | I29: =SUMIFS('Raw Data'!$L:$L,'Raw Data'!$B:$B,$B$2,'Raw Data'!$J:$J,I$2,'Raw Data'!$K:$K,"native",'Raw Data'!$H:$H,"Purchases",'Raw Data'!$I:$I,"",'Raw Data'!$M:$M,"count") -> 230800 | J29: =SUMIFS('Raw Data'!$L:$L,'Raw Data'!$B:$B,$B$2,'Raw Data'!$J:$J,J$2,'Raw Data'!$K:$K,"native",'Raw Data'!$H:$H,"Purchases",'Raw Data'!$I:$I,"",'Raw Data'!$M:$M,"count") -> 243100 | ... Z29: =SUMIFS('Raw Data'!$L:$L,'Raw Data'!$B:$B,$B$2,'Raw Data'!$J:$J,Z$2,'Raw Data'!$K:$K,"native",'Raw Data'!$H:$H,"Purchases",'Raw Data'!$I:$I,"",'Raw Data'!$M:$M,"count") -> 3200000
A30: TRANSACTIONS BY TYPE — DETAIL (%)
A31: Transactions | B31: Cash In: ATM/Kiosk | C31: =(SUMIFS('Raw Data'!$L:$L,'Raw Data'!$B:$B,$B$2,'Raw Data'!$J:$J,C$2,'Raw Data'!$K:$K,"native",'Raw Data'!$H:$H,"Cash In",'Raw Data'!$I:$I,"ATM/Kiosk",'Raw Data'!$M:$M,"percent",'Raw Data'!$F:$F,"Number*"))/100 -> 0.0173 | D31: =(SUMIFS('Raw Data'!$L:$L,'Raw Data'!$B:$B,$B$2,'Raw Data'!$J:$J,D$2,'Raw Data'!$K:$K,"native",'Raw Data'!$H:$H,"Cash In",'Raw Data'!$I:$I,"ATM/Kiosk",'Raw Data'!$M:$M,"percent",'Raw Data'!$F:$F,"Number*"))/100 -> 0.0143 | E31: =(SUMIFS('Raw Data'!$L:$L,'Raw Data'!$B:$B,$B$2,'Raw Data'!$J:$J,E$2,'Raw Data'!$K:$K,"native",'Raw Data'!$H:$H,"Cash In",'Raw Data'!$I:$I,"ATM/Kiosk",'Raw Data'!$M:$M,"percent",'Raw Data'!$F:$F,"Number*"))/100 -> 0.015 | F31: =(SUMIFS('Raw Data'!$L:$L,'Raw Data'!$B:$B,$B$2,'Raw Data'!$J:$J,F$2,'Raw Data'!$K:$K,"native",'Raw Data'!$H:$H,"Cash In",'Raw Data'!$I:$I,"ATM/Kiosk",'Raw Data'!$M:$M,"percent",'Raw Data'!$F:$F,"Number*"))/100 -> 0.0121 | G31: =(SUMIFS('Raw Data'!$L:$L,'Raw Data'!$B:$B,$B$2,'Raw Data'!$J:$J,G$2,'Raw Data'!$K:$K,"native",'Raw Data'!$H:$H,"Cash In",'Raw Data'!$I:$I,"ATM/Kiosk",'Raw Data'!$M:$M,"percent",'Raw Data'!$F:$F,"Number*"))/100 -> 0.0134 | H31: =(SUMIFS('Raw Data'!$L:$L,'Raw Data'!$B:$B,$B$2,'Raw Data'!$J:$J,H$2,'Raw Data'!$K:$K,"native",'Raw Data'!$H:$H,"Cash In",'Raw Data'!$I:$I,"ATM/Kiosk",'Raw Data'!$M:$M,"percent",'Raw Data'!$F:$F,"Number*"))/100 -> 0.0125 | I31: =(SUMIFS('Raw Data'!$L:$L,'Raw Data'!$B:$B,$B$2,'Raw Data'!$J:$J,I$2,'Raw Data'!$K:$K,"native",'Raw Data'!$H:$H,"Cash In",'Raw Data'!$I:$I,"ATM/Kiosk",'Raw Data'!$M:$M,"percent",'Raw Data'!$F:$F,"Number*"))/100 -> 0.0167 | J31: =(SUMIFS('Raw Data'!$L:$L,'Raw Data'!$B:$B,$B$2,'Raw Data'!$J:$J,J$2,'Raw Data'!$K:$K,"native",'Raw Data'!$H:$H,"Cash In",'Raw Data'!$I:$I,"ATM/Kiosk",'Raw Data'!$M:$M,"percent",'Raw Data'!$F:$F,"Number*"))/100 -> 0.0174 | ... M31: =(SUMIFS('Raw Data'!$L:$L,'Raw Data'!$B:$B,$B$2,'Raw Data'!$J:$J,M$2,'Raw Data'!$K:$K,"native",'Raw Data'!$H:$H,"Cash In",'Raw Data'!$I:$I,"ATM/Kiosk",'Raw Data'!$M:$M,"percent",'Raw Data'!$F:$F,"Number*"))/100 -> 0.0146 | Z31: =(SUMIFS('Raw Data'!$L:$L,'Raw Data'!$B:$B,$B$2,'Raw Data'!$J:$J,Z$2,'Raw Data'!$K:$K,"native",'Raw Data'!$H:$H,"Cash In",'Raw Data'!$I:$I,"ATM/Kiosk",'Raw Data'!$M:$M,"percent",'Raw Data'!$F:$F,"Number*"))/100 -> 0.0963
A32: Transactions | B32: Cash In: Agent/Teller | C32: =(SUMIFS('Raw Data'!$L:$L,'Raw Data'!$B:$B,$B$2,'Raw Data'!$J:$J,C$2,'Raw Data'!$K:$K,"native",'Raw Data'!$H:$H,"Cash In",'Raw Data'!$I:$I,"Agent/Teller",'Raw Data'!$M:$M,"percent",'Raw Data'!$F:$F,"Number*"))/100 -> 0.9827 | D32: =(SUMIFS('Raw Data'!$L:$L,'Raw Data'!$B:$B,$B$2,'Raw Data'!$J:$J,D$2,'Raw Data'!$K:$K,"native",'Raw Data'!$H:$H,"Cash In",'Raw Data'!$I:$I,"Agent/Teller",'Raw Data'!$M:$M,"percent",'Raw Data'!$F:$F,"Number*"))/100 -> 0.9857 | E32: =(SUMIFS('Raw Data'!$L:$L,'Raw Data'!$B:$B,$B$2,'Raw Data'!$J:$J,E$2,'Raw Data'!$K:$K,"native",'Raw Data'!$H:$H,"Cash In",'Raw Data'!$I:$I,"Agent/Teller",'Raw Data'!$M:$M,"percent",'Raw Data'!$F:$F,"Number*"))/100 -> 0.985 | F32: =(SUMIFS('Raw Data'!$L:$L,'Raw Data'!$B:$B,$B$2,'Raw Data'!$J:$J,F$2,'Raw Data'!$K:$K,"native",'Raw Data'!$H:$H,"Cash In",'Raw Data'!$I:$I,"Agent/Teller",'Raw Data'!$M:$M,"percent",'Raw Data'!$F:$F,"Number*"))/100 -> 0.9879 | G32: =(SUMIFS('Raw Data'!$L:$L,'Raw Data'!$B:$B,$B$2,'Raw Data'!$J:$J,G$2,'Raw Data'!$K:$K,"native",'Raw Data'!$H:$H,"Cash In",'Raw Data'!$I:$I,"Agent/Teller",'Raw Data'!$M:$M,"percent",'Raw Data'!$F:$F,"Number*"))/100 -> 0.9866 | H32: =(SUMIFS('Raw Data'!$L:$L,'Raw Data'!$B:$B,$B$2,'Raw Data'!$J:$J,H$2,'Raw Data'!$K:$K,"native",'Raw Data'!$H:$H,"Cash In",'Raw Data'!$I:$I,"Agent/Teller",'Raw Data'!$M:$M,"percent",'Raw Data'!$F:$F,"Number*"))/100 -> 0.9875 | I32: =(SUMIFS('Raw Data'!$L:$L,'Raw Data'!$B:$B,$B$2,'Raw Data'!$J:$J,I$2,'Raw Data'!$K:$K,"native",'Raw Data'!$H:$H,"Cash In",'Raw Data'!$I:$I,"Agent/Teller",'Raw Data'!$M:$M,"percent",'Raw Data'!$F:$F,"Number*"))/100 -> 0.9833 | J32: =(SUMIFS('Raw Data'!$L:$L,'Raw Data'!$B:$B,$B$2,'Raw Data'!$J:$J,J$2,'Raw Data'!$K:$K,"native",'Raw Data'!$H:$H,"Cash In",'Raw Data'!$I:$I,"Agent/Teller",'Raw Data'!$M:$M,"percent",'Raw Data'!$F:$F,"Number*"))/100 -> 0.9826 | ... M32: =(SUMIFS('Raw Data'!$L:$L,'Raw Data'!$B:$B,$B$2,'Raw Data'!$J:$J,M$2,'Raw Data'!$K:$K,"native",'Raw Data'!$H:$H,"Cash In",'Raw Data'!$I:$I,"Agent/Teller",'Raw Data'!$M:$M,"percent",'Raw Data'!$F:$F,"Number*"))/100 -> 0.9854 | Z32: =(SUMIFS('Raw Data'!$L:$L,'Raw Data'!$B:$B,$B$2,'Raw Data'!$J:$J,Z$2,'Raw Data'!$K:$K,"native",'Raw Data'!$H:$H,"Cash In",'Raw Data'!$I:$I,"Agent/Teller",'Raw Data'!$M:$M,"percent",'Raw Data'!$F:$F,"Number*"))/100 -> 0.9037
A33: Transactions | B33: Cash Out: ATM/Kiosk | C33: =(SUMIFS('Raw Data'!$L:$L,'Raw Data'!$B:$B,$B$2,'Raw Data'!$J:$J,C$2,'Raw Data'!$K:$K,"native",'Raw Data'!$H:$H,"Cash Out",'Raw Data'!$I:$I,"ATM/Kiosk",'Raw Data'!$M:$M,"percent",'Raw Data'!$F:$F,"Number*"))/100 -> 0.0878 | D33: =(SUMIFS('Raw Data'!$L:$L,'Raw Data'!$B:$B,$B$2,'Raw Data'!$J:$J,D$2,'Raw Data'!$K:$K,"native",'Raw Data'!$H:$H,"Cash Out",'Raw Data'!$I:$I,"ATM/Kiosk",'Raw Data'!$M:$M,"percent",'Raw Data'!$F:$F,"Number*"))/100 -> 0.0802 | E33: =(SUMIFS('Raw Data'!$L:$L,'Raw Data'!$B:$B,$B$2,'Raw Data'!$J:$J,E$2,'Raw Data'!$K:$K,"native",'Raw Data'!$H:$H,"Cash Out",'Raw Data'!$I:$I,"ATM/Kiosk",'Raw Data'!$M:$M,"percent",'Raw Data'!$F:$F,"Number*"))/100 -> 0.0852 | F33: =(SUMIFS('Raw Data'!$L:$L,'Raw Data'!$B:$B,$B$2,'Raw Data'!$J:$J,F$2,'Raw Data'!$K:$K,"native",'Raw Data'!$H:$H,"Cash Out",'Raw Data'!$I:$I,"ATM/Kiosk",'Raw Data'!$M:$M,"percent",'Raw Data'!$F:$F,"Number*"))/100 -> 0.0755 | G33: =(SUMIFS('Raw Data'!$L:$L,'Raw Data'!$B:$B,$B$2,'Raw Data'!$J:$J,G$2,'Raw Data'!$K:$K,"native",'Raw Data'!$H:$H,"Cash Out",'Raw Data'!$I:$I,"ATM/Kiosk",'Raw Data'!$M:$M,"percent",'Raw Data'!$F:$F,"Number*"))/100 -> 0.0729 | H33: =(SUMIFS('Raw Data'!$L:$L,'Raw Data'!$B:$B,$B$2,'Raw Data'!$J:$J,H$2,'Raw Data'!$K:$K,"native",'Raw Data'!$H:$H,"Cash Out",'Raw Data'!$I:$I,"ATM/Kiosk",'Raw Data'!$M:$M,"percent",'Raw Data'!$F:$F,"Number*"))/100 -> 0.0692 | I33: =(SUMIFS('Raw Data'!$L:$L,'Raw Data'!$B:$B,$B$2,'Raw Data'!$J:$J,I$2,'Raw Data'!$K:$K,"native",'Raw Data'!$H:$H,"Cash Out",'Raw Data'!$I:$I,"ATM/Kiosk",'Raw Data'!$M:$M,"percent",'Raw Data'!$F:$F,"Number*"))/100 -> 0.0696 | J33: =(SUMIFS('Raw Data'!$L:$L,'Raw Data'!$B:$B,$B$2,'Raw Data'!$J:$J,J$2,'Raw Data'!$K:$K,"native",'Raw Data'!$H:$H,"Cash Out",'Raw Data'!$I:$I,"ATM/Kiosk",'Raw Data'!$M:$M,"percent",'Raw Data'!$F:$F,"Number*"))/100 -> 0.0725 | ... M33: =(SUMIFS('Raw Data'!$L:$L,'Raw Data'!$B:$B,$B$2,'Raw Data'!$J:$J,M$2,'Raw Data'!$K:$K,"native",'Raw Data'!$H:$H,"Cash Out",'Raw Data'!$I:$I,"ATM/Kiosk",'Raw Data'!$M:$M,"percent",'Raw Data'!$F:$F,"Number*"))/100 -> 0.06 | Z33: =(SUMIFS('Raw Data'!$L:$L,'Raw Data'!$B:$B,$B$2,'Raw Data'!$J:$J,Z$2,'Raw Data'!$K:$K,"native",'Raw Data'!$H:$H,"Cash Out",'Raw Data'!$I:$I,"ATM/Kiosk",'Raw Data'!$M:$M,"percent",'Raw Data'!$F:$F,"Number*"))/100 -> 0.1333
A34: Transactions | B34: Cash Out: Agent/Teller | C34: =(SUMIFS('Raw Data'!$L:$L,'Raw Data'!$B:$B,$B$2,'Raw Data'!$J:$J,C$2,'Raw Data'!$K:$K,"native",'Raw Data'!$H:$H,"Cash Out",'Raw Data'!$I:$I,"Agent/Teller",'Raw Data'!$M:$M,"percent",'Raw Data'!$F:$F,"Number*"))/100 -> 0.9122 | D34: =(SUMIFS('Raw Data'!$L:$L,'Raw Data'!$B:$B,$B$2,'Raw Data'!$J:$J,D$2,'Raw Data'!$K:$K,"native",'Raw Data'!$H:$H,"Cash Out",'Raw Data'!$I:$I,"Agent/Teller",'Raw Data'!$M:$M,"percent",'Raw Data'!$F:$F,"Number*"))/100 -> 0.9198 | E34: =(SUMIFS('Raw Data'!$L:$L,'Raw Data'!$B:$B,$B$2,'Raw Data'!$J:$J,E$2,'Raw Data'!$K:$K,"native",'Raw Data'!$H:$H,"Cash Out",'Raw Data'!$I:$I,"Agent/Teller",'Raw Data'!$M:$M,"percent",'Raw Data'!$F:$F,"Number*"))/100 -> 0.9148 | F34: =(SUMIFS('Raw Data'!$L:$L,'Raw Data'!$B:$B,$B$2,'Raw Data'!$J:$J,F$2,'Raw Data'!$K:$K,"native",'Raw Data'!$H:$H,"Cash Out",'Raw Data'!$I:$I,"Agent/Teller",'Raw Data'!$M:$M,"percent",'Raw Data'!$F:$F,"Number*"))/100 -> 0.9245 | G34: =(SUMIFS('Raw Data'!$L:$L,'Raw Data'!$B:$B,$B$2,'Raw Data'!$J:$J,G$2,'Raw Data'!$K:$K,"native",'Raw Data'!$H:$H,"Cash Out",'Raw Data'!$I:$I,"Agent/Teller",'Raw Data'!$M:$M,"percent",'Raw Data'!$F:$F,"Number*"))/100 -> 0.9271 | H34: =(SUMIFS('Raw Data'!$L:$L,'Raw Data'!$B:$B,$B$2,'Raw Data'!$J:$J,H$2,'Raw Data'!$K:$K,"native",'Raw Data'!$H:$H,"Cash Out",'Raw Data'!$I:$I,"Agent/Teller",'Raw Data'!$M:$M,"percent",'Raw Data'!$F:$F,"Number*"))/100 -> 0.9308 | I34: =(SUMIFS('Raw Data'!$L:$L,'Raw Data'!$B:$B,$B$2,'Raw Data'!$J:$J,I$2,'Raw Data'!$K:$K,"native",'Raw Data'!$H:$H,"Cash Out",'Raw Data'!$I:$I,"Agent/Teller",'Raw Data'!$M:$M,"percent",'Raw Data'!$F:$F,"Number*"))/100 -> 0.9304 | J34: =(SUMIFS('Raw Data'!$L:$L,'Raw Data'!$B:$B,$B$2,'Raw Data'!$J:$J,J$2,'Raw Data'!$K:$K,"native",'Raw Data'!$H:$H,"Cash Out",'Raw Data'!$I:$I,"Agent/Teller",'Raw Data'!$M:$M,"percent",'Raw Data'!$F:$F,"Number*"))/100 -> 0.9275 | ... M34: =(SUMIFS('Raw Data'!$L:$L,'Raw Data'!$B:$B,$B$2,'Raw Data'!$J:$J,M$2,'Raw Data'!$K:$K,"native",'Raw Data'!$H:$H,"Cash Out",'Raw Data'!$I:$I,"Agent/Teller",'Raw Data'!$M:$M,"percent",'Raw Data'!$F:$F,"Number*"))/100 -> 0.94 | Z34: =(SUMIFS('Raw Data'!$L:$L,'Raw Data'!$B:$B,$B$2,'Raw Data'!$J:$J,Z$2,'Raw Data'!$K:$K,"native",'Raw Data'!$H:$H,"Cash Out",'Raw Data'!$I:$I,"Agent/Teller",'Raw Data'!$M:$M,"percent",'Raw Data'!$F:$F,"Number*"))/100 -> 0.8667
A35: Transactions | B35: Money Transfers: Aid/Charity/Grant | C35: =(SUMIFS('Raw Data'!$L:$L,'Raw Data'!$B:$B,$B$2,'Raw Data'!$J:$J,C$2,'Raw Data'!$K:$K,"native",'Raw Data'!$H:$H,"Money Transfers",'Raw Data'!$I:$I,"Aid/Charity/Grant",'Raw Data'!$M:$M,"percent",'Raw Data'!$F:$F,"Number*"))/100 -> 0.0262 | D35: =(SUMIFS('Raw Data'!$L:$L,'Raw Data'!$B:$B,$B$2,'Raw Data'!$J:$J,D$2,'Raw Data'!$K:$K,"native",'Raw Data'!$H:$H,"Money Transfers",'Raw Data'!$I:$I,"Aid/Charity/Grant",'Raw Data'!$M:$M,"percent",'Raw Data'!$F:$F,"Number*"))/100 -> 0.0204 | E35: =(SUMIFS('Raw Data'!$L:$L,'Raw Data'!$B:$B,$B$2,'Raw Data'!$J:$J,E$2,'Raw Data'!$K:$K,"native",'Raw Data'!$H:$H,"Money Transfers",'Raw Data'!$I:$I,"Aid/Charity/Grant",'Raw Data'!$M:$M,"percent",'Raw Data'!$F:$F,"Number*"))/100 -> 0.0214 | F35: =(SUMIFS('Raw Data'!$L:$L,'Raw Data'!$B:$B,$B$2,'Raw Data'!$J:$J,F$2,'Raw Data'!$K:$K,"native",'Raw Data'!$H:$H,"Money Transfers",'Raw Data'!$I:$I,"Aid/Charity/Grant",'Raw Data'!$M:$M,"percent",'Raw Data'!$F:$F,"Number*"))/100 -> 0.0226 | G35: =(SUMIFS('Raw Data'!$L:$L,'Raw Data'!$B:$B,$B$2,'Raw Data'!$J:$J,G$2,'Raw Data'!$K:$K,"native",'Raw Data'!$H:$H,"Money Transfers",'Raw Data'!$I:$I,"Aid/Charity/Grant",'Raw Data'!$M:$M,"percent",'Raw Data'!$F:$F,"Number*"))/100 -> 0.0157 | H35: =(SUMIFS('Raw Data'!$L:$L,'Raw Data'!$B:$B,$B$2,'Raw Data'!$J:$J,H$2,'Raw Data'!$K:$K,"native",'Raw Data'!$H:$H,"Money Transfers",'Raw Data'!$I:$I,"Aid/Charity/Grant",'Raw Data'!$M:$M,"percent",'Raw Data'!$F:$F,"Number*"))/100 -> 0.0176 | I35: =(SUMIFS('Raw Data'!$L:$L,'Raw Data'!$B:$B,$B$2,'Raw Data'!$J:$J,I$2,'Raw Data'!$K:$K,"native",'Raw Data'!$H:$H,"Money Transfers",'Raw Data'!$I:$I,"Aid/Charity/Grant",'Raw Data'!$M:$M,"percent",'Raw Data'!$F:$F,"Number*"))/100 -> 0.0222 | J35: =(SUMIFS('Raw Data'!$L:$L,'Raw Data'!$B:$B,$B$2,'Raw Data'!$J:$J,J$2,'Raw Data'!$K:$K,"native",'Raw Data'!$H:$H,"Money Transfers",'Raw Data'!$I:$I,"Aid/Charity/Grant",'Raw Data'!$M:$M,"percent",'Raw Data'!$F:$F,"Number*"))/100 -> 0.0143 | ... M35: =(SUMIFS('Raw Data'!$L:$L,'Raw Data'!$B:$B,$B$2,'Raw Data'!$J:$J,M$2,'Raw Data'!$K:$K,"native",'Raw Data'!$H:$H,"Money Transfers",'Raw Data'!$I:$I,"Aid/Charity/Grant",'Raw Data'!$M:$M,"percent",'Raw Data'!$F:$F,"Number*"))/100 -> 0.0052 | Z35: =(SUMIFS('Raw Data'!$L:$L,'Raw Data'!$B:$B,$B$2,'Raw Data'!$J:$J,Z$2,'Raw Data'!$K:$K,"native",'Raw Data'!$H:$H,"Money Transfers",'Raw Data'!$I:$I,"Aid/Charity/Grant",'Raw Data'!$M:$M,"percent",'Raw Data'!$F:$F,"Number*"))/100 -> 0.0122
A36: Transactions | B36: Money Transfers: Cross Border Remittances | C36: =(SUMIFS('Raw Data'!$L:$L,'Raw Data'!$B:$B,$B$2,'Raw Data'!$J:$J,C$2,'Raw Data'!$K:$K,"native",'Raw Data'!$H:$H,"Money Transfers",'Raw Data'!$I:$I,"Cross Border Remittances",'Raw Data'!$M:$M,"percent",'Raw Data'!$F:$F,"Number*"))/100 -> 0.0001 | D36: =(SUMIFS('Raw Data'!$L:$L,'Raw Data'!$B:$B,$B$2,'Raw Data'!$J:$J,D$2,'Raw Data'!$K:$K,"native",'Raw Data'!$H:$H,"Money Transfers",'Raw Data'!$I:$I,"Cross Border Remittances",'Raw Data'!$M:$M,"percent",'Raw Data'!$F:$F,"Number*"))/100 -> 0.0001 | E36: =(SUMIFS('Raw Data'!$L:$L,'Raw Data'!$B:$B,$B$2,'Raw Data'!$J:$J,E$2,'Raw Data'!$K:$K,"native",'Raw Data'!$H:$H,"Money Transfers",'Raw Data'!$I:$I,"Cross Border Remittances",'Raw Data'!$M:$M,"percent",'Raw Data'!$F:$F,"Number*"))/100 -> 0.0001 | F36: =(SUMIFS('Raw Data'!$L:$L,'Raw Data'!$B:$B,$B$2,'Raw Data'!$J:$J,F$2,'Raw Data'!$K:$K,"native",'Raw Data'!$H:$H,"Money Transfers",'Raw Data'!$I:$I,"Cross Border Remittances",'Raw Data'!$M:$M,"percent",'Raw Data'!$F:$F,"Number*"))/100 -> 0.0001 | G36: =(SUMIFS('Raw Data'!$L:$L,'Raw Data'!$B:$B,$B$2,'Raw Data'!$J:$J,G$2,'Raw Data'!$K:$K,"native",'Raw Data'!$H:$H,"Money Transfers",'Raw Data'!$I:$I,"Cross Border Remittances",'Raw Data'!$M:$M,"percent",'Raw Data'!$F:$F,"Number*"))/100 -> 0 | H36: =(SUMIFS('Raw Data'!$L:$L,'Raw Data'!$B:$B,$B$2,'Raw Data'!$J:$J,H$2,'Raw Data'!$K:$K,"native",'Raw Data'!$H:$H,"Money Transfers",'Raw Data'!$I:$I,"Cross Border Remittances",'Raw Data'!$M:$M,"percent",'Raw Data'!$F:$F,"Number*"))/100 -> 0 | I36: =(SUMIFS('Raw Data'!$L:$L,'Raw Data'!$B:$B,$B$2,'Raw Data'!$J:$J,I$2,'Raw Data'!$K:$K,"native",'Raw Data'!$H:$H,"Money Transfers",'Raw Data'!$I:$I,"Cross Border Remittances",'Raw Data'!$M:$M,"percent",'Raw Data'!$F:$F,"Number*"))/100 -> 0 | J36: =(SUMIFS('Raw Data'!$L:$L,'Raw Data'!$B:$B,$B$2,'Raw Data'!$J:$J,J$2,'Raw Data'!$K:$K,"native",'Raw Data'!$H:$H,"Money Transfers",'Raw Data'!$I:$I,"Cross Border Remittances",'Raw Data'!$M:$M,"percent",'Raw Data'!$F:$F,"Number*"))/100 -> 0 | ... L36: =(SUMIFS('Raw Data'!$L:$L,'Raw Data'!$B:$B,$B$2,'Raw Data'!$J:$J,L$2,'Raw Data'!$K:$K,"native",'Raw Data'!$H:$H,"Money Transfers",'Raw Data'!$I:$I,"Cross Border Remittances",'Raw Data'!$M:$M,"percent",'Raw Data'!$F:$F,"Number*"))/100 -> 0 | Z36: =(SUMIFS('Raw Data'!$L:$L,'Raw Data'!$B:$B,$B$2,'Raw Data'!$J:$J,Z$2,'Raw Data'!$K:$K,"native",'Raw Data'!$H:$H,"Money Transfers",'Raw Data'!$I:$I,"Loan/Loan Installment",'Raw Data'!$M:$M,"percent",'Raw Data'!$F:$F,"Number*"))/100 -> 0.0001
A37: Transactions | B37: Money Transfers: Loan/Loan Installment | C37: =(SUMIFS('Raw Data'!$L:$L,'Raw Data'!$B:$B,$B$2,'Raw Data'!$J:$J,C$2,'Raw Data'!$K:$K,"native",'Raw Data'!$H:$H,"Money Transfers",'Raw Data'!$I:$I,"Loan/Loan Installment",'Raw Data'!$M:$M,"percent",'Raw Data'!$F:$F,"Number*"))/100 -> 0.0067 | D37: =(SUMIFS('Raw Data'!$L:$L,'Raw Data'!$B:$B,$B$2,'Raw Data'!$J:$J,D$2,'Raw Data'!$K:$K,"native",'Raw Data'!$H:$H,"Money Transfers",'Raw Data'!$I:$I,"Loan/Loan Installment",'Raw Data'!$M:$M,"percent",'Raw Data'!$F:$F,"Number*"))/100 -> 0.0067 | E37: =(SUMIFS('Raw Data'!$L:$L,'Raw Data'!$B:$B,$B$2,'Raw Data'!$J:$J,E$2,'Raw Data'!$K:$K,"native",'Raw Data'!$H:$H,"Money Transfers",'Raw Data'!$I:$I,"Loan/Loan Installment",'Raw Data'!$M:$M,"percent",'Raw Data'!$F:$F,"Number*"))/100 -> 0.0057 | F37: =(SUMIFS('Raw Data'!$L:$L,'Raw Data'!$B:$B,$B$2,'Raw Data'!$J:$J,F$2,'Raw Data'!$K:$K,"native",'Raw Data'!$H:$H,"Money Transfers",'Raw Data'!$I:$I,"Loan/Loan Installment",'Raw Data'!$M:$M,"percent",'Raw Data'!$F:$F,"Number*"))/100 -> 0.0053 | G37: =(SUMIFS('Raw Data'!$L:$L,'Raw Data'!$B:$B,$B$2,'Raw Data'!$J:$J,G$2,'Raw Data'!$K:$K,"native",'Raw Data'!$H:$H,"Money Transfers",'Raw Data'!$I:$I,"Loan/Loan Installment",'Raw Data'!$M:$M,"percent",'Raw Data'!$F:$F,"Number*"))/100 -> 0.005 | H37: =(SUMIFS('Raw Data'!$L:$L,'Raw Data'!$B:$B,$B$2,'Raw Data'!$J:$J,H$2,'Raw Data'!$K:$K,"native",'Raw Data'!$H:$H,"Money Transfers",'Raw Data'!$I:$I,"Loan/Loan Installment",'Raw Data'!$M:$M,"percent",'Raw Data'!$F:$F,"Number*"))/100 -> 0.005 | I37: =(SUMIFS('Raw Data'!$L:$L,'Raw Data'!$B:$B,$B$2,'Raw Data'!$J:$J,I$2,'Raw Data'!$K:$K,"native",'Raw Data'!$H:$H,"Money Transfers",'Raw Data'!$I:$I,"Loan/Loan Installment",'Raw Data'!$M:$M,"percent",'Raw Data'!$F:$F,"Number*"))/100 -> 0.0033 | J37: =(SUMIFS('Raw Data'!$L:$L,'Raw Data'!$B:$B,$B$2,'Raw Data'!$J:$J,J$2,'Raw Data'!$K:$K,"native",'Raw Data'!$H:$H,"Money Transfers",'Raw Data'!$I:$I,"Loan/Loan Installment",'Raw Data'!$M:$M,"percent",'Raw Data'!$F:$F,"Number*"))/100 -> 0.0037 | ... M37: =(SUMIFS('Raw Data'!$L:$L,'Raw Data'!$B:$B,$B$2,'Raw Data'!$J:$J,M$2,'Raw Data'!$K:$K,"native",'Raw Data'!$H:$H,"Money Transfers",'Raw Data'!$I:$I,"Loan/Loan Installment",'Raw Data'!$M:$M,"percent",'Raw Data'!$F:$F,"Number*"))/100 -> 0.0003 | Z37: =(SUMIFS('Raw Data'!$L:$L,'Raw Data'!$B:$B,$B$2,'Raw Data'!$J:$J,Z$2,'Raw Data'!$K:$K,"native",'Raw Data'!$H:$H,"Money Transfers",'Raw Data'!$I:$I,"Loan/Loan Installment",'Raw Data'!$M:$M,"percent",'Raw Data'!$F:$F,"Number*"))/100 -> 0.0001
A38: Transactions | B38: Money Transfers: Salary/Bonus/Dividends | C38: =(SUMIFS('Raw Data'!$L:$L,'Raw Data'!$B:$B,$B$2,'Raw Data'!$J:$J,C$2,'Raw Data'!$K:$K,"native",'Raw Data'!$H:$H,"Money Transfers",'Raw Data'!$I:$I,"Salary/Bonus/Dividends",'Raw Data'!$M:$M,"percent",'Raw Data'!$F:$F,"Number*"))/100 -> 0.0343 | D38: =(SUMIFS('Raw Data'!$L:$L,'Raw Data'!$B:$B,$B$2,'Raw Data'!$J:$J,D$2,'Raw Data'!$K:$K,"native",'Raw Data'!$H:$H,"Money Transfers",'Raw Data'!$I:$I,"Salary/Bonus/Dividends",'Raw Data'!$M:$M,"percent",'Raw Data'!$F:$F,"Number*"))/100 -> 0.0437 | E38: =(SUMIFS('Raw Data'!$L:$L,'Raw Data'!$B:$B,$B$2,'Raw Data'!$J:$J,E$2,'Raw Data'!$K:$K,"native",'Raw Data'!$H:$H,"Money Transfers",'Raw Data'!$I:$I,"Salary/Bonus/Dividends",'Raw Data'!$M:$M,"percent",'Raw Data'!$F:$F,"Number*"))/100 -> 0.0302 | F38: =(SUMIFS('Raw Data'!$L:$L,'Raw Data'!$B:$B,$B$2,'Raw Data'!$J:$J,F$2,'Raw Data'!$K:$K,"native",'Raw Data'!$H:$H,"Money Transfers",'Raw Data'!$I:$I,"Salary/Bonus/Dividends",'Raw Data'!$M:$M,"percent",'Raw Data'!$F:$F,"Number*"))/100 -> 0.0403 | G38: =(SUMIFS('Raw Data'!$L:$L,'Raw Data'!$B:$B,$B$2,'Raw Data'!$J:$J,G$2,'Raw Data'!$K:$K,"native",'Raw Data'!$H:$H,"Money Transfers",'Raw Data'!$I:$I,"Salary/Bonus/Dividends",'Raw Data'!$M:$M,"percent",'Raw Data'!$F:$F,"Number*"))/100 -> 0.0366 | H38: =(SUMIFS('Raw Data'!$L:$L,'Raw Data'!$B:$B,$B$2,'Raw Data'!$J:$J,H$2,'Raw Data'!$K:$K,"native",'Raw Data'!$H:$H,"Money Transfers",'Raw Data'!$I:$I,"Salary/Bonus/Dividends",'Raw Data'!$M:$M,"percent",'Raw Data'!$F:$F,"Number*"))/100 -> 0.0248 | I38: =(SUMIFS('Raw Data'!$L:$L,'Raw Data'!$B:$B,$B$2,'Raw Data'!$J:$J,I$2,'Raw Data'!$K:$K,"native",'Raw Data'!$H:$H,"Money Transfers",'Raw Data'!$I:$I,"Salary/Bonus/Dividends",'Raw Data'!$M:$M,"percent",'Raw Data'!$F:$F,"Number*"))/100 -> 0.0333 | J38: =(SUMIFS('Raw Data'!$L:$L,'Raw Data'!$B:$B,$B$2,'Raw Data'!$J:$J,J$2,'Raw Data'!$K:$K,"native",'Raw Data'!$H:$H,"Money Transfers",'Raw Data'!$I:$I,"Salary/Bonus/Dividends",'Raw Data'!$M:$M,"percent",'Raw Data'!$F:$F,"Number*"))/100 -> 0.0263 | ... M38: =(SUMIFS('Raw Data'!$L:$L,'Raw Data'!$B:$B,$B$2,'Raw Data'!$J:$J,M$2,'Raw Data'!$K:$K,"native",'Raw Data'!$H:$H,"Money Transfers",'Raw Data'!$I:$I,"Salary/Bonus/Dividends",'Raw Data'!$M:$M,"percent",'Raw Data'!$F:$F,"Number*"))/100 -> 0.0296 | Z38: =(SUMIFS('Raw Data'!$L:$L,'Raw Data'!$B:$B,$B$2,'Raw Data'!$J:$J,Z$2,'Raw Data'!$K:$K,"native",'Raw Data'!$H:$H,"Money Transfers",'Raw Data'!$I:$I,"Salary/Bonus/Dividends",'Raw Data'!$M:$M,"percent",'Raw Data'!$F:$F,"Number*"))/100 -> 0.0033
A39: Transactions | B39: Money Transfers: Transfer to Family/Friends | C39: =(SUMIFS('Raw Data'!$L:$L,'Raw Data'!$B:$B,$B$2,'Raw Data'!$J:$J,C$2,'Raw Data'!$K:$K,"native",'Raw Data'!$H:$H,"Money Transfers",'Raw Data'!$I:$I,"Transfer to Family/Friends",'Raw Data'!$M:$M,"percent",'Raw Data'!$F:$F,"Number*"))/100 -> 0.8681 | D39: =(SUMIFS('Raw Data'!$L:$L,'Raw Data'!$B:$B,$B$2,'Raw Data'!$J:$J,D$2,'Raw Data'!$K:$K,"native",'Raw Data'!$H:$H,"Money Transfers",'Raw Data'!$I:$I,"Transfer to Family/Friends",'Raw Data'!$M:$M,"percent",'Raw Data'!$F:$F,"Number*"))/100 -> 0.8659 | E39: =(SUMIFS('Raw Data'!$L:$L,'Raw Data'!$B:$B,$B$2,'Raw Data'!$J:$J,E$2,'Raw Data'!$K:$K,"native",'Raw Data'!$H:$H,"Money Transfers",'Raw Data'!$I:$I,"Transfer to Family/Friends",'Raw Data'!$M:$M,"percent",'Raw Data'!$F:$F,"Number*"))/100 -> 0.8808 | F39: =(SUMIFS('Raw Data'!$L:$L,'Raw Data'!$B:$B,$B$2,'Raw Data'!$J:$J,F$2,'Raw Data'!$K:$K,"native",'Raw Data'!$H:$H,"Money Transfers",'Raw Data'!$I:$I,"Transfer to Family/Friends",'Raw Data'!$M:$M,"percent",'Raw Data'!$F:$F,"Number*"))/100 -> 0.8715 | G39: =(SUMIFS('Raw Data'!$L:$L,'Raw Data'!$B:$B,$B$2,'Raw Data'!$J:$J,G$2,'Raw Data'!$K:$K,"native",'Raw Data'!$H:$H,"Money Transfers",'Raw Data'!$I:$I,"Transfer to Family/Friends",'Raw Data'!$M:$M,"percent",'Raw Data'!$F:$F,"Number*"))/100 -> 0.8829 | H39: =(SUMIFS('Raw Data'!$L:$L,'Raw Data'!$B:$B,$B$2,'Raw Data'!$J:$J,H$2,'Raw Data'!$K:$K,"native",'Raw Data'!$H:$H,"Money Transfers",'Raw Data'!$I:$I,"Transfer to Family/Friends",'Raw Data'!$M:$M,"percent",'Raw Data'!$F:$F,"Number*"))/100 -> 0.8921 | I39: =(SUMIFS('Raw Data'!$L:$L,'Raw Data'!$B:$B,$B$2,'Raw Data'!$J:$J,I$2,'Raw Data'!$K:$K,"native",'Raw Data'!$H:$H,"Money Transfers",'Raw Data'!$I:$I,"Transfer to Family/Friends",'Raw Data'!$M:$M,"percent",'Raw Data'!$F:$F,"Number*"))/100 -> 0.8913 | J39: =(SUMIFS('Raw Data'!$L:$L,'Raw Data'!$B:$B,$B$2,'Raw Data'!$J:$J,J$2,'Raw Data'!$K:$K,"native",'Raw Data'!$H:$H,"Money Transfers",'Raw Data'!$I:$I,"Transfer to Family/Friends",'Raw Data'!$M:$M,"percent",'Raw Data'!$F:$F,"Number*"))/100 -> 0.9066 | ... M39: =(SUMIFS('Raw Data'!$L:$L,'Raw Data'!$B:$B,$B$2,'Raw Data'!$J:$J,M$2,'Raw Data'!$K:$K,"native",'Raw Data'!$H:$H,"Money Transfers",'Raw Data'!$I:$I,"Transfer to Family/Friends",'Raw Data'!$M:$M,"percent",'Raw Data'!$F:$F,"Number*"))/100 -> 0.8975 | Z39: =(SUMIFS('Raw Data'!$L:$L,'Raw Data'!$B:$B,$B$2,'Raw Data'!$J:$J,Z$2,'Raw Data'!$K:$K,"native",'Raw Data'!$H:$H,"Money Transfers",'Raw Data'!$I:$I,"Transfer to Family/Friends",'Raw Data'!$M:$M,"percent",'Raw Data'!$F:$F,"Number*"))/100 -> 0.8121
A40: Transactions | B40: Money Transfers: Transfer to Own Account | C40: =(SUMIFS('Raw Data'!$L:$L,'Raw Data'!$B:$B,$B$2,'Raw Data'!$J:$J,C$2,'Raw Data'!$K:$K,"native",'Raw Data'!$H:$H,"Money Transfers",'Raw Data'!$I:$I,"Transfer to Own Account",'Raw Data'!$M:$M,"percent",'Raw Data'!$F:$F,"Number*"))/100 -> 0.0646 | D40: =(SUMIFS('Raw Data'!$L:$L,'Raw Data'!$B:$B,$B$2,'Raw Data'!$J:$J,D$2,'Raw Data'!$K:$K,"native",'Raw Data'!$H:$H,"Money Transfers",'Raw Data'!$I:$I,"Transfer to Own Account",'Raw Data'!$M:$M,"percent",'Raw Data'!$F:$F,"Number*"))/100 -> 0.0632 | E40: =(SUMIFS('Raw Data'!$L:$L,'Raw Data'!$B:$B,$B$2,'Raw Data'!$J:$J,E$2,'Raw Data'!$K:$K,"native",'Raw Data'!$H:$H,"Money Transfers",'Raw Data'!$I:$I,"Transfer to Own Account",'Raw Data'!$M:$M,"percent",'Raw Data'!$F:$F,"Number*"))/100 -> 0.0618 | F40: =(SUMIFS('Raw Data'!$L:$L,'Raw Data'!$B:$B,$B$2,'Raw Data'!$J:$J,F$2,'Raw Data'!$K:$K,"native",'Raw Data'!$H:$H,"Money Transfers",'Raw Data'!$I:$I,"Transfer to Own Account",'Raw Data'!$M:$M,"percent",'Raw Data'!$F:$F,"Number*"))/100 -> 0.0601 | G40: =(SUMIFS('Raw Data'!$L:$L,'Raw Data'!$B:$B,$B$2,'Raw Data'!$J:$J,G$2,'Raw Data'!$K:$K,"native",'Raw Data'!$H:$H,"Money Transfers",'Raw Data'!$I:$I,"Transfer to Own Account",'Raw Data'!$M:$M,"percent",'Raw Data'!$F:$F,"Number*"))/100 -> 0.0598 | H40: =(SUMIFS('Raw Data'!$L:$L,'Raw Data'!$B:$B,$B$2,'Raw Data'!$J:$J,H$2,'Raw Data'!$K:$K,"native",'Raw Data'!$H:$H,"Money Transfers",'Raw Data'!$I:$I,"Transfer to Own Account",'Raw Data'!$M:$M,"percent",'Raw Data'!$F:$F,"Number*"))/100 -> 0.0605 | I40: =(SUMIFS('Raw Data'!$L:$L,'Raw Data'!$B:$B,$B$2,'Raw Data'!$J:$J,I$2,'Raw Data'!$K:$K,"native",'Raw Data'!$H:$H,"Money Transfers",'Raw Data'!$I:$I,"Transfer to Own Account",'Raw Data'!$M:$M,"percent",'Raw Data'!$F:$F,"Number*"))/100 -> 0.05 | J40: =(SUMIFS('Raw Data'!$L:$L,'Raw Data'!$B:$B,$B$2,'Raw Data'!$J:$J,J$2,'Raw Data'!$K:$K,"native",'Raw Data'!$H:$H,"Money Transfers",'Raw Data'!$I:$I,"Transfer to Own Account",'Raw Data'!$M:$M,"percent",'Raw Data'!$F:$F,"Number*"))/100 -> 0.0491 | ... M40: =(SUMIFS('Raw Data'!$L:$L,'Raw Data'!$B:$B,$B$2,'Raw Data'!$J:$J,M$2,'Raw Data'!$K:$K,"native",'Raw Data'!$H:$H,"Money Transfers",'Raw Data'!$I:$I,"Transfer to Own Account",'Raw Data'!$M:$M,"percent",'Raw Data'!$F:$F,"Number*"))/100 -> 0.0664 | Z40: =(SUMIFS('Raw Data'!$L:$L,'Raw Data'!$B:$B,$B$2,'Raw Data'!$J:$J,Z$2,'Raw Data'!$K:$K,"native",'Raw Data'!$H:$H,"Money Transfers",'Raw Data'!$I:$I,"Transfer to Own Account",'Raw Data'!$M:$M,"percent",'Raw Data'!$F:$F,"Number*"))/100 -> 0.1595
A41: Transactions | B41: Purchases: Purchases | C41: =(SUMIFS('Raw Data'!$L:$L,'Raw Data'!$B:$B,$B$2,'Raw Data'!$J:$J,C$2,'Raw Data'!$K:$K,"native",'Raw Data'!$H:$H,"Purchases",'Raw Data'!$I:$I,"Purchases",'Raw Data'!$M:$M,"percent",'Raw Data'!$F:$F,"Number*"))/100 -> 0.8444 | D41: =(SUMIFS('Raw Data'!$L:$L,'Raw Data'!$B:$B,$B$2,'Raw Data'!$J:$J,D$2,'Raw Data'!$K:$K,"native",'Raw Data'!$H:$H,"Purchases",'Raw Data'!$I:$I,"Purchases",'Raw Data'!$M:$M,"percent",'Raw Data'!$F:$F,"Number*"))/100 -> 0.8205 | E41: =(SUMIFS('Raw Data'!$L:$L,'Raw Data'!$B:$B,$B$2,'Raw Data'!$J:$J,E$2,'Raw Data'!$K:$K,"native",'Raw Data'!$H:$H,"Purchases",'Raw Data'!$I:$I,"Purchases",'Raw Data'!$M:$M,"percent",'Raw Data'!$F:$F,"Number*"))/100 -> 0.8068 | F41: =(SUMIFS('Raw Data'!$L:$L,'Raw Data'!$B:$B,$B$2,'Raw Data'!$J:$J,F$2,'Raw Data'!$K:$K,"native",'Raw Data'!$H:$H,"Purchases",'Raw Data'!$I:$I,"Purchases",'Raw Data'!$M:$M,"percent",'Raw Data'!$F:$F,"Number*"))/100 -> 0.7815 | G41: =(SUMIFS('Raw Data'!$L:$L,'Raw Data'!$B:$B,$B$2,'Raw Data'!$J:$J,G$2,'Raw Data'!$K:$K,"native",'Raw Data'!$H:$H,"Purchases",'Raw Data'!$I:$I,"Purchases",'Raw Data'!$M:$M,"percent",'Raw Data'!$F:$F,"Number*"))/100 -> 0.6905 | H41: =(SUMIFS('Raw Data'!$L:$L,'Raw Data'!$B:$B,$B$2,'Raw Data'!$J:$J,H$2,'Raw Data'!$K:$K,"native",'Raw Data'!$H:$H,"Purchases",'Raw Data'!$I:$I,"Purchases",'Raw Data'!$M:$M,"percent",'Raw Data'!$F:$F,"Number*"))/100 -> 0.6624 | I41: =(SUMIFS('Raw Data'!$L:$L,'Raw Data'!$B:$B,$B$2,'Raw Data'!$J:$J,I$2,'Raw Data'!$K:$K,"native",'Raw Data'!$H:$H,"Purchases",'Raw Data'!$I:$I,"Purchases",'Raw Data'!$M:$M,"percent",'Raw Data'!$F:$F,"Number*"))/100 -> 0.6746 | J41: =(SUMIFS('Raw Data'!$L:$L,'Raw Data'!$B:$B,$B$2,'Raw Data'!$J:$J,J$2,'Raw Data'!$K:$K,"native",'Raw Data'!$H:$H,"Purchases",'Raw Data'!$I:$I,"Purchases",'Raw Data'!$M:$M,"percent",'Raw Data'!$F:$F,"Number*"))/100 -> 0.621 | ... M41: =(SUMIFS('Raw Data'!$L:$L,'Raw Data'!$B:$B,$B$2,'Raw Data'!$J:$J,M$2,'Raw Data'!$K:$K,"native",'Raw Data'!$H:$H,"Purchases",'Raw Data'!$I:$I,"Purchases",'Raw Data'!$M:$M,"percent",'Raw Data'!$F:$F,"Number*"))/100 -> 0.7703 | Z41: =(SUMIFS('Raw Data'!$L:$L,'Raw Data'!$B:$B,$B$2,'Raw Data'!$J:$J,Z$2,'Raw Data'!$K:$K,"native",'Raw Data'!$H:$H,"Purchases",'Raw Data'!$I:$I,"Purchases",'Raw Data'!$M:$M,"percent",'Raw Data'!$F:$F,"Number*"))/100 -> 0.8551
A42: Transactions | B42: Purchases: QR Purchases | C42: =(SUMIFS('Raw Data'!$L:$L,'Raw Data'!$B:$B,$B$2,'Raw Data'!$J:$J,C$2,'Raw Data'!$K:$K,"native",'Raw Data'!$H:$H,"Purchases",'Raw Data'!$I:$I,"QR Purchases",'Raw Data'!$M:$M,"percent",'Raw Data'!$F:$F,"Number*"))/100 -> 0.1556 | D42: =(SUMIFS('Raw Data'!$L:$L,'Raw Data'!$B:$B,$B$2,'Raw Data'!$J:$J,D$2,'Raw Data'!$K:$K,"native",'Raw Data'!$H:$H,"Purchases",'Raw Data'!$I:$I,"QR Purchases",'Raw Data'!$M:$M,"percent",'Raw Data'!$F:$F,"Number*"))/100 -> 0.1795 | E42: =(SUMIFS('Raw Data'!$L:$L,'Raw Data'!$B:$B,$B$2,'Raw Data'!$J:$J,E$2,'Raw Data'!$K:$K,"native",'Raw Data'!$H:$H,"Purchases",'Raw Data'!$I:$I,"QR Purchases",'Raw Data'!$M:$M,"percent",'Raw Data'!$F:$F,"Number*"))/100 -> 0.1932 | F42: =(SUMIFS('Raw Data'!$L:$L,'Raw Data'!$B:$B,$B$2,'Raw Data'!$J:$J,F$2,'Raw Data'!$K:$K,"native",'Raw Data'!$H:$H,"Purchases",'Raw Data'!$I:$I,"QR Purchases",'Raw Data'!$M:$M,"percent",'Raw Data'!$F:$F,"Number*"))/100 -> 0.2185 | G42: =(SUMIFS('Raw Data'!$L:$L,'Raw Data'!$B:$B,$B$2,'Raw Data'!$J:$J,G$2,'Raw Data'!$K:$K,"native",'Raw Data'!$H:$H,"Purchases",'Raw Data'!$I:$I,"QR Purchases",'Raw Data'!$M:$M,"percent",'Raw Data'!$F:$F,"Number*"))/100 -> 0.3095 | H42: =(SUMIFS('Raw Data'!$L:$L,'Raw Data'!$B:$B,$B$2,'Raw Data'!$J:$J,H$2,'Raw Data'!$K:$K,"native",'Raw Data'!$H:$H,"Purchases",'Raw Data'!$I:$I,"QR Purchases",'Raw Data'!$M:$M,"percent",'Raw Data'!$F:$F,"Number*"))/100 -> 0.3376 | I42: =(SUMIFS('Raw Data'!$L:$L,'Raw Data'!$B:$B,$B$2,'Raw Data'!$J:$J,I$2,'Raw Data'!$K:$K,"native",'Raw Data'!$H:$H,"Purchases",'Raw Data'!$I:$I,"QR Purchases",'Raw Data'!$M:$M,"percent",'Raw Data'!$F:$F,"Number*"))/100 -> 0.3254 | J42: =(SUMIFS('Raw Data'!$L:$L,'Raw Data'!$B:$B,$B$2,'Raw Data'!$J:$J,J$2,'Raw Data'!$K:$K,"native",'Raw Data'!$H:$H,"Purchases",'Raw Data'!$I:$I,"QR Purchases",'Raw Data'!$M:$M,"percent",'Raw Data'!$F:$F,"Number*"))/100 -> 0.379 | ... M42: =(SUMIFS('Raw Data'!$L:$L,'Raw Data'!$B:$B,$B$2,'Raw Data'!$J:$J,M$2,'Raw Data'!$K:$K,"native",'Raw Data'!$H:$H,"Purchases",'Raw Data'!$I:$I,"QR Purchases",'Raw Data'!$M:$M,"percent",'Raw Data'!$F:$F,"Number*"))/100 -> 0.2297 | Z42: =(SUMIFS('Raw Data'!$L:$L,'Raw Data'!$B:$B,$B$2,'Raw Data'!$J:$J,Z$2,'Raw Data'!$K:$K,"native",'Raw Data'!$H:$H,"Purchases",'Raw Data'!$I:$I,"QR Purchases",'Raw Data'!$M:$M,"percent",'Raw Data'!$F:$F,"Number*"))/100 -> 0.1449
A43: Transactions | B43: Money Transfers: Loan/Loan Disbursement | M43: =(SUMIFS('Raw Data'!$L:$L,'Raw Data'!$B:$B,$B$2,'Raw Data'!$J:$J,M$2,'Raw Data'!$K:$K,"native",'Raw Data'!$H:$H,"Money Transfers",'Raw Data'!$I:$I,"Loan/Loan Disbursement",'Raw Data'!$M:$M,"percent",'Raw Data'!$F:$F,"Number*"))/100 -> 0.001 | Z43: =(SUMIFS('Raw Data'!$L:$L,'Raw Data'!$B:$B,$B$2,'Raw Data'!$J:$J,Z$2,'Raw Data'!$K:$K,"native",'Raw Data'!$H:$H,"Money Transfers",'Raw Data'!$I:$I,"Loan/Loan Disbursement",'Raw Data'!$M:$M,"percent",'Raw Data'!$F:$F,"Number*"))/100 -> 0.0007
A44: Transactions | B44: Money Transfers: Loan Disbursement
A45: Transactions | B45: Money Transfers: Loan Installment
A46: Transactions | B46: Purchases: Non-QR Purchases
A47: Transactions | B47: Money Transfers: Goods/Services | Z47: =(SUMIFS('Raw Data'!$L:$L,'Raw Data'!$B:$B,$B$2,'Raw Data'!$J:$J,Z$2,'Raw Data'!$K:$K,"native",'Raw Data'!$H:$H,"Money Transfers",'Raw Data'!$I:$I,"Goods/Services",'Raw Data'!$M:$M,"percent",'Raw Data'!$F:$F,"Number*"))/100 -> 0.0121
A48: TRANSACTIONS BY TRANSACTION TYPE (Value, JOD)
A49: Transactions | B49: Cash In | C49: =SUMIFS('Raw Data'!$L:$L,'Raw Data'!$B:$B,$B$2,'Raw Data'!$J:$J,C$2,'Raw Data'!$K:$K,"native",'Raw Data'!$H:$H,"Cash In",'Raw Data'!$I:$I,"",'Raw Data'!$M:$M,"JOD") -> 19600000 | D49: =SUMIFS('Raw Data'!$L:$L,'Raw Data'!$B:$B,$B$2,'Raw Data'!$J:$J,D$2,'Raw Data'!$K:$K,"native",'Raw Data'!$H:$H,"Cash In",'Raw Data'!$I:$I,"",'Raw Data'!$M:$M,"JOD") -> 20300000 | E49: =SUMIFS('Raw Data'!$L:$L,'Raw Data'!$B:$B,$B$2,'Raw Data'!$J:$J,E$2,'Raw Data'!$K:$K,"native",'Raw Data'!$H:$H,"Cash In",'Raw Data'!$I:$I,"",'Raw Data'!$M:$M,"JOD") -> 17700000 | F49: =SUMIFS('Raw Data'!$L:$L,'Raw Data'!$B:$B,$B$2,'Raw Data'!$J:$J,F$2,'Raw Data'!$K:$K,"native",'Raw Data'!$H:$H,"Cash In",'Raw Data'!$I:$I,"",'Raw Data'!$M:$M,"JOD") -> 18800000 | G49: =SUMIFS('Raw Data'!$L:$L,'Raw Data'!$B:$B,$B$2,'Raw Data'!$J:$J,G$2,'Raw Data'!$K:$K,"native",'Raw Data'!$H:$H,"Cash In",'Raw Data'!$I:$I,"",'Raw Data'!$M:$M,"JOD") -> 18080000 | H49: =SUMIFS('Raw Data'!$L:$L,'Raw Data'!$B:$B,$B$2,'Raw Data'!$J:$J,H$2,'Raw Data'!$K:$K,"native",'Raw Data'!$H:$H,"Cash In",'Raw Data'!$I:$I,"",'Raw Data'!$M:$M,"JOD") -> 17300000 | I49: =SUMIFS('Raw Data'!$L:$L,'Raw Data'!$B:$B,$B$2,'Raw Data'!$J:$J,I$2,'Raw Data'!$K:$K,"native",'Raw Data'!$H:$H,"Cash In",'Raw Data'!$I:$I,"",'Raw Data'!$M:$M,"JOD") -> 19000000 | J49: =SUMIFS('Raw Data'!$L:$L,'Raw Data'!$B:$B,$B$2,'Raw Data'!$J:$J,J$2,'Raw Data'!$K:$K,"native",'Raw Data'!$H:$H,"Cash In",'Raw Data'!$I:$I,"",'Raw Data'!$M:$M,"JOD") -> 17800000 | ... Z49: =SUMIFS('Raw Data'!$L:$L,'Raw Data'!$B:$B,$B$2,'Raw Data'!$J:$J,Z$2,'Raw Data'!$K:$K,"native",'Raw Data'!$H:$H,"Cash In",'Raw Data'!$I:$I,"",'Raw Data'!$M:$M,"JOD") -> 3900000
A50: Transactions | B50: Cash Out | C50: =SUMIFS('Raw Data'!$L:$L,'Raw Data'!$B:$B,$B$2,'Raw Data'!$J:$J,C$2,'Raw Data'!$K:$K,"native",'Raw Data'!$H:$H,"Cash Out",'Raw Data'!$I:$I,"",'Raw Data'!$M:$M,"JOD") -> 29300000 | D50: =SUMIFS('Raw Data'!$L:$L,'Raw Data'!$B:$B,$B$2,'Raw Data'!$J:$J,D$2,'Raw Data'!$K:$K,"native",'Raw Data'!$H:$H,"Cash Out",'Raw Data'!$I:$I,"",'Raw Data'!$M:$M,"JOD") -> 32000000 | E50: =SUMIFS('Raw Data'!$L:$L,'Raw Data'!$B:$B,$B$2,'Raw Data'!$J:$J,E$2,'Raw Data'!$K:$K,"native",'Raw Data'!$H:$H,"Cash Out",'Raw Data'!$I:$I,"",'Raw Data'!$M:$M,"JOD") -> 27100000 | F50: =SUMIFS('Raw Data'!$L:$L,'Raw Data'!$B:$B,$B$2,'Raw Data'!$J:$J,F$2,'Raw Data'!$K:$K,"native",'Raw Data'!$H:$H,"Cash Out",'Raw Data'!$I:$I,"",'Raw Data'!$M:$M,"JOD") -> 29300000 | G50: =SUMIFS('Raw Data'!$L:$L,'Raw Data'!$B:$B,$B$2,'Raw Data'!$J:$J,G$2,'Raw Data'!$K:$K,"native",'Raw Data'!$H:$H,"Cash Out",'Raw Data'!$I:$I,"",'Raw Data'!$M:$M,"JOD") -> 27200000 | H50: =SUMIFS('Raw Data'!$L:$L,'Raw Data'!$B:$B,$B$2,'Raw Data'!$J:$J,H$2,'Raw Data'!$K:$K,"native",'Raw Data'!$H:$H,"Cash Out",'Raw Data'!$I:$I,"",'Raw Data'!$M:$M,"JOD") -> 23700000 | I50: =SUMIFS('Raw Data'!$L:$L,'Raw Data'!$B:$B,$B$2,'Raw Data'!$J:$J,I$2,'Raw Data'!$K:$K,"native",'Raw Data'!$H:$H,"Cash Out",'Raw Data'!$I:$I,"",'Raw Data'!$M:$M,"JOD") -> 28600000 | J50: =SUMIFS('Raw Data'!$L:$L,'Raw Data'!$B:$B,$B$2,'Raw Data'!$J:$J,J$2,'Raw Data'!$K:$K,"native",'Raw Data'!$H:$H,"Cash Out",'Raw Data'!$I:$I,"",'Raw Data'!$M:$M,"JOD") -> 23000000 | ... Z50: =SUMIFS('Raw Data'!$L:$L,'Raw Data'!$B:$B,$B$2,'Raw Data'!$J:$J,Z$2,'Raw Data'!$K:$K,"native",'Raw Data'!$H:$H,"Cash Out",'Raw Data'!$I:$I,"",'Raw Data'!$M:$M,"JOD") -> 9500000
A51: Transactions | B51: Money Transfers | C51: =SUMIFS('Raw Data'!$L:$L,'Raw Data'!$B:$B,$B$2,'Raw Data'!$J:$J,C$2,'Raw Data'!$K:$K,"native",'Raw Data'!$H:$H,"Money Transfers",'Raw Data'!$I:$I,"",'Raw Data'!$M:$M,"JOD") -> 382800000 | D51: =SUMIFS('Raw Data'!$L:$L,'Raw Data'!$B:$B,$B$2,'Raw Data'!$J:$J,D$2,'Raw Data'!$K:$K,"native",'Raw Data'!$H:$H,"Money Transfers",'Raw Data'!$I:$I,"",'Raw Data'!$M:$M,"JOD") -> 399700000 | E51: =SUMIFS('Raw Data'!$L:$L,'Raw Data'!$B:$B,$B$2,'Raw Data'!$J:$J,E$2,'Raw Data'!$K:$K,"native",'Raw Data'!$H:$H,"Money Transfers",'Raw Data'!$I:$I,"",'Raw Data'!$M:$M,"JOD") -> 385200000 | F51: =SUMIFS('Raw Data'!$L:$L,'Raw Data'!$B:$B,$B$2,'Raw Data'!$J:$J,F$2,'Raw Data'!$K:$K,"native",'Raw Data'!$H:$H,"Money Transfers",'Raw Data'!$I:$I,"",'Raw Data'!$M:$M,"JOD") -> 429900000 | G51: =SUMIFS('Raw Data'!$L:$L,'Raw Data'!$B:$B,$B$2,'Raw Data'!$J:$J,G$2,'Raw Data'!$K:$K,"native",'Raw Data'!$H:$H,"Money Transfers",'Raw Data'!$I:$I,"",'Raw Data'!$M:$M,"JOD") -> 418190000 | H51: =SUMIFS('Raw Data'!$L:$L,'Raw Data'!$B:$B,$B$2,'Raw Data'!$J:$J,H$2,'Raw Data'!$K:$K,"native",'Raw Data'!$H:$H,"Money Transfers",'Raw Data'!$I:$I,"",'Raw Data'!$M:$M,"JOD") -> 385200000 | I51: =SUMIFS('Raw Data'!$L:$L,'Raw Data'!$B:$B,$B$2,'Raw Data'!$J:$J,I$2,'Raw Data'!$K:$K,"native",'Raw Data'!$H:$H,"Money Transfers",'Raw Data'!$I:$I,"",'Raw Data'!$M:$M,"JOD") -> 483500000 | J51: =SUMIFS('Raw Data'!$L:$L,'Raw Data'!$B:$B,$B$2,'Raw Data'!$J:$J,J$2,'Raw Data'!$K:$K,"native",'Raw Data'!$H:$H,"Money Transfers",'Raw Data'!$I:$I,"",'Raw Data'!$M:$M,"JOD") -> 422000000 | ... Z51: =SUMIFS('Raw Data'!$L:$L,'Raw Data'!$B:$B,$B$2,'Raw Data'!$J:$J,Z$2,'Raw Data'!$K:$K,"native",'Raw Data'!$H:$H,"Money Transfers",'Raw Data'!$I:$I,"",'Raw Data'!$M:$M,"JOD") -> 582300000
A52: Transactions | B52: Purchases | C52: =SUMIFS('Raw Data'!$L:$L,'Raw Data'!$B:$B,$B$2,'Raw Data'!$J:$J,C$2,'Raw Data'!$K:$K,"native",'Raw Data'!$H:$H,"Purchases",'Raw Data'!$I:$I,"",'Raw Data'!$M:$M,"JOD") -> 14800000 | D52: =SUMIFS('Raw Data'!$L:$L,'Raw Data'!$B:$B,$B$2,'Raw Data'!$J:$J,D$2,'Raw Data'!$K:$K,"native",'Raw Data'!$H:$H,"Purchases",'Raw Data'!$I:$I,"",'Raw Data'!$M:$M,"JOD") -> 15300000 | E52: =SUMIFS('Raw Data'!$L:$L,'Raw Data'!$B:$B,$B$2,'Raw Data'!$J:$J,E$2,'Raw Data'!$K:$K,"native",'Raw Data'!$H:$H,"Purchases",'Raw Data'!$I:$I,"",'Raw Data'!$M:$M,"JOD") -> 1420000 | F52: =SUMIFS('Raw Data'!$L:$L,'Raw Data'!$B:$B,$B$2,'Raw Data'!$J:$J,F$2,'Raw Data'!$K:$K,"native",'Raw Data'!$H:$H,"Purchases",'Raw Data'!$I:$I,"",'Raw Data'!$M:$M,"JOD") -> 15500000 | G52: =SUMIFS('Raw Data'!$L:$L,'Raw Data'!$B:$B,$B$2,'Raw Data'!$J:$J,G$2,'Raw Data'!$K:$K,"native",'Raw Data'!$H:$H,"Purchases",'Raw Data'!$I:$I,"",'Raw Data'!$M:$M,"JOD") -> 5180000 | H52: =SUMIFS('Raw Data'!$L:$L,'Raw Data'!$B:$B,$B$2,'Raw Data'!$J:$J,H$2,'Raw Data'!$K:$K,"native",'Raw Data'!$H:$H,"Purchases",'Raw Data'!$I:$I,"",'Raw Data'!$M:$M,"JOD") -> 4760000 | I52: =SUMIFS('Raw Data'!$L:$L,'Raw Data'!$B:$B,$B$2,'Raw Data'!$J:$J,I$2,'Raw Data'!$K:$K,"native",'Raw Data'!$H:$H,"Purchases",'Raw Data'!$I:$I,"",'Raw Data'!$M:$M,"JOD") -> 6400000 | J52: =SUMIFS('Raw Data'!$L:$L,'Raw Data'!$B:$B,$B$2,'Raw Data'!$J:$J,J$2,'Raw Data'!$K:$K,"native",'Raw Data'!$H:$H,"Purchases",'Raw Data'!$I:$I,"",'Raw Data'!$M:$M,"JOD") -> 6200000 | ... Z52: =SUMIFS('Raw Data'!$L:$L,'Raw Data'!$B:$B,$B$2,'Raw Data'!$J:$J,Z$2,'Raw Data'!$K:$K,"native",'Raw Data'!$H:$H,"Purchases",'Raw Data'!$I:$I,"",'Raw Data'!$M:$M,"JOD") -> 174500000
A53: TRANSACTIONS BY TYPE — DETAIL (%)
A54: Transactions | B54: Cash In: ATM/Kiosk | C54: =(SUMIFS('Raw Data'!$L:$L,'Raw Data'!$B:$B,$B$2,'Raw Data'!$J:$J,C$2,'Raw Data'!$K:$K,"native",'Raw Data'!$H:$H,"Cash In",'Raw Data'!$I:$I,"ATM/Kiosk",'Raw Data'!$M:$M,"percent",'Raw Data'!$F:$F,"Value*"))/100 -> 0.0179 | D54: =(SUMIFS('Raw Data'!$L:$L,'Raw Data'!$B:$B,$B$2,'Raw Data'!$J:$J,D$2,'Raw Data'!$K:$K,"native",'Raw Data'!$H:$H,"Cash In",'Raw Data'!$I:$I,"ATM/Kiosk",'Raw Data'!$M:$M,"percent",'Raw Data'!$F:$F,"Value*"))/100 -> 0.0171 | E54: =(SUMIFS('Raw Data'!$L:$L,'Raw Data'!$B:$B,$B$2,'Raw Data'!$J:$J,E$2,'Raw Data'!$K:$K,"native",'Raw Data'!$H:$H,"Cash In",'Raw Data'!$I:$I,"ATM/Kiosk",'Raw Data'!$M:$M,"percent",'Raw Data'!$F:$F,"Value*"))/100 -> 0.017 | F54: =(SUMIFS('Raw Data'!$L:$L,'Raw Data'!$B:$B,$B$2,'Raw Data'!$J:$J,F$2,'Raw Data'!$K:$K,"native",'Raw Data'!$H:$H,"Cash In",'Raw Data'!$I:$I,"ATM/Kiosk",'Raw Data'!$M:$M,"percent",'Raw Data'!$F:$F,"Value*"))/100 -> 0.0153 | G54: =(SUMIFS('Raw Data'!$L:$L,'Raw Data'!$B:$B,$B$2,'Raw Data'!$J:$J,G$2,'Raw Data'!$K:$K,"native",'Raw Data'!$H:$H,"Cash In",'Raw Data'!$I:$I,"ATM/Kiosk",'Raw Data'!$M:$M,"percent",'Raw Data'!$F:$F,"Value*"))/100 -> 0.0139 | H54: =(SUMIFS('Raw Data'!$L:$L,'Raw Data'!$B:$B,$B$2,'Raw Data'!$J:$J,H$2,'Raw Data'!$K:$K,"native",'Raw Data'!$H:$H,"Cash In",'Raw Data'!$I:$I,"ATM/Kiosk",'Raw Data'!$M:$M,"percent",'Raw Data'!$F:$F,"Value*"))/100 -> 0.0128 | I54: =(SUMIFS('Raw Data'!$L:$L,'Raw Data'!$B:$B,$B$2,'Raw Data'!$J:$J,I$2,'Raw Data'!$K:$K,"native",'Raw Data'!$H:$H,"Cash In",'Raw Data'!$I:$I,"ATM/Kiosk",'Raw Data'!$M:$M,"percent",'Raw Data'!$F:$F,"Value*"))/100 -> 0.0171 | J54: =(SUMIFS('Raw Data'!$L:$L,'Raw Data'!$B:$B,$B$2,'Raw Data'!$J:$J,J$2,'Raw Data'!$K:$K,"native",'Raw Data'!$H:$H,"Cash In",'Raw Data'!$I:$I,"ATM/Kiosk",'Raw Data'!$M:$M,"percent",'Raw Data'!$F:$F,"Value*"))/100 -> 0.0156 | ... M54: =(SUMIFS('Raw Data'!$L:$L,'Raw Data'!$B:$B,$B$2,'Raw Data'!$J:$J,M$2,'Raw Data'!$K:$K,"native",'Raw Data'!$H:$H,"Cash In",'Raw Data'!$I:$I,"ATM/Kiosk",'Raw Data'!$M:$M,"percent",'Raw Data'!$F:$F,"Value*"))/100 -> 0.0138 | Z54: =(SUMIFS('Raw Data'!$L:$L,'Raw Data'!$B:$B,$B$2,'Raw Data'!$J:$J,Z$2,'Raw Data'!$K:$K,"native",'Raw Data'!$H:$H,"Cash In",'Raw Data'!$I:$I,"ATM/Kiosk",'Raw Data'!$M:$M,"percent",'Raw Data'!$F:$F,"Value*"))/100 -> 0.0784
A55: Transactions | B55: Cash In: Agent/Teller | C55: =(SUMIFS('Raw Data'!$L:$L,'Raw Data'!$B:$B,$B$2,'Raw Data'!$J:$J,C$2,'Raw Data'!$K:$K,"native",'Raw Data'!$H:$H,"Cash In",'Raw Data'!$I:$I,"Agent/Teller",'Raw Data'!$M:$M,"percent",'Raw Data'!$F:$F,"Value*"))/100 -> 0.9821 | D55: =(SUMIFS('Raw Data'!$L:$L,'Raw Data'!$B:$B,$B$2,'Raw Data'!$J:$J,D$2,'Raw Data'!$K:$K,"native",'Raw Data'!$H:$H,"Cash In",'Raw Data'!$I:$I,"Agent/Teller",'Raw Data'!$M:$M,"percent",'Raw Data'!$F:$F,"Value*"))/100 -> 0.9829 | E55: =(SUMIFS('Raw Data'!$L:$L,'Raw Data'!$B:$B,$B$2,'Raw Data'!$J:$J,E$2,'Raw Data'!$K:$K,"native",'Raw Data'!$H:$H,"Cash In",'Raw Data'!$I:$I,"Agent/Teller",'Raw Data'!$M:$M,"percent",'Raw Data'!$F:$F,"Value*"))/100 -> 0.983 | F55: =(SUMIFS('Raw Data'!$L:$L,'Raw Data'!$B:$B,$B$2,'Raw Data'!$J:$J,F$2,'Raw Data'!$K:$K,"native",'Raw Data'!$H:$H,"Cash In",'Raw Data'!$I:$I,"Agent/Teller",'Raw Data'!$M:$M,"percent",'Raw Data'!$F:$F,"Value*"))/100 -> 0.9847 | G55: =(SUMIFS('Raw Data'!$L:$L,'Raw Data'!$B:$B,$B$2,'Raw Data'!$J:$J,G$2,'Raw Data'!$K:$K,"native",'Raw Data'!$H:$H,"Cash In",'Raw Data'!$I:$I,"Agent/Teller",'Raw Data'!$M:$M,"percent",'Raw Data'!$F:$F,"Value*"))/100 -> 0.9861 | H55: =(SUMIFS('Raw Data'!$L:$L,'Raw Data'!$B:$B,$B$2,'Raw Data'!$J:$J,H$2,'Raw Data'!$K:$K,"native",'Raw Data'!$H:$H,"Cash In",'Raw Data'!$I:$I,"Agent/Teller",'Raw Data'!$M:$M,"percent",'Raw Data'!$F:$F,"Value*"))/100 -> 0.9872 | I55: =(SUMIFS('Raw Data'!$L:$L,'Raw Data'!$B:$B,$B$2,'Raw Data'!$J:$J,I$2,'Raw Data'!$K:$K,"native",'Raw Data'!$H:$H,"Cash In",'Raw Data'!$I:$I,"Agent/Teller",'Raw Data'!$M:$M,"percent",'Raw Data'!$F:$F,"Value*"))/100 -> 0.9829 | J55: =(SUMIFS('Raw Data'!$L:$L,'Raw Data'!$B:$B,$B$2,'Raw Data'!$J:$J,J$2,'Raw Data'!$K:$K,"native",'Raw Data'!$H:$H,"Cash In",'Raw Data'!$I:$I,"Agent/Teller",'Raw Data'!$M:$M,"percent",'Raw Data'!$F:$F,"Value*"))/100 -> 0.9844 | ... M55: =(SUMIFS('Raw Data'!$L:$L,'Raw Data'!$B:$B,$B$2,'Raw Data'!$J:$J,M$2,'Raw Data'!$K:$K,"native",'Raw Data'!$H:$H,"Cash In",'Raw Data'!$I:$I,"Agent/Teller",'Raw Data'!$M:$M,"percent",'Raw Data'!$F:$F,"Value*"))/100 -> 0.9862 | Z55: =(SUMIFS('Raw Data'!$L:$L,'Raw Data'!$B:$B,$B$2,'Raw Data'!$J:$J,Z$2,'Raw Data'!$K:$K,"native",'Raw Data'!$H:$H,"Cash In",'Raw Data'!$I:$I,"Agent/Teller",'Raw Data'!$M:$M,"percent",'Raw Data'!$F:$F,"Value*"))/100 -> 0.9216
A56: Transactions | B56: Cash Out: ATM/Kiosk | C56: =(SUMIFS('Raw Data'!$L:$L,'Raw Data'!$B:$B,$B$2,'Raw Data'!$J:$J,C$2,'Raw Data'!$K:$K,"native",'Raw Data'!$H:$H,"Cash Out",'Raw Data'!$I:$I,"ATM/Kiosk",'Raw Data'!$M:$M,"percent",'Raw Data'!$F:$F,"Value*"))/100 -> 0.0777 | D56: =(SUMIFS('Raw Data'!$L:$L,'Raw Data'!$B:$B,$B$2,'Raw Data'!$J:$J,D$2,'Raw Data'!$K:$K,"native",'Raw Data'!$H:$H,"Cash Out",'Raw Data'!$I:$I,"ATM/Kiosk",'Raw Data'!$M:$M,"percent",'Raw Data'!$F:$F,"Value*"))/100 -> 0.0748 | E56: =(SUMIFS('Raw Data'!$L:$L,'Raw Data'!$B:$B,$B$2,'Raw Data'!$J:$J,E$2,'Raw Data'!$K:$K,"native",'Raw Data'!$H:$H,"Cash Out",'Raw Data'!$I:$I,"ATM/Kiosk",'Raw Data'!$M:$M,"percent",'Raw Data'!$F:$F,"Value*"))/100 -> 0.0839 | F56: =(SUMIFS('Raw Data'!$L:$L,'Raw Data'!$B:$B,$B$2,'Raw Data'!$J:$J,F$2,'Raw Data'!$K:$K,"native",'Raw Data'!$H:$H,"Cash Out",'Raw Data'!$I:$I,"ATM/Kiosk",'Raw Data'!$M:$M,"percent",'Raw Data'!$F:$F,"Value*"))/100 -> 0.0826 | G56: =(SUMIFS('Raw Data'!$L:$L,'Raw Data'!$B:$B,$B$2,'Raw Data'!$J:$J,G$2,'Raw Data'!$K:$K,"native",'Raw Data'!$H:$H,"Cash Out",'Raw Data'!$I:$I,"ATM/Kiosk",'Raw Data'!$M:$M,"percent",'Raw Data'!$F:$F,"Value*"))/100 -> 0.0769 | H56: =(SUMIFS('Raw Data'!$L:$L,'Raw Data'!$B:$B,$B$2,'Raw Data'!$J:$J,H$2,'Raw Data'!$K:$K,"native",'Raw Data'!$H:$H,"Cash Out",'Raw Data'!$I:$I,"ATM/Kiosk",'Raw Data'!$M:$M,"percent",'Raw Data'!$F:$F,"Value*"))/100 -> 0.0705 | I56: =(SUMIFS('Raw Data'!$L:$L,'Raw Data'!$B:$B,$B$2,'Raw Data'!$J:$J,I$2,'Raw Data'!$K:$K,"native",'Raw Data'!$H:$H,"Cash Out",'Raw Data'!$I:$I,"ATM/Kiosk",'Raw Data'!$M:$M,"percent",'Raw Data'!$F:$F,"Value*"))/100 -> 0.0752 | J56: =(SUMIFS('Raw Data'!$L:$L,'Raw Data'!$B:$B,$B$2,'Raw Data'!$J:$J,J$2,'Raw Data'!$K:$K,"native",'Raw Data'!$H:$H,"Cash Out",'Raw Data'!$I:$I,"ATM/Kiosk",'Raw Data'!$M:$M,"percent",'Raw Data'!$F:$F,"Value*"))/100 -> 0.0685 | ... M56: =(SUMIFS('Raw Data'!$L:$L,'Raw Data'!$B:$B,$B$2,'Raw Data'!$J:$J,M$2,'Raw Data'!$K:$K,"native",'Raw Data'!$H:$H,"Cash Out",'Raw Data'!$I:$I,"ATM/Kiosk",'Raw Data'!$M:$M,"percent",'Raw Data'!$F:$F,"Value*"))/100 -> 0.0654 | Z56: =(SUMIFS('Raw Data'!$L:$L,'Raw Data'!$B:$B,$B$2,'Raw Data'!$J:$J,Z$2,'Raw Data'!$K:$K,"native",'Raw Data'!$H:$H,"Cash Out",'Raw Data'!$I:$I,"ATM/Kiosk",'Raw Data'!$M:$M,"percent",'Raw Data'!$F:$F,"Value*"))/100 -> 0.192
A57: Transactions | B57: Cash Out: Agent/Teller | C57: =(SUMIFS('Raw Data'!$L:$L,'Raw Data'!$B:$B,$B$2,'Raw Data'!$J:$J,C$2,'Raw Data'!$K:$K,"native",'Raw Data'!$H:$H,"Cash Out",'Raw Data'!$I:$I,"Agent/Teller",'Raw Data'!$M:$M,"percent",'Raw Data'!$F:$F,"Value*"))/100 -> 0.9223 | D57: =(SUMIFS('Raw Data'!$L:$L,'Raw Data'!$B:$B,$B$2,'Raw Data'!$J:$J,D$2,'Raw Data'!$K:$K,"native",'Raw Data'!$H:$H,"Cash Out",'Raw Data'!$I:$I,"Agent/Teller",'Raw Data'!$M:$M,"percent",'Raw Data'!$F:$F,"Value*"))/100 -> 0.9252 | E57: =(SUMIFS('Raw Data'!$L:$L,'Raw Data'!$B:$B,$B$2,'Raw Data'!$J:$J,E$2,'Raw Data'!$K:$K,"native",'Raw Data'!$H:$H,"Cash Out",'Raw Data'!$I:$I,"Agent/Teller",'Raw Data'!$M:$M,"percent",'Raw Data'!$F:$F,"Value*"))/100 -> 0.9161 | F57: =(SUMIFS('Raw Data'!$L:$L,'Raw Data'!$B:$B,$B$2,'Raw Data'!$J:$J,F$2,'Raw Data'!$K:$K,"native",'Raw Data'!$H:$H,"Cash Out",'Raw Data'!$I:$I,"Agent/Teller",'Raw Data'!$M:$M,"percent",'Raw Data'!$F:$F,"Value*"))/100 -> 0.9174 | G57: =(SUMIFS('Raw Data'!$L:$L,'Raw Data'!$B:$B,$B$2,'Raw Data'!$J:$J,G$2,'Raw Data'!$K:$K,"native",'Raw Data'!$H:$H,"Cash Out",'Raw Data'!$I:$I,"Agent/Teller",'Raw Data'!$M:$M,"percent",'Raw Data'!$F:$F,"Value*"))/100 -> 0.9231 | H57: =(SUMIFS('Raw Data'!$L:$L,'Raw Data'!$B:$B,$B$2,'Raw Data'!$J:$J,H$2,'Raw Data'!$K:$K,"native",'Raw Data'!$H:$H,"Cash Out",'Raw Data'!$I:$I,"Agent/Teller",'Raw Data'!$M:$M,"percent",'Raw Data'!$F:$F,"Value*"))/100 -> 0.9295 | I57: =(SUMIFS('Raw Data'!$L:$L,'Raw Data'!$B:$B,$B$2,'Raw Data'!$J:$J,I$2,'Raw Data'!$K:$K,"native",'Raw Data'!$H:$H,"Cash Out",'Raw Data'!$I:$I,"Agent/Teller",'Raw Data'!$M:$M,"percent",'Raw Data'!$F:$F,"Value*"))/100 -> 0.9248 | J57: =(SUMIFS('Raw Data'!$L:$L,'Raw Data'!$B:$B,$B$2,'Raw Data'!$J:$J,J$2,'Raw Data'!$K:$K,"native",'Raw Data'!$H:$H,"Cash Out",'Raw Data'!$I:$I,"Agent/Teller",'Raw Data'!$M:$M,"percent",'Raw Data'!$F:$F,"Value*"))/100 -> 0.9315 | ... M57: =(SUMIFS('Raw Data'!$L:$L,'Raw Data'!$B:$B,$B$2,'Raw Data'!$J:$J,M$2,'Raw Data'!$K:$K,"native",'Raw Data'!$H:$H,"Cash Out",'Raw Data'!$I:$I,"Agent/Teller",'Raw Data'!$M:$M,"percent",'Raw Data'!$F:$F,"Value*"))/100 -> 0.9346 | Z57: =(SUMIFS('Raw Data'!$L:$L,'Raw Data'!$B:$B,$B$2,'Raw Data'!$J:$J,Z$2,'Raw Data'!$K:$K,"native",'Raw Data'!$H:$H,"Cash Out",'Raw Data'!$I:$I,"Agent/Teller",'Raw Data'!$M:$M,"percent",'Raw Data'!$F:$F,"Value*"))/100 -> 0.808
A58: Transactions | B58: Money Transfers: Aid/Charity/Grant | C58: =(SUMIFS('Raw Data'!$L:$L,'Raw Data'!$B:$B,$B$2,'Raw Data'!$J:$J,C$2,'Raw Data'!$K:$K,"native",'Raw Data'!$H:$H,"Money Transfers",'Raw Data'!$I:$I,"Aid/Charity/Grant",'Raw Data'!$M:$M,"percent",'Raw Data'!$F:$F,"Value*"))/100 -> 0.0457 | D58: =(SUMIFS('Raw Data'!$L:$L,'Raw Data'!$B:$B,$B$2,'Raw Data'!$J:$J,D$2,'Raw Data'!$K:$K,"native",'Raw Data'!$H:$H,"Money Transfers",'Raw Data'!$I:$I,"Aid/Charity/Grant",'Raw Data'!$M:$M,"percent",'Raw Data'!$F:$F,"Value*"))/100 -> 0.0406 | E58: =(SUMIFS('Raw Data'!$L:$L,'Raw Data'!$B:$B,$B$2,'Raw Data'!$J:$J,E$2,'Raw Data'!$K:$K,"native",'Raw Data'!$H:$H,"Money Transfers",'Raw Data'!$I:$I,"Aid/Charity/Grant",'Raw Data'!$M:$M,"percent",'Raw Data'!$F:$F,"Value*"))/100 -> 0.0437 | F58: =(SUMIFS('Raw Data'!$L:$L,'Raw Data'!$B:$B,$B$2,'Raw Data'!$J:$J,F$2,'Raw Data'!$K:$K,"native",'Raw Data'!$H:$H,"Money Transfers",'Raw Data'!$I:$I,"Aid/Charity/Grant",'Raw Data'!$M:$M,"percent",'Raw Data'!$F:$F,"Value*"))/100 -> 0.0494 | G58: =(SUMIFS('Raw Data'!$L:$L,'Raw Data'!$B:$B,$B$2,'Raw Data'!$J:$J,G$2,'Raw Data'!$K:$K,"native",'Raw Data'!$H:$H,"Money Transfers",'Raw Data'!$I:$I,"Aid/Charity/Grant",'Raw Data'!$M:$M,"percent",'Raw Data'!$F:$F,"Value*"))/100 -> 0.038 | H58: =(SUMIFS('Raw Data'!$L:$L,'Raw Data'!$B:$B,$B$2,'Raw Data'!$J:$J,H$2,'Raw Data'!$K:$K,"native",'Raw Data'!$H:$H,"Money Transfers",'Raw Data'!$I:$I,"Aid/Charity/Grant",'Raw Data'!$M:$M,"percent",'Raw Data'!$F:$F,"Value*"))/100 -> 0.0405 | I58: =(SUMIFS('Raw Data'!$L:$L,'Raw Data'!$B:$B,$B$2,'Raw Data'!$J:$J,I$2,'Raw Data'!$K:$K,"native",'Raw Data'!$H:$H,"Money Transfers",'Raw Data'!$I:$I,"Aid/Charity/Grant",'Raw Data'!$M:$M,"percent",'Raw Data'!$F:$F,"Value*"))/100 -> 0.0521 | J58: =(SUMIFS('Raw Data'!$L:$L,'Raw Data'!$B:$B,$B$2,'Raw Data'!$J:$J,J$2,'Raw Data'!$K:$K,"native",'Raw Data'!$H:$H,"Money Transfers",'Raw Data'!$I:$I,"Aid/Charity/Grant",'Raw Data'!$M:$M,"percent",'Raw Data'!$F:$F,"Value*"))/100 -> 0.0321 | ... M58: =(SUMIFS('Raw Data'!$L:$L,'Raw Data'!$B:$B,$B$2,'Raw Data'!$J:$J,M$2,'Raw Data'!$K:$K,"native",'Raw Data'!$H:$H,"Money Transfers",'Raw Data'!$I:$I,"Aid/Charity/Grant",'Raw Data'!$M:$M,"percent",'Raw Data'!$F:$F,"Value*"))/100 -> 0.0273 | Z58: =(SUMIFS('Raw Data'!$L:$L,'Raw Data'!$B:$B,$B$2,'Raw Data'!$J:$J,Z$2,'Raw Data'!$K:$K,"native",'Raw Data'!$H:$H,"Money Transfers",'Raw Data'!$I:$I,"Aid/Charity/Grant",'Raw Data'!$M:$M,"percent",'Raw Data'!$F:$F,"Value*"))/100 -> 0.0362
A59: Transactions | B59: Money Transfers: Cross Border Remittances | C59: =(SUMIFS('Raw Data'!$L:$L,'Raw Data'!$B:$B,$B$2,'Raw Data'!$J:$J,C$2,'Raw Data'!$K:$K,"native",'Raw Data'!$H:$H,"Money Transfers",'Raw Data'!$I:$I,"Cross Border Remittances",'Raw Data'!$M:$M,"percent",'Raw Data'!$F:$F,"Value*"))/100 -> 0.0003 | D59: =(SUMIFS('Raw Data'!$L:$L,'Raw Data'!$B:$B,$B$2,'Raw Data'!$J:$J,D$2,'Raw Data'!$K:$K,"native",'Raw Data'!$H:$H,"Money Transfers",'Raw Data'!$I:$I,"Cross Border Remittances",'Raw Data'!$M:$M,"percent",'Raw Data'!$F:$F,"Value*"))/100 -> 0.0002 | E59: =(SUMIFS('Raw Data'!$L:$L,'Raw Data'!$B:$B,$B$2,'Raw Data'!$J:$J,E$2,'Raw Data'!$K:$K,"native",'Raw Data'!$H:$H,"Money Transfers",'Raw Data'!$I:$I,"Cross Border Remittances",'Raw Data'!$M:$M,"percent",'Raw Data'!$F:$F,"Value*"))/100 -> 0.0004 | F59: =(SUMIFS('Raw Data'!$L:$L,'Raw Data'!$B:$B,$B$2,'Raw Data'!$J:$J,F$2,'Raw Data'!$K:$K,"native",'Raw Data'!$H:$H,"Money Transfers",'Raw Data'!$I:$I,"Cross Border Remittances",'Raw Data'!$M:$M,"percent",'Raw Data'!$F:$F,"Value*"))/100 -> 0.0004 | G59: =(SUMIFS('Raw Data'!$L:$L,'Raw Data'!$B:$B,$B$2,'Raw Data'!$J:$J,G$2,'Raw Data'!$K:$K,"native",'Raw Data'!$H:$H,"Money Transfers",'Raw Data'!$I:$I,"Cross Border Remittances",'Raw Data'!$M:$M,"percent",'Raw Data'!$F:$F,"Value*"))/100 -> 0.0001 | H59: =(SUMIFS('Raw Data'!$L:$L,'Raw Data'!$B:$B,$B$2,'Raw Data'!$J:$J,H$2,'Raw Data'!$K:$K,"native",'Raw Data'!$H:$H,"Money Transfers",'Raw Data'!$I:$I,"Cross Border Remittances",'Raw Data'!$M:$M,"percent",'Raw Data'!$F:$F,"Value*"))/100 -> 0 | I59: =(SUMIFS('Raw Data'!$L:$L,'Raw Data'!$B:$B,$B$2,'Raw Data'!$J:$J,I$2,'Raw Data'!$K:$K,"native",'Raw Data'!$H:$H,"Money Transfers",'Raw Data'!$I:$I,"Cross Border Remittances",'Raw Data'!$M:$M,"percent",'Raw Data'!$F:$F,"Value*"))/100 -> 0 | J59: =(SUMIFS('Raw Data'!$L:$L,'Raw Data'!$B:$B,$B$2,'Raw Data'!$J:$J,J$2,'Raw Data'!$K:$K,"native",'Raw Data'!$H:$H,"Money Transfers",'Raw Data'!$I:$I,"Cross Border Remittances",'Raw Data'!$M:$M,"percent",'Raw Data'!$F:$F,"Value*"))/100 -> 0 | ... L59: =(SUMIFS('Raw Data'!$L:$L,'Raw Data'!$B:$B,$B$2,'Raw Data'!$J:$J,L$2,'Raw Data'!$K:$K,"native",'Raw Data'!$H:$H,"Money Transfers",'Raw Data'!$I:$I,"Cross Border Remittances",'Raw Data'!$M:$M,"percent",'Raw Data'!$F:$F,"Value*"))/100 -> 0
A60: Transactions | B60: Money Transfers: Loan/Loan Installment | C60: =(SUMIFS('Raw Data'!$L:$L,'Raw Data'!$B:$B,$B$2,'Raw Data'!$J:$J,C$2,'Raw Data'!$K:$K,"native",'Raw Data'!$H:$H,"Money Transfers",'Raw Data'!$I:$I,"Loan/Loan Installment",'Raw Data'!$M:$M,"percent",'Raw Data'!$F:$F,"Value*"))/100 -> 0.0296 | D60: =(SUMIFS('Raw Data'!$L:$L,'Raw Data'!$B:$B,$B$2,'Raw Data'!$J:$J,D$2,'Raw Data'!$K:$K,"native",'Raw Data'!$H:$H,"Money Transfers",'Raw Data'!$I:$I,"Loan/Loan Installment",'Raw Data'!$M:$M,"percent",'Raw Data'!$F:$F,"Value*"))/100 -> 0.0307 | E60: =(SUMIFS('Raw Data'!$L:$L,'Raw Data'!$B:$B,$B$2,'Raw Data'!$J:$J,E$2,'Raw Data'!$K:$K,"native",'Raw Data'!$H:$H,"Money Transfers",'Raw Data'!$I:$I,"Loan/Loan Installment",'Raw Data'!$M:$M,"percent",'Raw Data'!$F:$F,"Value*"))/100 -> 0.0275 | F60: =(SUMIFS('Raw Data'!$L:$L,'Raw Data'!$B:$B,$B$2,'Raw Data'!$J:$J,F$2,'Raw Data'!$K:$K,"native",'Raw Data'!$H:$H,"Money Transfers",'Raw Data'!$I:$I,"Loan/Loan Installment",'Raw Data'!$M:$M,"percent",'Raw Data'!$F:$F,"Value*"))/100 -> 0.0254 | G60: =(SUMIFS('Raw Data'!$L:$L,'Raw Data'!$B:$B,$B$2,'Raw Data'!$J:$J,G$2,'Raw Data'!$K:$K,"native",'Raw Data'!$H:$H,"Money Transfers",'Raw Data'!$I:$I,"Loan/Loan Installment",'Raw Data'!$M:$M,"percent",'Raw Data'!$F:$F,"Value*"))/100 -> 0.0247 | H60: =(SUMIFS('Raw Data'!$L:$L,'Raw Data'!$B:$B,$B$2,'Raw Data'!$J:$J,H$2,'Raw Data'!$K:$K,"native",'Raw Data'!$H:$H,"Money Transfers",'Raw Data'!$I:$I,"Loan/Loan Installment",'Raw Data'!$M:$M,"percent",'Raw Data'!$F:$F,"Value*"))/100 -> 0.0256 | I60: =(SUMIFS('Raw Data'!$L:$L,'Raw Data'!$B:$B,$B$2,'Raw Data'!$J:$J,I$2,'Raw Data'!$K:$K,"native",'Raw Data'!$H:$H,"Money Transfers",'Raw Data'!$I:$I,"Loan/Loan Installment",'Raw Data'!$M:$M,"percent",'Raw Data'!$F:$F,"Value*"))/100 -> 0.018 | J60: =(SUMIFS('Raw Data'!$L:$L,'Raw Data'!$B:$B,$B$2,'Raw Data'!$J:$J,J$2,'Raw Data'!$K:$K,"native",'Raw Data'!$H:$H,"Money Transfers",'Raw Data'!$I:$I,"Loan/Loan Installment",'Raw Data'!$M:$M,"percent",'Raw Data'!$F:$F,"Value*"))/100 -> 0.0215 | ... M60: =(SUMIFS('Raw Data'!$L:$L,'Raw Data'!$B:$B,$B$2,'Raw Data'!$J:$J,M$2,'Raw Data'!$K:$K,"native",'Raw Data'!$H:$H,"Money Transfers",'Raw Data'!$I:$I,"Loan/Loan Installment",'Raw Data'!$M:$M,"percent",'Raw Data'!$F:$F,"Value*"))/100 -> 0.0007 | Z60: =(SUMIFS('Raw Data'!$L:$L,'Raw Data'!$B:$B,$B$2,'Raw Data'!$J:$J,Z$2,'Raw Data'!$K:$K,"native",'Raw Data'!$H:$H,"Money Transfers",'Raw Data'!$I:$I,"Loan/Loan Installment",'Raw Data'!$M:$M,"percent",'Raw Data'!$F:$F,"Value*"))/100 -> 0.0003
A61: Transactions | B61: Money Transfers: Salary/Bonus/Dividends | C61: =(SUMIFS('Raw Data'!$L:$L,'Raw Data'!$B:$B,$B$2,'Raw Data'!$J:$J,C$2,'Raw Data'!$K:$K,"native",'Raw Data'!$H:$H,"Money Transfers",'Raw Data'!$I:$I,"Salary/Bonus/Dividends",'Raw Data'!$M:$M,"percent",'Raw Data'!$F:$F,"Value*"))/100 -> 0.0475 | D61: =(SUMIFS('Raw Data'!$L:$L,'Raw Data'!$B:$B,$B$2,'Raw Data'!$J:$J,D$2,'Raw Data'!$K:$K,"native",'Raw Data'!$H:$H,"Money Transfers",'Raw Data'!$I:$I,"Salary/Bonus/Dividends",'Raw Data'!$M:$M,"percent",'Raw Data'!$F:$F,"Value*"))/100 -> 0.056 | E61: =(SUMIFS('Raw Data'!$L:$L,'Raw Data'!$B:$B,$B$2,'Raw Data'!$J:$J,E$2,'Raw Data'!$K:$K,"native",'Raw Data'!$H:$H,"Money Transfers",'Raw Data'!$I:$I,"Salary/Bonus/Dividends",'Raw Data'!$M:$M,"percent",'Raw Data'!$F:$F,"Value*"))/100 -> 0.0405 | F61: =(SUMIFS('Raw Data'!$L:$L,'Raw Data'!$B:$B,$B$2,'Raw Data'!$J:$J,F$2,'Raw Data'!$K:$K,"native",'Raw Data'!$H:$H,"Money Transfers",'Raw Data'!$I:$I,"Salary/Bonus/Dividends",'Raw Data'!$M:$M,"percent",'Raw Data'!$F:$F,"Value*"))/100 -> 0.051 | G61: =(SUMIFS('Raw Data'!$L:$L,'Raw Data'!$B:$B,$B$2,'Raw Data'!$J:$J,G$2,'Raw Data'!$K:$K,"native",'Raw Data'!$H:$H,"Money Transfers",'Raw Data'!$I:$I,"Salary/Bonus/Dividends",'Raw Data'!$M:$M,"percent",'Raw Data'!$F:$F,"Value*"))/100 -> 0.0468 | H61: =(SUMIFS('Raw Data'!$L:$L,'Raw Data'!$B:$B,$B$2,'Raw Data'!$J:$J,H$2,'Raw Data'!$K:$K,"native",'Raw Data'!$H:$H,"Money Transfers",'Raw Data'!$I:$I,"Salary/Bonus/Dividends",'Raw Data'!$M:$M,"percent",'Raw Data'!$F:$F,"Value*"))/100 -> 0.0351 | I61: =(SUMIFS('Raw Data'!$L:$L,'Raw Data'!$B:$B,$B$2,'Raw Data'!$J:$J,I$2,'Raw Data'!$K:$K,"native",'Raw Data'!$H:$H,"Money Transfers",'Raw Data'!$I:$I,"Salary/Bonus/Dividends",'Raw Data'!$M:$M,"percent",'Raw Data'!$F:$F,"Value*"))/100 -> 0.0426 | J61: =(SUMIFS('Raw Data'!$L:$L,'Raw Data'!$B:$B,$B$2,'Raw Data'!$J:$J,J$2,'Raw Data'!$K:$K,"native",'Raw Data'!$H:$H,"Money Transfers",'Raw Data'!$I:$I,"Salary/Bonus/Dividends",'Raw Data'!$M:$M,"percent",'Raw Data'!$F:$F,"Value*"))/100 -> 0.0386 | ... M61: =(SUMIFS('Raw Data'!$L:$L,'Raw Data'!$B:$B,$B$2,'Raw Data'!$J:$J,M$2,'Raw Data'!$K:$K,"native",'Raw Data'!$H:$H,"Money Transfers",'Raw Data'!$I:$I,"Salary/Bonus/Dividends",'Raw Data'!$M:$M,"percent",'Raw Data'!$F:$F,"Value*"))/100 -> 0.0538 | Z61: =(SUMIFS('Raw Data'!$L:$L,'Raw Data'!$B:$B,$B$2,'Raw Data'!$J:$J,Z$2,'Raw Data'!$K:$K,"native",'Raw Data'!$H:$H,"Money Transfers",'Raw Data'!$I:$I,"Salary/Bonus/Dividends",'Raw Data'!$M:$M,"percent",'Raw Data'!$F:$F,"Value*"))/100 -> 0.0119
A62: Transactions | B62: Money Transfers: Transfer to Family/Friends | C62: =(SUMIFS('Raw Data'!$L:$L,'Raw Data'!$B:$B,$B$2,'Raw Data'!$J:$J,C$2,'Raw Data'!$K:$K,"native",'Raw Data'!$H:$H,"Money Transfers",'Raw Data'!$I:$I,"Transfer to Family/Friends",'Raw Data'!$M:$M,"percent",'Raw Data'!$F:$F,"Value*"))/100 -> 0.7369 | D62: =(SUMIFS('Raw Data'!$L:$L,'Raw Data'!$B:$B,$B$2,'Raw Data'!$J:$J,D$2,'Raw Data'!$K:$K,"native",'Raw Data'!$H:$H,"Money Transfers",'Raw Data'!$I:$I,"Transfer to Family/Friends",'Raw Data'!$M:$M,"percent",'Raw Data'!$F:$F,"Value*"))/100 -> 0.7188 | E62: =(SUMIFS('Raw Data'!$L:$L,'Raw Data'!$B:$B,$B$2,'Raw Data'!$J:$J,E$2,'Raw Data'!$K:$K,"native",'Raw Data'!$H:$H,"Money Transfers",'Raw Data'!$I:$I,"Transfer to Family/Friends",'Raw Data'!$M:$M,"percent",'Raw Data'!$F:$F,"Value*"))/100 -> 0.7339 | F62: =(SUMIFS('Raw Data'!$L:$L,'Raw Data'!$B:$B,$B$2,'Raw Data'!$J:$J,F$2,'Raw Data'!$K:$K,"native",'Raw Data'!$H:$H,"Money Transfers",'Raw Data'!$I:$I,"Transfer to Family/Friends",'Raw Data'!$M:$M,"percent",'Raw Data'!$F:$F,"Value*"))/100 -> 0.7219 | G62: =(SUMIFS('Raw Data'!$L:$L,'Raw Data'!$B:$B,$B$2,'Raw Data'!$J:$J,G$2,'Raw Data'!$K:$K,"native",'Raw Data'!$H:$H,"Money Transfers",'Raw Data'!$I:$I,"Transfer to Family/Friends",'Raw Data'!$M:$M,"percent",'Raw Data'!$F:$F,"Value*"))/100 -> 0.7352 | H62: =(SUMIFS('Raw Data'!$L:$L,'Raw Data'!$B:$B,$B$2,'Raw Data'!$J:$J,H$2,'Raw Data'!$K:$K,"native",'Raw Data'!$H:$H,"Money Transfers",'Raw Data'!$I:$I,"Transfer to Family/Friends",'Raw Data'!$M:$M,"percent",'Raw Data'!$F:$F,"Value*"))/100 -> 0.7417 | I62: =(SUMIFS('Raw Data'!$L:$L,'Raw Data'!$B:$B,$B$2,'Raw Data'!$J:$J,I$2,'Raw Data'!$K:$K,"native",'Raw Data'!$H:$H,"Money Transfers",'Raw Data'!$I:$I,"Transfer to Family/Friends",'Raw Data'!$M:$M,"percent",'Raw Data'!$F:$F,"Value*"))/100 -> 0.7393 | J62: =(SUMIFS('Raw Data'!$L:$L,'Raw Data'!$B:$B,$B$2,'Raw Data'!$J:$J,J$2,'Raw Data'!$K:$K,"native",'Raw Data'!$H:$H,"Money Transfers",'Raw Data'!$I:$I,"Transfer to Family/Friends",'Raw Data'!$M:$M,"percent",'Raw Data'!$F:$F,"Value*"))/100 -> 0.7513 | ... M62: =(SUMIFS('Raw Data'!$L:$L,'Raw Data'!$B:$B,$B$2,'Raw Data'!$J:$J,M$2,'Raw Data'!$K:$K,"native",'Raw Data'!$H:$H,"Money Transfers",'Raw Data'!$I:$I,"Transfer to Family/Friends",'Raw Data'!$M:$M,"percent",'Raw Data'!$F:$F,"Value*"))/100 -> 0.7013 | Z62: =(SUMIFS('Raw Data'!$L:$L,'Raw Data'!$B:$B,$B$2,'Raw Data'!$J:$J,Z$2,'Raw Data'!$K:$K,"native",'Raw Data'!$H:$H,"Money Transfers",'Raw Data'!$I:$I,"Transfer to Family/Friends",'Raw Data'!$M:$M,"percent",'Raw Data'!$F:$F,"Value*"))/100 -> 0.6423
A63: Transactions | B63: Money Transfers: Transfer to Own Account | C63: =(SUMIFS('Raw Data'!$L:$L,'Raw Data'!$B:$B,$B$2,'Raw Data'!$J:$J,C$2,'Raw Data'!$K:$K,"native",'Raw Data'!$H:$H,"Money Transfers",'Raw Data'!$I:$I,"Transfer to Own Account",'Raw Data'!$M:$M,"percent",'Raw Data'!$F:$F,"Value*"))/100 -> 0.14 | D63: =(SUMIFS('Raw Data'!$L:$L,'Raw Data'!$B:$B,$B$2,'Raw Data'!$J:$J,D$2,'Raw Data'!$K:$K,"native",'Raw Data'!$H:$H,"Money Transfers",'Raw Data'!$I:$I,"Transfer to Own Account",'Raw Data'!$M:$M,"percent",'Raw Data'!$F:$F,"Value*"))/100 -> 0.1537 | E63: =(SUMIFS('Raw Data'!$L:$L,'Raw Data'!$B:$B,$B$2,'Raw Data'!$J:$J,E$2,'Raw Data'!$K:$K,"native",'Raw Data'!$H:$H,"Money Transfers",'Raw Data'!$I:$I,"Transfer to Own Account",'Raw Data'!$M:$M,"percent",'Raw Data'!$F:$F,"Value*"))/100 -> 0.1541 | F63: =(SUMIFS('Raw Data'!$L:$L,'Raw Data'!$B:$B,$B$2,'Raw Data'!$J:$J,F$2,'Raw Data'!$K:$K,"native",'Raw Data'!$H:$H,"Money Transfers",'Raw Data'!$I:$I,"Transfer to Own Account",'Raw Data'!$M:$M,"percent",'Raw Data'!$F:$F,"Value*"))/100 -> 0.1518 | G63: =(SUMIFS('Raw Data'!$L:$L,'Raw Data'!$B:$B,$B$2,'Raw Data'!$J:$J,G$2,'Raw Data'!$K:$K,"native",'Raw Data'!$H:$H,"Money Transfers",'Raw Data'!$I:$I,"Transfer to Own Account",'Raw Data'!$M:$M,"percent",'Raw Data'!$F:$F,"Value*"))/100 -> 0.1552 | H63: =(SUMIFS('Raw Data'!$L:$L,'Raw Data'!$B:$B,$B$2,'Raw Data'!$J:$J,H$2,'Raw Data'!$K:$K,"native",'Raw Data'!$H:$H,"Money Transfers",'Raw Data'!$I:$I,"Transfer to Own Account",'Raw Data'!$M:$M,"percent",'Raw Data'!$F:$F,"Value*"))/100 -> 0.1571 | I63: =(SUMIFS('Raw Data'!$L:$L,'Raw Data'!$B:$B,$B$2,'Raw Data'!$J:$J,I$2,'Raw Data'!$K:$K,"native",'Raw Data'!$H:$H,"Money Transfers",'Raw Data'!$I:$I,"Transfer to Own Account",'Raw Data'!$M:$M,"percent",'Raw Data'!$F:$F,"Value*"))/100 -> 0.148 | J63: =(SUMIFS('Raw Data'!$L:$L,'Raw Data'!$B:$B,$B$2,'Raw Data'!$J:$J,J$2,'Raw Data'!$K:$K,"native",'Raw Data'!$H:$H,"Money Transfers",'Raw Data'!$I:$I,"Transfer to Own Account",'Raw Data'!$M:$M,"percent",'Raw Data'!$F:$F,"Value*"))/100 -> 0.1565 | ... M63: =(SUMIFS('Raw Data'!$L:$L,'Raw Data'!$B:$B,$B$2,'Raw Data'!$J:$J,M$2,'Raw Data'!$K:$K,"native",'Raw Data'!$H:$H,"Money Transfers",'Raw Data'!$I:$I,"Transfer to Own Account",'Raw Data'!$M:$M,"percent",'Raw Data'!$F:$F,"Value*"))/100 -> 0.2089 | Z63: =(SUMIFS('Raw Data'!$L:$L,'Raw Data'!$B:$B,$B$2,'Raw Data'!$J:$J,Z$2,'Raw Data'!$K:$K,"native",'Raw Data'!$H:$H,"Money Transfers",'Raw Data'!$I:$I,"Transfer to Own Account",'Raw Data'!$M:$M,"percent",'Raw Data'!$F:$F,"Value*"))/100 -> 0.2265
A64: Transactions | B64: Purchases: Purchases | C64: =(SUMIFS('Raw Data'!$L:$L,'Raw Data'!$B:$B,$B$2,'Raw Data'!$J:$J,C$2,'Raw Data'!$K:$K,"native",'Raw Data'!$H:$H,"Purchases",'Raw Data'!$I:$I,"Purchases",'Raw Data'!$M:$M,"percent",'Raw Data'!$F:$F,"Value*"))/100 -> 0.9677 | D64: =(SUMIFS('Raw Data'!$L:$L,'Raw Data'!$B:$B,$B$2,'Raw Data'!$J:$J,D$2,'Raw Data'!$K:$K,"native",'Raw Data'!$H:$H,"Purchases",'Raw Data'!$I:$I,"Purchases",'Raw Data'!$M:$M,"percent",'Raw Data'!$F:$F,"Value*"))/100 -> 0.9613 | E64: =(SUMIFS('Raw Data'!$L:$L,'Raw Data'!$B:$B,$B$2,'Raw Data'!$J:$J,E$2,'Raw Data'!$K:$K,"native",'Raw Data'!$H:$H,"Purchases",'Raw Data'!$I:$I,"Purchases",'Raw Data'!$M:$M,"percent",'Raw Data'!$F:$F,"Value*"))/100 -> 0.9528 | F64: =(SUMIFS('Raw Data'!$L:$L,'Raw Data'!$B:$B,$B$2,'Raw Data'!$J:$J,F$2,'Raw Data'!$K:$K,"native",'Raw Data'!$H:$H,"Purchases",'Raw Data'!$I:$I,"Purchases",'Raw Data'!$M:$M,"percent",'Raw Data'!$F:$F,"Value*"))/100 -> 0.9544 | G64: =(SUMIFS('Raw Data'!$L:$L,'Raw Data'!$B:$B,$B$2,'Raw Data'!$J:$J,G$2,'Raw Data'!$K:$K,"native",'Raw Data'!$H:$H,"Purchases",'Raw Data'!$I:$I,"Purchases",'Raw Data'!$M:$M,"percent",'Raw Data'!$F:$F,"Value*"))/100 -> 0.8449 | H64: =(SUMIFS('Raw Data'!$L:$L,'Raw Data'!$B:$B,$B$2,'Raw Data'!$J:$J,H$2,'Raw Data'!$K:$K,"native",'Raw Data'!$H:$H,"Purchases",'Raw Data'!$I:$I,"Purchases",'Raw Data'!$M:$M,"percent",'Raw Data'!$F:$F,"Value*"))/100 -> 0.8288 | I64: =(SUMIFS('Raw Data'!$L:$L,'Raw Data'!$B:$B,$B$2,'Raw Data'!$J:$J,I$2,'Raw Data'!$K:$K,"native",'Raw Data'!$H:$H,"Purchases",'Raw Data'!$I:$I,"Purchases",'Raw Data'!$M:$M,"percent",'Raw Data'!$F:$F,"Value*"))/100 -> 0.8398 | J64: =(SUMIFS('Raw Data'!$L:$L,'Raw Data'!$B:$B,$B$2,'Raw Data'!$J:$J,J$2,'Raw Data'!$K:$K,"native",'Raw Data'!$H:$H,"Purchases",'Raw Data'!$I:$I,"Purchases",'Raw Data'!$M:$M,"percent",'Raw Data'!$F:$F,"Value*"))/100 -> 0.8187 | ... M64: =(SUMIFS('Raw Data'!$L:$L,'Raw Data'!$B:$B,$B$2,'Raw Data'!$J:$J,M$2,'Raw Data'!$K:$K,"native",'Raw Data'!$H:$H,"Purchases",'Raw Data'!$I:$I,"Purchases",'Raw Data'!$M:$M,"percent",'Raw Data'!$F:$F,"Value*"))/100 -> 0.9487 | Z64: =(SUMIFS('Raw Data'!$L:$L,'Raw Data'!$B:$B,$B$2,'Raw Data'!$J:$J,Z$2,'Raw Data'!$K:$K,"native",'Raw Data'!$H:$H,"Purchases",'Raw Data'!$I:$I,"Purchases",'Raw Data'!$M:$M,"percent",'Raw Data'!$F:$F,"Value*"))/100 -> 0.9746
A65: Transactions | B65: Purchases: QR Purchases | C65: =(SUMIFS('Raw Data'!$L:$L,'Raw Data'!$B:$B,$B$2,'Raw Data'!$J:$J,C$2,'Raw Data'!$K:$K,"native",'Raw Data'!$H:$H,"Purchases",'Raw Data'!$I:$I,"QR Purchases",'Raw Data'!$M:$M,"percent",'Raw Data'!$F:$F,"Value*"))/100 -> 0.0323 | D65: =(SUMIFS('Raw Data'!$L:$L,'Raw Data'!$B:$B,$B$2,'Raw Data'!$J:$J,D$2,'Raw Data'!$K:$K,"native",'Raw Data'!$H:$H,"Purchases",'Raw Data'!$I:$I,"QR Purchases",'Raw Data'!$M:$M,"percent",'Raw Data'!$F:$F,"Value*"))/100 -> 0.0387 | E65: =(SUMIFS('Raw Data'!$L:$L,'Raw Data'!$B:$B,$B$2,'Raw Data'!$J:$J,E$2,'Raw Data'!$K:$K,"native",'Raw Data'!$H:$H,"Purchases",'Raw Data'!$I:$I,"QR Purchases",'Raw Data'!$M:$M,"percent",'Raw Data'!$F:$F,"Value*"))/100 -> 0.0472 | F65: =(SUMIFS('Raw Data'!$L:$L,'Raw Data'!$B:$B,$B$2,'Raw Data'!$J:$J,F$2,'Raw Data'!$K:$K,"native",'Raw Data'!$H:$H,"Purchases",'Raw Data'!$I:$I,"QR Purchases",'Raw Data'!$M:$M,"percent",'Raw Data'!$F:$F,"Value*"))/100 -> 0.0456 | G65: =(SUMIFS('Raw Data'!$L:$L,'Raw Data'!$B:$B,$B$2,'Raw Data'!$J:$J,G$2,'Raw Data'!$K:$K,"native",'Raw Data'!$H:$H,"Purchases",'Raw Data'!$I:$I,"QR Purchases",'Raw Data'!$M:$M,"percent",'Raw Data'!$F:$F,"Value*"))/100 -> 0.1551 | H65: =(SUMIFS('Raw Data'!$L:$L,'Raw Data'!$B:$B,$B$2,'Raw Data'!$J:$J,H$2,'Raw Data'!$K:$K,"native",'Raw Data'!$H:$H,"Purchases",'Raw Data'!$I:$I,"QR Purchases",'Raw Data'!$M:$M,"percent",'Raw Data'!$F:$F,"Value*"))/100 -> 0.1712 | I65: =(SUMIFS('Raw Data'!$L:$L,'Raw Data'!$B:$B,$B$2,'Raw Data'!$J:$J,I$2,'Raw Data'!$K:$K,"native",'Raw Data'!$H:$H,"Purchases",'Raw Data'!$I:$I,"QR Purchases",'Raw Data'!$M:$M,"percent",'Raw Data'!$F:$F,"Value*"))/100 -> 0.1602 | J65: =(SUMIFS('Raw Data'!$L:$L,'Raw Data'!$B:$B,$B$2,'Raw Data'!$J:$J,J$2,'Raw Data'!$K:$K,"native",'Raw Data'!$H:$H,"Purchases",'Raw Data'!$I:$I,"QR Purchases",'Raw Data'!$M:$M,"percent",'Raw Data'!$F:$F,"Value*"))/100 -> 0.1813 | ... M65: =(SUMIFS('Raw Data'!$L:$L,'Raw Data'!$B:$B,$B$2,'Raw Data'!$J:$J,M$2,'Raw Data'!$K:$K,"native",'Raw Data'!$H:$H,"Purchases",'Raw Data'!$I:$I,"QR Purchases",'Raw Data'!$M:$M,"percent",'Raw Data'!$F:$F,"Value*"))/100 -> 0.0513 | Z65: =(SUMIFS('Raw Data'!$L:$L,'Raw Data'!$B:$B,$B$2,'Raw Data'!$J:$J,Z$2,'Raw Data'!$K:$K,"native",'Raw Data'!$H:$H,"Purchases",'Raw Data'!$I:$I,"QR Purchases",'Raw Data'!$M:$M,"percent",'Raw Data'!$F:$F,"Value*"))/100 -> 0.0254
A66: Transactions | B66: Money Transfers: Loan/Loan Disbursement | M66: =(SUMIFS('Raw Data'!$L:$L,'Raw Data'!$B:$B,$B$2,'Raw Data'!$J:$J,M$2,'Raw Data'!$K:$K,"native",'Raw Data'!$H:$H,"Money Transfers",'Raw Data'!$I:$I,"Loan/Loan Disbursement",'Raw Data'!$M:$M,"percent",'Raw Data'!$F:$F,"Value*"))/100 -> 0.008 | Z66: =(SUMIFS('Raw Data'!$L:$L,'Raw Data'!$B:$B,$B$2,'Raw Data'!$J:$J,Z$2,'Raw Data'!$K:$K,"native",'Raw Data'!$H:$H,"Money Transfers",'Raw Data'!$I:$I,"Loan/Loan Disbursement",'Raw Data'!$M:$M,"percent",'Raw Data'!$F:$F,"Value*"))/100 -> 0.0117
A67: Transactions | B67: Money Transfers: Loan Disbursement
A68: Transactions | B68: Money Transfers: Loan Installment
A69: Transactions | B69: Purchases: Non-QR Purchases
A70: Transactions | B70: Money Transfers: Goods/Services | Z70: =(SUMIFS('Raw Data'!$L:$L,'Raw Data'!$B:$B,$B$2,'Raw Data'!$J:$J,Z$2,'Raw Data'!$K:$K,"native",'Raw Data'!$H:$H,"Money Transfers",'Raw Data'!$I:$I,"Goods/Services",'Raw Data'!$M:$M,"percent",'Raw Data'!$F:$F,"Value*"))/100 -> 0.071
A71: TRANSACTIONS BY DIRECTION (ON US / OFF US) (Number)
A72: Transactions | B72: Off Us | C72: =SUMIFS('Raw Data'!$L:$L,'Raw Data'!$B:$B,$B$2,'Raw Data'!$J:$J,C$2,'Raw Data'!$K:$K,"native",'Raw Data'!$H:$H,"Off Us",'Raw Data'!$I:$I,"",'Raw Data'!$M:$M,"count") -> 1500000 | D72: =SUMIFS('Raw Data'!$L:$L,'Raw Data'!$B:$B,$B$2,'Raw Data'!$J:$J,D$2,'Raw Data'!$K:$K,"native",'Raw Data'!$H:$H,"Off Us",'Raw Data'!$I:$I,"",'Raw Data'!$M:$M,"count") -> 1650000 | E72: =SUMIFS('Raw Data'!$L:$L,'Raw Data'!$B:$B,$B$2,'Raw Data'!$J:$J,E$2,'Raw Data'!$K:$K,"native",'Raw Data'!$H:$H,"Off Us",'Raw Data'!$I:$I,"",'Raw Data'!$M:$M,"count") -> 1590000 | F72: =SUMIFS('Raw Data'!$L:$L,'Raw Data'!$B:$B,$B$2,'Raw Data'!$J:$J,F$2,'Raw Data'!$K:$K,"native",'Raw Data'!$H:$H,"Off Us",'Raw Data'!$I:$I,"",'Raw Data'!$M:$M,"count") -> 1750000 | G72: =SUMIFS('Raw Data'!$L:$L,'Raw Data'!$B:$B,$B$2,'Raw Data'!$J:$J,G$2,'Raw Data'!$K:$K,"native",'Raw Data'!$H:$H,"Off Us",'Raw Data'!$I:$I,"",'Raw Data'!$M:$M,"count") -> 1800000 | H72: =SUMIFS('Raw Data'!$L:$L,'Raw Data'!$B:$B,$B$2,'Raw Data'!$J:$J,H$2,'Raw Data'!$K:$K,"native",'Raw Data'!$H:$H,"Off Us",'Raw Data'!$I:$I,"",'Raw Data'!$M:$M,"count") -> 1610000 | I72: =SUMIFS('Raw Data'!$L:$L,'Raw Data'!$B:$B,$B$2,'Raw Data'!$J:$J,I$2,'Raw Data'!$K:$K,"native",'Raw Data'!$H:$H,"Off Us",'Raw Data'!$I:$I,"",'Raw Data'!$M:$M,"count") -> 2040000 | J72: =SUMIFS('Raw Data'!$L:$L,'Raw Data'!$B:$B,$B$2,'Raw Data'!$J:$J,J$2,'Raw Data'!$K:$K,"native",'Raw Data'!$H:$H,"Off Us",'Raw Data'!$I:$I,"",'Raw Data'!$M:$M,"count") -> 1870000 | ... Z72: =SUMIFS('Raw Data'!$L:$L,'Raw Data'!$B:$B,$B$2,'Raw Data'!$J:$J,Z$2,'Raw Data'!$K:$K,"native",'Raw Data'!$H:$H,"Off Us",'Raw Data'!$I:$I,"",'Raw Data'!$M:$M,"count") -> 3480000
A73: Transactions | B73: On Us | C73: =SUMIFS('Raw Data'!$L:$L,'Raw Data'!$B:$B,$B$2,'Raw Data'!$J:$J,C$2,'Raw Data'!$K:$K,"native",'Raw Data'!$H:$H,"On Us",'Raw Data'!$I:$I,"",'Raw Data'!$M:$M,"count") -> 1600000 | D73: =SUMIFS('Raw Data'!$L:$L,'Raw Data'!$B:$B,$B$2,'Raw Data'!$J:$J,D$2,'Raw Data'!$K:$K,"native",'Raw Data'!$H:$H,"On Us",'Raw Data'!$I:$I,"",'Raw Data'!$M:$M,"count") -> 1710000 | E73: =SUMIFS('Raw Data'!$L:$L,'Raw Data'!$B:$B,$B$2,'Raw Data'!$J:$J,E$2,'Raw Data'!$K:$K,"native",'Raw Data'!$H:$H,"On Us",'Raw Data'!$I:$I,"",'Raw Data'!$M:$M,"count") -> 1810000 | F73: =SUMIFS('Raw Data'!$L:$L,'Raw Data'!$B:$B,$B$2,'Raw Data'!$J:$J,F$2,'Raw Data'!$K:$K,"native",'Raw Data'!$H:$H,"On Us",'Raw Data'!$I:$I,"",'Raw Data'!$M:$M,"count") -> 2090000 | G73: =SUMIFS('Raw Data'!$L:$L,'Raw Data'!$B:$B,$B$2,'Raw Data'!$J:$J,G$2,'Raw Data'!$K:$K,"native",'Raw Data'!$H:$H,"On Us",'Raw Data'!$I:$I,"",'Raw Data'!$M:$M,"count") -> 2170000 | H73: =SUMIFS('Raw Data'!$L:$L,'Raw Data'!$B:$B,$B$2,'Raw Data'!$J:$J,H$2,'Raw Data'!$K:$K,"native",'Raw Data'!$H:$H,"On Us",'Raw Data'!$I:$I,"",'Raw Data'!$M:$M,"count") -> 2000000 | I73: =SUMIFS('Raw Data'!$L:$L,'Raw Data'!$B:$B,$B$2,'Raw Data'!$J:$J,I$2,'Raw Data'!$K:$K,"native",'Raw Data'!$H:$H,"On Us",'Raw Data'!$I:$I,"",'Raw Data'!$M:$M,"count") -> 2500000 | J73: =SUMIFS('Raw Data'!$L:$L,'Raw Data'!$B:$B,$B$2,'Raw Data'!$J:$J,J$2,'Raw Data'!$K:$K,"native",'Raw Data'!$H:$H,"On Us",'Raw Data'!$I:$I,"",'Raw Data'!$M:$M,"count") -> 2460000 | ... Z73: =SUMIFS('Raw Data'!$L:$L,'Raw Data'!$B:$B,$B$2,'Raw Data'!$J:$J,Z$2,'Raw Data'!$K:$K,"native",'Raw Data'!$H:$H,"On Us",'Raw Data'!$I:$I,"",'Raw Data'!$M:$M,"count") -> 6680000
A74: TRANSACTIONS BY DIRECTION (ON US / OFF US) (Value, JOD)
A75: Transactions | B75: Off Us | C75: =SUMIFS('Raw Data'!$L:$L,'Raw Data'!$B:$B,$B$2,'Raw Data'!$J:$J,C$2,'Raw Data'!$K:$K,"native",'Raw Data'!$H:$H,"Off Us",'Raw Data'!$I:$I,"",'Raw Data'!$M:$M,"JOD") -> 89600000 | D75: =SUMIFS('Raw Data'!$L:$L,'Raw Data'!$B:$B,$B$2,'Raw Data'!$J:$J,D$2,'Raw Data'!$K:$K,"native",'Raw Data'!$H:$H,"Off Us",'Raw Data'!$I:$I,"",'Raw Data'!$M:$M,"JOD") -> 92300000 | E75: =SUMIFS('Raw Data'!$L:$L,'Raw Data'!$B:$B,$B$2,'Raw Data'!$J:$J,E$2,'Raw Data'!$K:$K,"native",'Raw Data'!$H:$H,"Off Us",'Raw Data'!$I:$I,"",'Raw Data'!$M:$M,"JOD") -> 85800000 | F75: =SUMIFS('Raw Data'!$L:$L,'Raw Data'!$B:$B,$B$2,'Raw Data'!$J:$J,F$2,'Raw Data'!$K:$K,"native",'Raw Data'!$H:$H,"Off Us",'Raw Data'!$I:$I,"",'Raw Data'!$M:$M,"JOD") -> 93800000 | G75: =SUMIFS('Raw Data'!$L:$L,'Raw Data'!$B:$B,$B$2,'Raw Data'!$J:$J,G$2,'Raw Data'!$K:$K,"native",'Raw Data'!$H:$H,"Off Us",'Raw Data'!$I:$I,"",'Raw Data'!$M:$M,"JOD") -> 90400000 | H75: =SUMIFS('Raw Data'!$L:$L,'Raw Data'!$B:$B,$B$2,'Raw Data'!$J:$J,H$2,'Raw Data'!$K:$K,"native",'Raw Data'!$H:$H,"Off Us",'Raw Data'!$I:$I,"",'Raw Data'!$M:$M,"JOD") -> 80050000 | I75: =SUMIFS('Raw Data'!$L:$L,'Raw Data'!$B:$B,$B$2,'Raw Data'!$J:$J,I$2,'Raw Data'!$K:$K,"native",'Raw Data'!$H:$H,"Off Us",'Raw Data'!$I:$I,"",'Raw Data'!$M:$M,"JOD") -> 103400000 | J75: =SUMIFS('Raw Data'!$L:$L,'Raw Data'!$B:$B,$B$2,'Raw Data'!$J:$J,J$2,'Raw Data'!$K:$K,"native",'Raw Data'!$H:$H,"Off Us",'Raw Data'!$I:$I,"",'Raw Data'!$M:$M,"JOD") -> 84700000 | ... Z75: =SUMIFS('Raw Data'!$L:$L,'Raw Data'!$B:$B,$B$2,'Raw Data'!$J:$J,Z$2,'Raw Data'!$K:$K,"native",'Raw Data'!$H:$H,"Off Us",'Raw Data'!$I:$I,"",'Raw Data'!$M:$M,"JOD") -> 110360000
A76: Transactions | B76: On Us | C76: =SUMIFS('Raw Data'!$L:$L,'Raw Data'!$B:$B,$B$2,'Raw Data'!$J:$J,C$2,'Raw Data'!$K:$K,"native",'Raw Data'!$H:$H,"On Us",'Raw Data'!$I:$I,"",'Raw Data'!$M:$M,"JOD") -> 91200000 | D76: =SUMIFS('Raw Data'!$L:$L,'Raw Data'!$B:$B,$B$2,'Raw Data'!$J:$J,D$2,'Raw Data'!$K:$K,"native",'Raw Data'!$H:$H,"On Us",'Raw Data'!$I:$I,"",'Raw Data'!$M:$M,"JOD") -> 88400000 | E76: =SUMIFS('Raw Data'!$L:$L,'Raw Data'!$B:$B,$B$2,'Raw Data'!$J:$J,E$2,'Raw Data'!$K:$K,"native",'Raw Data'!$H:$H,"On Us",'Raw Data'!$I:$I,"",'Raw Data'!$M:$M,"JOD") -> 86800000 | F76: =SUMIFS('Raw Data'!$L:$L,'Raw Data'!$B:$B,$B$2,'Raw Data'!$J:$J,F$2,'Raw Data'!$K:$K,"native",'Raw Data'!$H:$H,"On Us",'Raw Data'!$I:$I,"",'Raw Data'!$M:$M,"JOD") -> 104800000 | G76: =SUMIFS('Raw Data'!$L:$L,'Raw Data'!$B:$B,$B$2,'Raw Data'!$J:$J,G$2,'Raw Data'!$K:$K,"native",'Raw Data'!$H:$H,"On Us",'Raw Data'!$I:$I,"",'Raw Data'!$M:$M,"JOD") -> 101300000 | H76: =SUMIFS('Raw Data'!$L:$L,'Raw Data'!$B:$B,$B$2,'Raw Data'!$J:$J,H$2,'Raw Data'!$K:$K,"native",'Raw Data'!$H:$H,"On Us",'Raw Data'!$I:$I,"",'Raw Data'!$M:$M,"JOD") -> 93430000 | I76: =SUMIFS('Raw Data'!$L:$L,'Raw Data'!$B:$B,$B$2,'Raw Data'!$J:$J,I$2,'Raw Data'!$K:$K,"native",'Raw Data'!$H:$H,"On Us",'Raw Data'!$I:$I,"",'Raw Data'!$M:$M,"JOD") -> 119600000 | J76: =SUMIFS('Raw Data'!$L:$L,'Raw Data'!$B:$B,$B$2,'Raw Data'!$J:$J,J$2,'Raw Data'!$K:$K,"native",'Raw Data'!$H:$H,"On Us",'Raw Data'!$I:$I,"",'Raw Data'!$M:$M,"JOD") -> 102000000 | ... Z76: =SUMIFS('Raw Data'!$L:$L,'Raw Data'!$B:$B,$B$2,'Raw Data'!$J:$J,Z$2,'Raw Data'!$K:$K,"native",'Raw Data'!$H:$H,"On Us",'Raw Data'!$I:$I,"",'Raw Data'!$M:$M,"JOD") -> 161940000

Sheet eFAWATEERcom
A1: eFAWATEER.com (Bill Payments)
A2: Raw Data keys → (system | period) | B2: efawateercom | C2: =RIGHT(C$3,4)&"-"&TEXT(MATCH(LEFT(C$3,3),{"Jan","Feb","Mar","Apr","May","Jun","Jul","Aug","Sep","Oct","Nov","Dec"},0),"00") -> 2024-09 | D2: =RIGHT(D$3,4)&"-"&TEXT(MATCH(LEFT(D$3,3),{"Jan","Feb","Mar","Apr","May","Jun","Jul","Aug","Sep","Oct","Nov","Dec"},0),"00") -> 2024-10 | E2: =RIGHT(E$3,4)&"-"&TEXT(MATCH(LEFT(E$3,3),{"Jan","Feb","Mar","Apr","May","Jun","Jul","Aug","Sep","Oct","Nov","Dec"},0),"00") -> 2024-11 | F2: =RIGHT(F$3,4)&"-"&TEXT(MATCH(LEFT(F$3,3),{"Jan","Feb","Mar","Apr","May","Jun","Jul","Aug","Sep","Oct","Nov","Dec"},0),"00") -> 2024-12 | G2: =RIGHT(G$3,4)&"-"&TEXT(MATCH(LEFT(G$3,3),{"Jan","Feb","Mar","Apr","May","Jun","Jul","Aug","Sep","Oct","Nov","Dec"},0),"00") -> 2025-01 | H2: =RIGHT(H$3,4)&"-"&TEXT(MATCH(LEFT(H$3,3),{"Jan","Feb","Mar","Apr","May","Jun","Jul","Aug","Sep","Oct","Nov","Dec"},0),"00") -> 2025-02 | I2: =RIGHT(I$3,4)&"-"&TEXT(MATCH(LEFT(I$3,3),{"Jan","Feb","Mar","Apr","May","Jun","Jul","Aug","Sep","Oct","Nov","Dec"},0),"00") -> 2025-03 | J2: =RIGHT(J$3,4)&"-"&TEXT(MATCH(LEFT(J$3,3),{"Jan","Feb","Mar","Apr","May","Jun","Jul","Aug","Sep","Oct","Nov","Dec"},0),"00") -> 2025-04 | ... Z2: =RIGHT(Z$3,4)&"-"&TEXT(MATCH(LEFT(Z$3,3),{"Jan","Feb","Mar","Apr","May","Jun","Jul","Aug","Sep","Oct","Nov","Dec"},0),"00") -> 2026-08
A3: Category | B3: Metric | C3: Sep 2024 | D3: Oct 2024 | E3: Nov 2024 | F3: Dec 2024 | G3: Jan 2025 | H3: Feb 2025 | I3: Mar 2025 | J3: Apr 2025 | K3: May 2025 | L3: Jun 2025 | M3: Jul 2025 | N3: Aug 2025 | O3: Sep 2025 | P3: Oct 2025 | Q3: Nov 2025 | R3: Dec 2025 | S3: Jan 2026 | T3: Feb 2026 | U3: Mar 2026 | V3: Apr 2026 | W3: May 2026 | X3: Jun 2026 | Y3: Jul 2026 | Z3: Aug 2026
A4: USERS BY USER STATUS (Number)
A5: Users | B5: Existing Users | C5: =SUMIFS('Raw Data'!$L:$L,'Raw Data'!$B:$B,$B$2,'Raw Data'!$J:$J,C$2,'Raw Data'!$K:$K,"native",'Raw Data'!$H:$H,"Existing Users",'Raw Data'!$I:$I,"",'Raw Data'!$M:$M,"count") -> 4390000 | D5: =SUMIFS('Raw Data'!$L:$L,'Raw Data'!$B:$B,$B$2,'Raw Data'!$J:$J,D$2,'Raw Data'!$K:$K,"native",'Raw Data'!$H:$H,"Existing Users",'Raw Data'!$I:$I,"",'Raw Data'!$M:$M,"count") -> 4430000 | E5: =SUMIFS('Raw Data'!$L:$L,'Raw Data'!$B:$B,$B$2,'Raw Data'!$J:$J,E$2,'Raw Data'!$K:$K,"native",'Raw Data'!$H:$H,"Existing Users",'Raw Data'!$I:$I,"",'Raw Data'!$M:$M,"count") -> 4470000 | F5: =SUMIFS('Raw Data'!$L:$L,'Raw Data'!$B:$B,$B$2,'Raw Data'!$J:$J,F$2,'Raw Data'!$K:$K,"native",'Raw Data'!$H:$H,"Existing Users",'Raw Data'!$I:$I,"",'Raw Data'!$M:$M,"count") -> 4500000 | G5: =SUMIFS('Raw Data'!$L:$L,'Raw Data'!$B:$B,$B$2,'Raw Data'!$J:$J,G$2,'Raw Data'!$K:$K,"native",'Raw Data'!$H:$H,"Existing Users",'Raw Data'!$I:$I,"",'Raw Data'!$M:$M,"count") -> 4540000 | H5: =SUMIFS('Raw Data'!$L:$L,'Raw Data'!$B:$B,$B$2,'Raw Data'!$J:$J,H$2,'Raw Data'!$K:$K,"native",'Raw Data'!$H:$H,"Existing Users",'Raw Data'!$I:$I,"",'Raw Data'!$M:$M,"count") -> 4580000 | I5: =SUMIFS('Raw Data'!$L:$L,'Raw Data'!$B:$B,$B$2,'Raw Data'!$J:$J,I$2,'Raw Data'!$K:$K,"native",'Raw Data'!$H:$H,"Existing Users",'Raw Data'!$I:$I,"",'Raw Data'!$M:$M,"count") -> 4620000 | J5: =SUMIFS('Raw Data'!$L:$L,'Raw Data'!$B:$B,$B$2,'Raw Data'!$J:$J,J$2,'Raw Data'!$K:$K,"native",'Raw Data'!$H:$H,"Existing Users",'Raw Data'!$I:$I,"",'Raw Data'!$M:$M,"count") -> 4650000 | ... Z5: =SUMIFS('Raw Data'!$L:$L,'Raw Data'!$B:$B,$B$2,'Raw Data'!$J:$J,Z$2,'Raw Data'!$K:$K,"native",'Raw Data'!$H:$H,"Existing Users",'Raw Data'!$I:$I,"",'Raw Data'!$M:$M,"count") -> 5340000
A6: Users | B6: New Users | C6: =SUMIFS('Raw Data'!$L:$L,'Raw Data'!$B:$B,$B$2,'Raw Data'!$J:$J,C$2,'Raw Data'!$K:$K,"native",'Raw Data'!$H:$H,"New Users",'Raw Data'!$I:$I,"",'Raw Data'!$M:$M,"count") -> 38800 | D6: =SUMIFS('Raw Data'!$L:$L,'Raw Data'!$B:$B,$B$2,'Raw Data'!$J:$J,D$2,'Raw Data'!$K:$K,"native",'Raw Data'!$H:$H,"New Users",'Raw Data'!$I:$I,"",'Raw Data'!$M:$M,"count") -> 40600 | E6: =SUMIFS('Raw Data'!$L:$L,'Raw Data'!$B:$B,$B$2,'Raw Data'!$J:$J,E$2,'Raw Data'!$K:$K,"native",'Raw Data'!$H:$H,"New Users",'Raw Data'!$I:$I,"",'Raw Data'!$M:$M,"count") -> 34400 | F6: =SUMIFS('Raw Data'!$L:$L,'Raw Data'!$B:$B,$B$2,'Raw Data'!$J:$J,F$2,'Raw Data'!$K:$K,"native",'Raw Data'!$H:$H,"New Users",'Raw Data'!$I:$I,"",'Raw Data'!$M:$M,"count") -> 38100 | G6: =SUMIFS('Raw Data'!$L:$L,'Raw Data'!$B:$B,$B$2,'Raw Data'!$J:$J,G$2,'Raw Data'!$K:$K,"native",'Raw Data'!$H:$H,"New Users",'Raw Data'!$I:$I,"",'Raw Data'!$M:$M,"count") -> 37100 | H6: =SUMIFS('Raw Data'!$L:$L,'Raw Data'!$B:$B,$B$2,'Raw Data'!$J:$J,H$2,'Raw Data'!$K:$K,"native",'Raw Data'!$H:$H,"New Users",'Raw Data'!$I:$I,"",'Raw Data'!$M:$M,"count") -> 37900 | I6: =SUMIFS('Raw Data'!$L:$L,'Raw Data'!$B:$B,$B$2,'Raw Data'!$J:$J,I$2,'Raw Data'!$K:$K,"native",'Raw Data'!$H:$H,"New Users",'Raw Data'!$I:$I,"",'Raw Data'!$M:$M,"count") -> 35500 | J6: =SUMIFS('Raw Data'!$L:$L,'Raw Data'!$B:$B,$B$2,'Raw Data'!$J:$J,J$2,'Raw Data'!$K:$K,"native",'Raw Data'!$H:$H,"New Users",'Raw Data'!$I:$I,"",'Raw Data'!$M:$M,"count") -> 34200 | ... Z6: =SUMIFS('Raw Data'!$L:$L,'Raw Data'!$B:$B,$B$2,'Raw Data'!$J:$J,Z$2,'Raw Data'!$K:$K,"native",'Raw Data'!$H:$H,"New Users",'Raw Data'!$I:$I,"",'Raw Data'!$M:$M,"count") -> 53280
A7: TRANSACTIONS BY BILLER CATEGORY (Number)
A8: Transactions | B8: Associations and Organizations | C8: =SUMIFS('Raw Data'!$L:$L,'Raw Data'!$B:$B,$B$2,'Raw Data'!$J:$J,C$2,'Raw Data'!$K:$K,"native",'Raw Data'!$H:$H,"Associations and Organizations",'Raw Data'!$I:$I,"",'Raw Data'!$M:$M,"count") -> 30000 | D8: =SUMIFS('Raw Data'!$L:$L,'Raw Data'!$B:$B,$B$2,'Raw Data'!$J:$J,D$2,'Raw Data'!$K:$K,"native",'Raw Data'!$H:$H,"Associations and Organizations",'Raw Data'!$I:$I,"",'Raw Data'!$M:$M,"count") -> 32000 | E8: =SUMIFS('Raw Data'!$L:$L,'Raw Data'!$B:$B,$B$2,'Raw Data'!$J:$J,E$2,'Raw Data'!$K:$K,"native",'Raw Data'!$H:$H,"Associations and Organizations",'Raw Data'!$I:$I,"",'Raw Data'!$M:$M,"count") -> 30000 | F8: =SUMIFS('Raw Data'!$L:$L,'Raw Data'!$B:$B,$B$2,'Raw Data'!$J:$J,F$2,'Raw Data'!$K:$K,"native",'Raw Data'!$H:$H,"Associations and Organizations",'Raw Data'!$I:$I,"",'Raw Data'!$M:$M,"count") -> 36000 | G8: =SUMIFS('Raw Data'!$L:$L,'Raw Data'!$B:$B,$B$2,'Raw Data'!$J:$J,G$2,'Raw Data'!$K:$K,"native",'Raw Data'!$H:$H,"Associations and Organizations",'Raw Data'!$I:$I,"",'Raw Data'!$M:$M,"count") -> 60000 | H8: =SUMIFS('Raw Data'!$L:$L,'Raw Data'!$B:$B,$B$2,'Raw Data'!$J:$J,H$2,'Raw Data'!$K:$K,"native",'Raw Data'!$H:$H,"Associations and Organizations",'Raw Data'!$I:$I,"",'Raw Data'!$M:$M,"count") -> 46000 | I8: =SUMIFS('Raw Data'!$L:$L,'Raw Data'!$B:$B,$B$2,'Raw Data'!$J:$J,I$2,'Raw Data'!$K:$K,"native",'Raw Data'!$H:$H,"Associations and Organizations",'Raw Data'!$I:$I,"",'Raw Data'!$M:$M,"count") -> 39000 | J8: =SUMIFS('Raw Data'!$L:$L,'Raw Data'!$B:$B,$B$2,'Raw Data'!$J:$J,J$2,'Raw Data'!$K:$K,"native",'Raw Data'!$H:$H,"Associations and Organizations",'Raw Data'!$I:$I,"",'Raw Data'!$M:$M,"count") -> 39000 | ... Z8: =SUMIFS('Raw Data'!$L:$L,'Raw Data'!$B:$B,$B$2,'Raw Data'!$J:$J,Z$2,'Raw Data'!$K:$K,"native",'Raw Data'!$H:$H,"Associations and Organizations",'Raw Data'!$I:$I,"",'Raw Data'!$M:$M,"count") -> 39000
A9: Transactions | B9: Education | C9: =SUMIFS('Raw Data'!$L:$L,'Raw Data'!$B:$B,$B$2,'Raw Data'!$J:$J,C$2,'Raw Data'!$K:$K,"native",'Raw Data'!$H:$H,"Education",'Raw Data'!$I:$I,"",'Raw Data'!$M:$M,"count") -> 177000 | D9: =SUMIFS('Raw Data'!$L:$L,'Raw Data'!$B:$B,$B$2,'Raw Data'!$J:$J,D$2,'Raw Data'!$K:$K,"native",'Raw Data'!$H:$H,"Education",'Raw Data'!$I:$I,"",'Raw Data'!$M:$M,"count") -> 135000 | E9: =SUMIFS('Raw Data'!$L:$L,'Raw Data'!$B:$B,$B$2,'Raw Data'!$J:$J,E$2,'Raw Data'!$K:$K,"native",'Raw Data'!$H:$H,"Education",'Raw Data'!$I:$I,"",'Raw Data'!$M:$M,"count") -> 41000 | F9: =SUMIFS('Raw Data'!$L:$L,'Raw Data'!$B:$B,$B$2,'Raw Data'!$J:$J,F$2,'Raw Data'!$K:$K,"native",'Raw Data'!$H:$H,"Education",'Raw Data'!$I:$I,"",'Raw Data'!$M:$M,"count") -> 116000 | G9: =SUMIFS('Raw Data'!$L:$L,'Raw Data'!$B:$B,$B$2,'Raw Data'!$J:$J,G$2,'Raw Data'!$K:$K,"native",'Raw Data'!$H:$H,"Education",'Raw Data'!$I:$I,"",'Raw Data'!$M:$M,"count") -> 95000 | H9: =SUMIFS('Raw Data'!$L:$L,'Raw Data'!$B:$B,$B$2,'Raw Data'!$J:$J,H$2,'Raw Data'!$K:$K,"native",'Raw Data'!$H:$H,"Education",'Raw Data'!$I:$I,"",'Raw Data'!$M:$M,"count") -> 210000 | I9: =SUMIFS('Raw Data'!$L:$L,'Raw Data'!$B:$B,$B$2,'Raw Data'!$J:$J,I$2,'Raw Data'!$K:$K,"native",'Raw Data'!$H:$H,"Education",'Raw Data'!$I:$I,"",'Raw Data'!$M:$M,"count") -> 51000 | J9: =SUMIFS('Raw Data'!$L:$L,'Raw Data'!$B:$B,$B$2,'Raw Data'!$J:$J,J$2,'Raw Data'!$K:$K,"native",'Raw Data'!$H:$H,"Education",'Raw Data'!$I:$I,"",'Raw Data'!$M:$M,"count") -> 79000 | ... Z9: =SUMIFS('Raw Data'!$L:$L,'Raw Data'!$B:$B,$B$2,'Raw Data'!$J:$J,Z$2,'Raw Data'!$K:$K,"native",'Raw Data'!$H:$H,"Education",'Raw Data'!$I:$I,"",'Raw Data'!$M:$M,"count") -> 197000
A10: Transactions | B10: Financial Services | C10: =SUMIFS('Raw Data'!$L:$L,'Raw Data'!$B:$B,$B$2,'Raw Data'!$J:$J,C$2,'Raw Data'!$K:$K,"native",'Raw Data'!$H:$H,"Financial Services",'Raw Data'!$I:$I,"",'Raw Data'!$M:$M,"count") -> 302000 | D10: =SUMIFS('Raw Data'!$L:$L,'Raw Data'!$B:$B,$B$2,'Raw Data'!$J:$J,D$2,'Raw Data'!$K:$K,"native",'Raw Data'!$H:$H,"Financial Services",'Raw Data'!$I:$I,"",'Raw Data'!$M:$M,"count") -> 313000 | E10: =SUMIFS('Raw Data'!$L:$L,'Raw Data'!$B:$B,$B$2,'Raw Data'!$J:$J,E$2,'Raw Data'!$K:$K,"native",'Raw Data'!$H:$H,"Financial Services",'Raw Data'!$I:$I,"",'Raw Data'!$M:$M,"count") -> 283000 | F10: =SUMIFS('Raw Data'!$L:$L,'Raw Data'!$B:$B,$B$2,'Raw Data'!$J:$J,F$2,'Raw Data'!$K:$K,"native",'Raw Data'!$H:$H,"Financial Services",'Raw Data'!$I:$I,"",'Raw Data'!$M:$M,"count") -> 321000 | G10: =SUMIFS('Raw Data'!$L:$L,'Raw Data'!$B:$B,$B$2,'Raw Data'!$J:$J,G$2,'Raw Data'!$K:$K,"native",'Raw Data'!$H:$H,"Financial Services",'Raw Data'!$I:$I,"",'Raw Data'!$M:$M,"count") -> 295000 | H10: =SUMIFS('Raw Data'!$L:$L,'Raw Data'!$B:$B,$B$2,'Raw Data'!$J:$J,H$2,'Raw Data'!$K:$K,"native",'Raw Data'!$H:$H,"Financial Services",'Raw Data'!$I:$I,"",'Raw Data'!$M:$M,"count") -> 286000 | I10: =SUMIFS('Raw Data'!$L:$L,'Raw Data'!$B:$B,$B$2,'Raw Data'!$J:$J,I$2,'Raw Data'!$K:$K,"native",'Raw Data'!$H:$H,"Financial Services",'Raw Data'!$I:$I,"",'Raw Data'!$M:$M,"count") -> 287000 | J10: =SUMIFS('Raw Data'!$L:$L,'Raw Data'!$B:$B,$B$2,'Raw Data'!$J:$J,J$2,'Raw Data'!$K:$K,"native",'Raw Data'!$H:$H,"Financial Services",'Raw Data'!$I:$I,"",'Raw Data'!$M:$M,"count") -> 383000 | ... Z10: =SUMIFS('Raw Data'!$L:$L,'Raw Data'!$B:$B,$B$2,'Raw Data'!$J:$J,Z$2,'Raw Data'!$K:$K,"native",'Raw Data'!$H:$H,"Financial Services",'Raw Data'!$I:$I,"",'Raw Data'!$M:$M,"count") -> 317000
A11: Transactions | B11: Gas And Energy | C11: =SUMIFS('Raw Data'!$L:$L,'Raw Data'!$B:$B,$B$2,'Raw Data'!$J:$J,C$2,'Raw Data'!$K:$K,"native",'Raw Data'!$H:$H,"Gas And Energy",'Raw Data'!$I:$I,"",'Raw Data'!$M:$M,"count") -> 26000 | D11: =SUMIFS('Raw Data'!$L:$L,'Raw Data'!$B:$B,$B$2,'Raw Data'!$J:$J,D$2,'Raw Data'!$K:$K,"native",'Raw Data'!$H:$H,"Gas And Energy",'Raw Data'!$I:$I,"",'Raw Data'!$M:$M,"count") -> 27000 | E11: =SUMIFS('Raw Data'!$L:$L,'Raw Data'!$B:$B,$B$2,'Raw Data'!$J:$J,E$2,'Raw Data'!$K:$K,"native",'Raw Data'!$H:$H,"Gas And Energy",'Raw Data'!$I:$I,"",'Raw Data'!$M:$M,"count") -> 24000 | F11: =SUMIFS('Raw Data'!$L:$L,'Raw Data'!$B:$B,$B$2,'Raw Data'!$J:$J,F$2,'Raw Data'!$K:$K,"native",'Raw Data'!$H:$H,"Gas And Energy",'Raw Data'!$I:$I,"",'Raw Data'!$M:$M,"count") -> 31000 | G11: =SUMIFS('Raw Data'!$L:$L,'Raw Data'!$B:$B,$B$2,'Raw Data'!$J:$J,G$2,'Raw Data'!$K:$K,"native",'Raw Data'!$H:$H,"Gas And Energy",'Raw Data'!$I:$I,"",'Raw Data'!$M:$M,"count") -> 29000 | H11: =SUMIFS('Raw Data'!$L:$L,'Raw Data'!$B:$B,$B$2,'Raw Data'!$J:$J,H$2,'Raw Data'!$K:$K,"native",'Raw Data'!$H:$H,"Gas And Energy",'Raw Data'!$I:$I,"",'Raw Data'!$M:$M,"count") -> 28000 | J11: =SUMIFS('Raw Data'!$L:$L,'Raw Data'!$B:$B,$B$2,'Raw Data'!$J:$J,J$2,'Raw Data'!$K:$K,"native",'Raw Data'!$H:$H,"Gas And Energy",'Raw Data'!$I:$I,"",'Raw Data'!$M:$M,"count") -> 31000 | K11: =SUMIFS('Raw Data'!$L:$L,'Raw Data'!$B:$B,$B$2,'Raw Data'!$J:$J,K$2,'Raw Data'!$K:$K,"native",'Raw Data'!$H:$H,"Gas And Energy",'Raw Data'!$I:$I,"",'Raw Data'!$M:$M,"count") -> 26000 | L11: =SUMIFS('Raw Data'!$L:$L,'Raw Data'!$B:$B,$B$2,'Raw Data'!$J:$J,L$2,'Raw Data'!$K:$K,"native",'Raw Data'!$H:$H,"Gas And Energy",'Raw Data'!$I:$I,"",'Raw Data'!$M:$M,"count") -> 29000 | M11: =SUMIFS('Raw Data'!$L:$L,'Raw Data'!$B:$B,$B$2,'Raw Data'!$J:$J,M$2,'Raw Data'!$K:$K,"native",'Raw Data'!$H:$H,"Gas And Energy",'Raw Data'!$I:$I,"",'Raw Data'!$M:$M,"count") -> 33000 | N11: =SUMIFS('Raw Data'!$L:$L,'Raw Data'!$B:$B,$B$2,'Raw Data'!$J:$J,N$2,'Raw Data'!$K:$K,"native",'Raw Data'!$H:$H,"Gas And Energy",'Raw Data'!$I:$I,"",'Raw Data'!$M:$M,"count") -> 33000 | O11: =SUMIFS('Raw Data'!$L:$L,'Raw Data'!$B:$B,$B$2,'Raw Data'!$J:$J,O$2,'Raw Data'!$K:$K,"native",'Raw Data'!$H:$H,"Gas And Energy",'Raw Data'!$I:$I,"",'Raw Data'!$M:$M,"count") -> 33000 | P11: =SUMIFS('Raw Data'!$L:$L,'Raw Data'!$B:$B,$B$2,'Raw Data'!$J:$J,P$2,'Raw Data'!$K:$K,"native",'Raw Data'!$H:$H,"Gas And Energy",'Raw Data'!$I:$I,"",'Raw Data'!$M:$M,"count") -> 34000 | Q11: =SUMIFS('Raw Data'!$L:$L,'Raw Data'!$B:$B,$B$2,'Raw Data'!$J:$J,Q$2,'Raw Data'!$K:$K,"native",'Raw Data'!$H:$H,"Gas And Energy",'Raw Data'!$I:$I,"",'Raw Data'!$M:$M,"count") -> 35000 | ... Z11: =SUMIFS('Raw Data'!$L:$L,'Raw Data'!$B:$B,$B$2,'Raw Data'!$J:$J,Z$2,'Raw Data'!$K:$K,"native",'Raw Data'!$H:$H,"Gas And Energy",'Raw Data'!$I:$I,"",'Raw Data'!$M:$M,"count") -> 41000
A12: Transactions | B12: Government Service | C12: =SUMIFS('Raw Data'!$L:$L,'Raw Data'!$B:$B,$B$2,'Raw Data'!$J:$J,C$2,'Raw Data'!$K:$K,"native",'Raw Data'!$H:$H,"Government Service",'Raw Data'!$I:$I,"",'Raw Data'!$M:$M,"count") -> 1099000 | D12: =SUMIFS('Raw Data'!$L:$L,'Raw Data'!$B:$B,$B$2,'Raw Data'!$J:$J,D$2,'Raw Data'!$K:$K,"native",'Raw Data'!$H:$H,"Government Service",'Raw Data'!$I:$I,"",'Raw Data'!$M:$M,"count") -> 1195000 | E12: =SUMIFS('Raw Data'!$L:$L,'Raw Data'!$B:$B,$B$2,'Raw Data'!$J:$J,E$2,'Raw Data'!$K:$K,"native",'Raw Data'!$H:$H,"Government Service",'Raw Data'!$I:$I,"",'Raw Data'!$M:$M,"count") -> 954000 | F12: =SUMIFS('Raw Data'!$L:$L,'Raw Data'!$B:$B,$B$2,'Raw Data'!$J:$J,F$2,'Raw Data'!$K:$K,"native",'Raw Data'!$H:$H,"Government Service",'Raw Data'!$I:$I,"",'Raw Data'!$M:$M,"count") -> 1218000 | G12: =SUMIFS('Raw Data'!$L:$L,'Raw Data'!$B:$B,$B$2,'Raw Data'!$J:$J,G$2,'Raw Data'!$K:$K,"native",'Raw Data'!$H:$H,"Government Service",'Raw Data'!$I:$I,"",'Raw Data'!$M:$M,"count") -> 1309000 | H12: =SUMIFS('Raw Data'!$L:$L,'Raw Data'!$B:$B,$B$2,'Raw Data'!$J:$J,H$2,'Raw Data'!$K:$K,"native",'Raw Data'!$H:$H,"Government Service",'Raw Data'!$I:$I,"",'Raw Data'!$M:$M,"count") -> 1179000 | I12: =SUMIFS('Raw Data'!$L:$L,'Raw Data'!$B:$B,$B$2,'Raw Data'!$J:$J,I$2,'Raw Data'!$K:$K,"native",'Raw Data'!$H:$H,"Government Service",'Raw Data'!$I:$I,"",'Raw Data'!$M:$M,"count") -> 974000 | J12: =SUMIFS('Raw Data'!$L:$L,'Raw Data'!$B:$B,$B$2,'Raw Data'!$J:$J,J$2,'Raw Data'!$K:$K,"native",'Raw Data'!$H:$H,"Government Service",'Raw Data'!$I:$I,"",'Raw Data'!$M:$M,"count") -> 1165000 | ... Z12: =SUMIFS('Raw Data'!$L:$L,'Raw Data'!$B:$B,$B$2,'Raw Data'!$J:$J,Z$2,'Raw Data'!$K:$K,"native",'Raw Data'!$H:$H,"Government Service",'Raw Data'!$I:$I,"",'Raw Data'!$M:$M,"count") -> 2010000
A13: Transactions | B13: Telecommunication | C13: =SUMIFS('Raw Data'!$L:$L,'Raw Data'!$B:$B,$B$2,'Raw Data'!$J:$J,C$2,'Raw Data'!$K:$K,"native",'Raw Data'!$H:$H,"Telecommunication",'Raw Data'!$I:$I,"",'Raw Data'!$M:$M,"count") -> 1959000 | D13: =SUMIFS('Raw Data'!$L:$L,'Raw Data'!$B:$B,$B$2,'Raw Data'!$J:$J,D$2,'Raw Data'!$K:$K,"native",'Raw Data'!$H:$H,"Telecommunication",'Raw Data'!$I:$I,"",'Raw Data'!$M:$M,"count") -> 1927000 | E13: =SUMIFS('Raw Data'!$L:$L,'Raw Data'!$B:$B,$B$2,'Raw Data'!$J:$J,E$2,'Raw Data'!$K:$K,"native",'Raw Data'!$H:$H,"Telecommunication",'Raw Data'!$I:$I,"",'Raw Data'!$M:$M,"count") -> 1732000 | F13: =SUMIFS('Raw Data'!$L:$L,'Raw Data'!$B:$B,$B$2,'Raw Data'!$J:$J,F$2,'Raw Data'!$K:$K,"native",'Raw Data'!$H:$H,"Telecommunication",'Raw Data'!$I:$I,"",'Raw Data'!$M:$M,"count") -> 2082000 | G13: =SUMIFS('Raw Data'!$L:$L,'Raw Data'!$B:$B,$B$2,'Raw Data'!$J:$J,G$2,'Raw Data'!$K:$K,"native",'Raw Data'!$H:$H,"Telecommunication",'Raw Data'!$I:$I,"",'Raw Data'!$M:$M,"count") -> 1846000 | H13: =SUMIFS('Raw Data'!$L:$L,'Raw Data'!$B:$B,$B$2,'Raw Data'!$J:$J,H$2,'Raw Data'!$K:$K,"native",'Raw Data'!$H:$H,"Telecommunication",'Raw Data'!$I:$I,"",'Raw Data'!$M:$M,"count") -> 1770000 | I13: =SUMIFS('Raw Data'!$L:$L,'Raw Data'!$B:$B,$B$2,'Raw Data'!$J:$J,I$2,'Raw Data'!$K:$K,"native",'Raw Data'!$H:$H,"Telecommunication",'Raw Data'!$I:$I,"",'Raw Data'!$M:$M,"count") -> 1847000 | J13: =SUMIFS('Raw Data'!$L:$L,'Raw Data'!$B:$B,$B$2,'Raw Data'!$J:$J,J$2,'Raw Data'!$K:$K,"native",'Raw Data'!$H:$H,"Telecommunication",'Raw Data'!$I:$I,"",'Raw Data'!$M:$M,"count") -> 2215000 | ... Z13: =SUMIFS('Raw Data'!$L:$L,'Raw Data'!$B:$B,$B$2,'Raw Data'!$J:$J,Z$2,'Raw Data'!$K:$K,"native",'Raw Data'!$H:$H,"Telecommunication",'Raw Data'!$I:$I,"",'Raw Data'!$M:$M,"count") -> 2300000
A14: Transactions | B14: Trading and Services | C14: =SUMIFS('Raw Data'!$L:$L,'Raw Data'!$B:$B,$B$2,'Raw Data'!$J:$J,C$2,'Raw Data'!$K:$K,"native",'Raw Data'!$H:$H,"Trading and Services",'Raw Data'!$I:$I,"",'Raw Data'!$M:$M,"count") -> 36000 | D14: =SUMIFS('Raw Data'!$L:$L,'Raw Data'!$B:$B,$B$2,'Raw Data'!$J:$J,D$2,'Raw Data'!$K:$K,"native",'Raw Data'!$H:$H,"Trading and Services",'Raw Data'!$I:$I,"",'Raw Data'!$M:$M,"count") -> 33000 | E14: =SUMIFS('Raw Data'!$L:$L,'Raw Data'!$B:$B,$B$2,'Raw Data'!$J:$J,E$2,'Raw Data'!$K:$K,"native",'Raw Data'!$H:$H,"Trading and Services",'Raw Data'!$I:$I,"",'Raw Data'!$M:$M,"count") -> 31000 | F14: =SUMIFS('Raw Data'!$L:$L,'Raw Data'!$B:$B,$B$2,'Raw Data'!$J:$J,F$2,'Raw Data'!$K:$K,"native",'Raw Data'!$H:$H,"Trading and Services",'Raw Data'!$I:$I,"",'Raw Data'!$M:$M,"count") -> 50000 | G14: =SUMIFS('Raw Data'!$L:$L,'Raw Data'!$B:$B,$B$2,'Raw Data'!$J:$J,G$2,'Raw Data'!$K:$K,"native",'Raw Data'!$H:$H,"Trading and Services",'Raw Data'!$I:$I,"",'Raw Data'!$M:$M,"count") -> 35000 | H14: =SUMIFS('Raw Data'!$L:$L,'Raw Data'!$B:$B,$B$2,'Raw Data'!$J:$J,H$2,'Raw Data'!$K:$K,"native",'Raw Data'!$H:$H,"Trading and Services",'Raw Data'!$I:$I,"",'Raw Data'!$M:$M,"count") -> 31000 | I14: =SUMIFS('Raw Data'!$L:$L,'Raw Data'!$B:$B,$B$2,'Raw Data'!$J:$J,I$2,'Raw Data'!$K:$K,"native",'Raw Data'!$H:$H,"Trading and Services",'Raw Data'!$I:$I,"",'Raw Data'!$M:$M,"count") -> 30000 | J14: =SUMIFS('Raw Data'!$L:$L,'Raw Data'!$B:$B,$B$2,'Raw Data'!$J:$J,J$2,'Raw Data'!$K:$K,"native",'Raw Data'!$H:$H,"Trading and Services",'Raw Data'!$I:$I,"",'Raw Data'!$M:$M,"count") -> 35000 | ... T14: =SUMIFS('Raw Data'!$L:$L,'Raw Data'!$B:$B,$B$2,'Raw Data'!$J:$J,T$2,'Raw Data'!$K:$K,"native",'Raw Data'!$H:$H,"Trading and Services",'Raw Data'!$I:$I,"",'Raw Data'!$M:$M,"count") -> 26000 | V14: =SUMIFS('Raw Data'!$L:$L,'Raw Data'!$B:$B,$B$2,'Raw Data'!$J:$J,V$2,'Raw Data'!$K:$K,"native",'Raw Data'!$H:$H,"Trading and Services",'Raw Data'!$I:$I,"",'Raw Data'!$M:$M,"count") -> 29000 | W14: =SUMIFS('Raw Data'!$L:$L,'Raw Data'!$B:$B,$B$2,'Raw Data'!$J:$J,W$2,'Raw Data'!$K:$K,"native",'Raw Data'!$H:$H,"Trading and Services",'Raw Data'!$I:$I,"",'Raw Data'!$M:$M,"count") -> 27000 | X14: =SUMIFS('Raw Data'!$L:$L,'Raw Data'!$B:$B,$B$2,'Raw Data'!$J:$J,X$2,'Raw Data'!$K:$K,"native",'Raw Data'!$H:$H,"Trading and Services",'Raw Data'!$I:$I,"",'Raw Data'!$M:$M,"count") -> 33000 | Y14: =SUMIFS('Raw Data'!$L:$L,'Raw Data'!$B:$B,$B$2,'Raw Data'!$J:$J,Y$2,'Raw Data'!$K:$K,"native",'Raw Data'!$H:$H,"Trading and Services",'Raw Data'!$I:$I,"",'Raw Data'!$M:$M,"count") -> 36000 | Z14: =SUMIFS('Raw Data'!$L:$L,'Raw Data'!$B:$B,$B$2,'Raw Data'!$J:$J,Z$2,'Raw Data'!$K:$K,"native",'Raw Data'!$H:$H,"Trading and Services",'Raw Data'!$I:$I,"",'Raw Data'!$M:$M,"count") -> 38000
A15: Transactions | B15: Travel & Transportation | C15: =SUMIFS('Raw Data'!$L:$L,'Raw Data'!$B:$B,$B$2,'Raw Data'!$J:$J,C$2,'Raw Data'!$K:$K,"native",'Raw Data'!$H:$H,"Travel & Transportation",'Raw Data'!$I:$I,"",'Raw Data'!$M:$M,"count") -> 41000 | D15: =SUMIFS('Raw Data'!$L:$L,'Raw Data'!$B:$B,$B$2,'Raw Data'!$J:$J,D$2,'Raw Data'!$K:$K,"native",'Raw Data'!$H:$H,"Travel & Transportation",'Raw Data'!$I:$I,"",'Raw Data'!$M:$M,"count") -> 43000 | E15: =SUMIFS('Raw Data'!$L:$L,'Raw Data'!$B:$B,$B$2,'Raw Data'!$J:$J,E$2,'Raw Data'!$K:$K,"native",'Raw Data'!$H:$H,"Travel & Transportation",'Raw Data'!$I:$I,"",'Raw Data'!$M:$M,"count") -> 40000 | F15: =SUMIFS('Raw Data'!$L:$L,'Raw Data'!$B:$B,$B$2,'Raw Data'!$J:$J,F$2,'Raw Data'!$K:$K,"native",'Raw Data'!$H:$H,"Travel & Transportation",'Raw Data'!$I:$I,"",'Raw Data'!$M:$M,"count") -> 46000 | G15: =SUMIFS('Raw Data'!$L:$L,'Raw Data'!$B:$B,$B$2,'Raw Data'!$J:$J,G$2,'Raw Data'!$K:$K,"native",'Raw Data'!$H:$H,"Travel & Transportation",'Raw Data'!$I:$I,"",'Raw Data'!$M:$M,"count") -> 42000 | H15: =SUMIFS('Raw Data'!$L:$L,'Raw Data'!$B:$B,$B$2,'Raw Data'!$J:$J,H$2,'Raw Data'!$K:$K,"native",'Raw Data'!$H:$H,"Travel & Transportation",'Raw Data'!$I:$I,"",'Raw Data'!$M:$M,"count") -> 38000 | I15: =SUMIFS('Raw Data'!$L:$L,'Raw Data'!$B:$B,$B$2,'Raw Data'!$J:$J,I$2,'Raw Data'!$K:$K,"native",'Raw Data'!$H:$H,"Travel & Transportation",'Raw Data'!$I:$I,"",'Raw Data'!$M:$M,"count") -> 43000 | J15: =SUMIFS('Raw Data'!$L:$L,'Raw Data'!$B:$B,$B$2,'Raw Data'!$J:$J,J$2,'Raw Data'!$K:$K,"native",'Raw Data'!$H:$H,"Travel & Transportation",'Raw Data'!$I:$I,"",'Raw Data'!$M:$M,"count") -> 54000 | ... Z15: =SUMIFS('Raw Data'!$L:$L,'Raw Data'!$B:$B,$B$2,'Raw Data'!$J:$J,Z$2,'Raw Data'!$K:$K,"native",'Raw Data'!$H:$H,"Travel & Transportation",'Raw Data'!$I:$I,"",'Raw Data'!$M:$M,"count") -> 75000
